Workbook

Sheet MOQ
A1: MRP BAUMON
A2: Qtd | B2: Produto | C2: Código Bemol | D2: DESCRIÇÃO | E2: MOQ Mínimo | F2: Produtos por caixa Master Box | G2: Quantidade de Caixa Master | H2: CBM por Caixa Master | I2: CBM Total
A3: 1 | C3: 238697 | D3: FRITAD BAUMON AIR FRYER 35L YJ-613D PT | E3: 1500 | F3: 2 | G3: =E3/F3 -> 750 | H3: 0.064 | I3: =H3*G3 -> 48
A4: 2 | C4: 238698 | D4: FRITAD BAUMON AIR FRYER 12L GSE021 PT | E4: 700 | F4: 1 | G4: =E4/F4 -> 700 | H4: 0.063 | I4: =H4*G4 -> 44.1
A5: 3 | C5: 238699 | D5: CAFETEIRA BAUMON 108TS PT/PR | E5: 1800 | F5: 4 | G5: =E5/F5 -> 450 | H5: 0.073 | I5: =H5*G5 -> 32.85
A6: 4 | C6: 238700 | D6: SANDUICHEIRA BAUMON FS-8009C PT | E6: 2004 | F6: 6 | G6: =E6/F6 -> 334 | H6: 0.041 | I6: =H6*G6 -> 13.694
A7: 5 | C7: 238721 | D7: GRILL BAUMON 9228D PT | E7: 2010 | F7: 6 | G7: =E7/F7 -> 335 | H7: 0.068 | I7: =H7*G7 -> 22.78
A8: 6 | C8: 238722 | D8: FERRO BAUMON SECO LM-209A AZ | E8: 2604 | F8: 12 | G8: =E8/F8 -> 217 | H8: 0.046 | I8: =H8*G8 -> 9.982
A9: 7 | C9: 238723 | D9: FERRO BAUMON VAPOR LM-2262 AZ | E9: 2450 | F9: 10 | G9: =E9/F9 -> 245 | H9: 0.046 | I9: =H9*G9 -> 11.27
A10: 8 | C10: 267869 | D10: POTE HERM BAUMON RET 400ML C/ TAMPA R145 | E10: 3024 | F10: 36 | G10: =E10/F10 -> 84 | H10: 0.04394971 | I10: =H10*G10 -> 3.6917756
A11: 9 | C11: 267870 | D11: POTE HERM BAUMON RET 630ML C/ TAMPA R170 | E11: 3000 | F11: 24 | G11: =E11/F11 -> 125 | H11: 0.04353888 | I11: =H11*G11 -> 5.44236
A12: 10 | C12: 267931 | D12: POTE HERM BAUMON 1410ML R220-2FULL | E12: 3000 | F12: 12 | G12: =E12/F12 -> 250 | H12: 0.04136 | I12: =H12*G12 -> 10.34
A13: 11 | C13: 267932 | D13: POTE HERM BAUMON 1040ML C/TAM R195-2FULL | E13: 3000 | F13: 24 | G13: =E13/F13 -> 125 | H13: 0.0623922 | I13: =H13*G13 -> 7.799025
A14: 12 | C14: 267936 | D14: POTE HERM BAUMON QD 750ML C/TAMP S150-2 | E14: 3000 | F14: 24 | G14: =E14/F14 -> 125 | H14: 0.04025334 | I14: =H14*G14 -> 5.0316675
... A55: 53 | C55: 370451 | D55: Sup p/TV Baumon Fixo LCD-800 PT | E55: 6000 | F55: 40 | G55: =E55/F55 -> 150 | H55: 0.0337 | I55: =H55*G55 -> 5.055
A56: 54 | D56: Sup p/TV Baumon Universal YN-LED001 PT | E56: 600 | F56: 20 | G56: =E56/F56 -> 30 | H56: 0.0125 | I56: =H56*G56 -> 0.375
A57: 55 | C57: 370452 | D57: Sup p/TV Baumon fixo YN-109MF PT | E57: 3000 | F57: 10 | G57: =E57/F57 -> 300 | H57: 0.0359 | I57: =H57*G57 -> 10.77
A58: 56 | C58: 370453 | D58: Sup p/TV Baumon Articulado YN-927AT PT | E58: 2760 | F58: 6 | G58: =E58/F58 -> 460 | H58: 0.0416 | I58: =H58*G58 -> 19.136
A59: 57 | D59: Jogo de Cama solteiro 100% penteado 180 fios azul | E59: 264 | F59: 12 | G59: =E59/F59 -> 22 | H59: 2.115564 | I59: =H59*G59 -> 46.542408
A60: 58 | D60: Jogo de Cama solteiro 100% penteado 180 fios bege | E60: 264 | F60: 12 | G60: =E60/F60 -> 22 | H60: 2.163645 | I60: =H60*G60 -> 47.60019
A61: 59 | D61: Jogo de Cama solteiro 100% penteado 180 fios verde | E61: 264 | F61: 12 | G61: =E61/F61 -> 22 | H61: 2.115564 | I61: =H61*G61 -> 46.542408
A62: 60 | D62: Jogo de cama casal 100% penteado 200 fios azul | E62: 264 | F62: 12 | G62: =E62/F62 -> 22 | H62: 4.12566 | I62: =H62*G62 -> 90.76452
A63: 61 | D63: Jogo de cama casal 100% penteado 200 fios bege | E63: 180 | F63: 12 | G63: =E63/F63 -> 15 | H63: 4.12566 | I63: =H63*G63 -> 61.8849
A64: 62 | D64: Jogo de cama casal 100% penteado 200 fios verde | E64: 264 | F64: 12 | G64: =E64/F64 -> 22 | H64: 4.12566 | I64: =H64*G64 -> 90.76452
A65: 63 | D65: Jogo de cama Queen 100% penteado 200 fios Azul | E65: 264 | F65: 10 | G65: =E65/F65 -> 26.4 | H65: 4.55994 | I65: =H65*G65 -> 120.38242
A66: 64 | D66: Jogo de cama Queen 100% penteado 200 fios bege | E66: 264 | F66: 10 | G66: =E66/F66 -> 26.4 | H66: 4.55994 | I66: =H66*G66 -> 120.38242
A67: 65 | D67: Jogo de cama Queen 100% penteado 200 fios verde | E67: 264 | F67: 10 | G67: =E67/F67 -> 26.4 | H67: 4.55994 | I67: =H67*G67 -> 120.38242
A68: 66 | D68: Jogo de cama King 100% penteado 200 fios Azul | E68: 264 | F68: 8 | G68: =E68/F68 -> 33 | H68: 2.877105 | I68: =H68*G68 -> 94.944465
A69: 67 | D69: Jogo de cama King 100% penteado 200 fios Bege | E69: 264 | F69: 8 | G69: =E69/F69 -> 33 | H69: 2.985675 | I69: =H69*G69 -> 98.527275
A70: 68 | D70: Jogo de cama King 100% penteado 200 fios Verde | E70: 264 | F70: 8 | G70: =E70/F70 -> 33 | H70: 2.877105 | I70: =H70*G70 -> 94.944465
... A79: 77 | D79: 2 toalhas + rosto 100% algodão (126cm x 68 cm) 500 GSM rosa | E79: 200 | F79: 8 | G79: =E79/F79 -> 25 | H79: 5.082 | I79: =H79*G79 -> 127.05

Sheet MRP NACIONAL
F1: Data do pedido
F2: Saída - ETD | G2: 46092 | H2: 46086 | I2: 46064 | J2: 46126 | N2: 46126 | P2: 46114 | X2: 46162
F3: Previsão de Chegada - ETA | G3: 46153 | H3: 05/05/026 | I3: 46142 | J3: 46187 | N3: 46187 | P3: 46191 | X3: 46219
A4: Qtd | B4: Categoria | C4: GM9 Descrição | D4: Trade | E4: Código | F4: Descrição | G4: Bemol 36 | H4: Bemol 37 | I4: Bemol 38 | J4: Bemol 39 | K4: Bemol 40 | L4: Bemol 41 | M4: Bemol 42 | N4: Bemol 43 | O4: Bemol 44 | P4: Bemol 45 | Q4: Bemol 46 | R4: Bemol 47 | S4: Bemol 48 | T4: Bemol 49 | U4: Bemol 50 | V4: Bemol 51 | W4: Bemol 52 | X4: Bemol 53 | Y4: Bemol 54 | Z4: Bemol 55 | AA4: Bemol 56 | AB4: Bemol 57 | AC4: Bemol 58 | AD4: Bemol 59 | AE4: Bemol 60 | AF4: Bemol 61 | AG4: Bemol 62 | AH4: Bemol 63 | AI4: Bemol 64 | AJ4: Bemol 65 | AK4: Bemol 66 | AL4: Bemol 67 | AM4: Bemol 68 | AN4: Bemol 69 | AO4: Bemol 70 | AP4: Bemol 71 | AQ4: Bemol 72 | AR4: Bemol 73 | AS4: Bemol 74
A5: 1 | B5: 111002004 | C5: VENTILADOR DE MESA | D5: Fresnomaq | E5: 252881 | F5: VENT MESA 50 BAUMON 2EM1 FW10595 PT | AL5: =SUM(G5:AJ5) -> 0
A6: 2 | B6: 111002003 | C6: VENTILADOR DE COLUNA | D6: Importad | E6: 252882 | F6: VENT COLUNA 50 BAUMON FW010593 PT | AL6: =SUM(G6:AJ6) -> 0
A7: 3 | B7: 120010004 | C7: KIT COZINHA DE MADEIRA | D7: THB | E7: 374681 | F7: Kit 9P/1G Cozinha Baumon Açai CC/OW | AL7: =SUM(G7:AJ7) -> 0
A8: 4 | B8: 120010004 | C8: KIT COZINHA DE MADEIRA | D8: Kit´s Paraná | E8: 391650 | F8: Kit 8p/1G cozinha Baumon Cupuaçu FJ/SFT | AL8: =SUM(G8:AJ8) -> 0
A9: 5 | B9: 120003013 | C9: ROUP PORTA BASCULANTE ATÉ 4 PTS | D9: Demobille | E9: 358745 | F9: Roupeiro 4P/2G Baumon Coari 43240 Branco | AL9: =SUM(G9:AJ9) -> 0
A10: 6 | B10: 120003014 | C10: ROUP PORTA BASCULANTE DE 5 À 12 PTS | D10: Demobille | E10: 358746 | F10: Roupeiro 6P/2G Baumon Autazes 63220 CNM/OW | AL10: =SUM(G10:AJ10) -> 0
A11: 7 | B11: 120003014 | C11: ROUP PORTA BASCULANTE DE 5 À 12 PTS | D11: Demobille | E11: 358747 | F11: Roupeiro 6P/2G Baumon Maués 62560 CNM/OW | AL11: =SUM(G11:AJ11) -> 0
A12: 8 | B12: 120010003 | C12: BALCÃO COZINHA DE MADEIRA | D12: LInea | E12: 394619 | F12: BALC 2P BAUMON MANAÓS OW | AL12: =SUM(G12:AJ12) -> 0
A13: 9 | B13: 120010006 | C13: KIT FORNO DE MADEIRA | D13: LInea | E13: 394620 | F13: KIT FORNO 4P BAUMON MANAÓS OW | AL13: =SUM(G13:AJ13) -> 0
A14: 10 | B14: 120010002 | C14: ARMÁRIO AÉREO COZINHA DE MADEIRA | D14: LInea | E14: 395051 | F14: ARMÁRIO 2P BAUMON MANAÓS 810015116 OW | AL14: =SUM(G14:AJ14) -> 0
A15: 11 | B15: 120010002 | C15: ARMÁRIO AÉREO COZINHA DE MADEIRA | D15: LInea | E15: 395052 | F15: ARMÁRIO 2P BAUMON MANAÓS 810015117 OW | AL15: =SUM(G15:AJ15) -> 0
A16: 12 | B16: 120010003 | C16: BALCÃO COZINHA DE MADEIRA | D16: LInea | E16: 395053 | F16: BALC 2P/3G BAUMON MANAÓS C/TAMPO OW | AL16: =SUM(G16:AJ16) -> 0
... A27: 27 | B27: 111001017 | C27: LIQUIDIFICADOR ACIMA DE 3 VEL | D27: Mallory | E27: 400883 | F27: LIQUIDIFICADOR BAUMON BM1000 900W VM | AL27: =SUM(G27:AJ27) -> 0
A28: 28 | B28: 109001005 | C28: ENROLADO MOLA CASAL | D28: Herval | E28: 402152 | F28: COLC ENROLADO BAUMON C1972 138X188X30
A29: 29 | B29: 109001008 | C29: ENROLADO MOLA QUEEN | D29: Herval | E29: 402179 | F29: COLC ENROLADO BAUMON C1973 158X198X30
A30: 30 | B30: 109004006 | C30: CAMA AMERICANA QUEEN | D30: Herval | E30: 402247 | F30: CAMA AMERIC BAUMON CZ 158X198X28
A31: 31 | B31: 117004002 | C31: FOGÃO 4 BOCAS | D31: Mueller | E31: 406032 | F31: FOGÃO 4B BAUMON MESA INOX MFI4BB BR
A32: 32 | B32: 117004002 | C32: FOGÃO 4 BOCAS | D32: Mueller | E32: 406033 | F32: FOGÃO 4B BAUMON MESA VIDRO MFV4BB BR
A33: 33 | B33: 117004003 | C33: FOGÃO 5 BOCAS | D33: Mueller | E33: 406034 | F33: FOGÃO 5B BAUMON MESA INOX MFI5BB BR
A34: 34 | B34: 117004003 | C34: FOGÃO 5 BOCAS | D34: Mueller | E34: 406035 | F34: FOGÃO 5B BAUMON MESA VIDRO MFV5BB BR
A35: 35 | B35: 117004009 | C35: COOKTOP Á GÁS | D35: Mueller | E35: 406036 | F35: COOKTOP 5B BAUMON A GÁS MCG5BB PT
A36: 36 | B36: 117001017 | C36: CENTRÍFUGA LINHA BRANCA | D36: Mueller | E36: 406037 | F36: CENTRÍFUGA 15 BAUMON FIT 610008325 BR
A37: 37 | B37: 117007005 | C37: LAVADORA AUTOMÁTICA À PARTIR DE 12 KG | D37: Mueller | E37: 406038 | F37: LAVADORA 15 BAUMON 610008326 BR

Sheet Pedidos - Bemol Lovers
A2: Material | B2: Nome | C2: Pedido 19/03 | D2: Pedido 15/04 | E2: Pedido 08/06 | F2: Pedido 18/06 | J2: Total
A3: 374885 | B3: 1 PAR MEIA BEMOL BR LOGO AZ E LISTRA M | J3: =SUM(C3:I3) -> 0
A4: 374876 | B4: 1 PAR MEIA BEMOL AZ COM LOGO AZ M | J4: =SUM(C4:I4) -> 0
A5: 374873 | B5: 1 PAR MEIA BEMOL LISTRA AZ E VM M | J5: =SUM(C5:I5) -> 0
A6: 374879 | B6: 1 PAR MEIA BEMOL AZ COM LOGO BR M | J6: =SUM(C6:I6) -> 0
A7: 374882 | B7: 1 PAR MEIA BEMOL BRANCA COM LOGO AZ M | J7: =SUM(C7:I7) -> 0
A8: 374870 | B8: 1 PAR MEIA BEMOL COCAR M | D8: 600 | F8: 4000 | J8: =SUM(C8:I8) -> 4600
A9: 374867 | B9: 1 PAR MEIA BEMOL TEATRO AMAZONAS M | D9: 700 | F9: 4000 | J9: =SUM(C9:I9) -> 4700
A10: 374864 | B10: 1 PAR MEIA BEMOL BOTO COR DE RO M | D10: 1320 | F10: 4000 | J10: =SUM(C10:I10) -> 5320
A11: 374861 | B11: 1 PAR MEIA BEMOL CAPIVARA M | D11: 1820 | F11: 4000 | J11: =SUM(C11:I11) -> 5820
A12: 374875 | B12: 1 PAR MEIA BEMOL AZ COM LOGO AZ P | J12: =SUM(C12:I12) -> 0
A13: 374881 | B13: 1 PAR MEIA BEMOL BRANCA COM LOGO AZ P | J13: =SUM(C13:I13) -> 0
A14: 374878 | B14: 1 PAR MEIA BEMOL AZ COM LOGO BR P | J14: =SUM(C14:I14) -> 0
A15: 374888 | B15: 1 PAR MEIA BEMOL ONÇA PINTADA M | D15: 2070 | F15: 4000 | J15: =SUM(C15:I15) -> 6070
A16: 374884 | B16: 1 PAR MEIA BEMOL BR LOGO AZ E LISTRA P | D16: 500 | J16: =SUM(C16:I16) -> 500
A17: 374872 | B17: 1 PAR MEIA BEMOL LISTRA AZ E VM P | D17: 500 | J17: =SUM(C17:I17) -> 500
A18: 374858 | B18: 1 PAR MEIA BEMOL GATO PT M | D18: 2200 | F18: 4000 | J18: =SUM(C18:I18) -> 6200
A19: 374869 | B19: 1 PAR MEIA BEMOL COCAR P | C19: 1000 | F19: 4000 | J19: =SUM(C19:I19) -> 5000
A20: 374866 | B20: 1 PAR MEIA BEMOL TEATRO AMAZONAS P | C20: 1000 | D20: 500 | F20: 4000 | J20: =SUM(C20:I20) -> 5500
A21: 374863 | B21: 1 PAR MEIA BEMOL BOTO COR DE RO P | C21: 1000 | D21: 1230 | F21: 4000 | J21: =SUM(C21:I21) -> 6230
A22: 374857 | B22: 1 PAR MEIA BEMOL GATO PT P | D22: 2500 | F22: 4000 | J22: =SUM(C22:I22) -> 6500
A23: 374886 | B23: 1 PAR MEIA BEMOL BR LOGO AZ E LISTRA G | C23: 1000 | J23: =SUM(C23:I23) -> 1000
A24: 374887 | B24: 1 PAR MEIA BEMOL ONÇA PINTADA P | C24: 1000 | D24: 1660 | F24: 4000 | J24: =SUM(C24:I24) -> 6660
A25: 374883 | B25: 1 PAR MEIA BEMOL BRANCA COM LOGO AZ G | C25: 1000 | J25: =SUM(C25:I25) -> 1000
A26: 374880 | B26: 1 PAR MEIA BEMOL AZ COM LOGO BR G | C26: 1000 | J26: =SUM(C26:I26) -> 1000
A27: 374877 | B27: 1 PAR MEIA BEMOL AZ COM LOGO AZ G | C27: 1000 | J27: =SUM(C27:I27) -> 1000
A28: 374860 | B28: 1 PAR MEIA BEMOL CAPIVARA P | C28: 1600 | D28: 1500 | F28: 4000 | J28: =SUM(C28:I28) -> 7100
A29: 374874 | B29: 1 PAR MEIA BEMOL LISTRA AZ E VM G | C29: 1000 | D29: 500 | J29: =SUM(C29:I29) -> 1500
A30: 374868 | B30: 1 PAR MEIA BEMOL TEATRO AMAZONAS G | C30: 1000 | D30: 500 | F30: 4000 | J30: =SUM(C30:I30) -> 5500
A31: 374871 | B31: 1 PAR MEIA BEMOL COCAR G | C31: 1000 | D31: 500 | F31: 4000 | J31: =SUM(C31:I31) -> 5500
A32: 374865 | B32: 1 PAR MEIA BEMOL BOTO COR DE RO G | C32: 1000 | D32: 500 | F32: 4000 | J32: =SUM(C32:I32) -> 5500
A33: 374862 | B33: 1 PAR MEIA BEMOL CAPIVARA G | C33: 1200 | D33: 500 | F33: 4000 | J33: =SUM(C33:I33) -> 5700
A34: 374889 | B34: 1 PAR MEIA BEMOL ONÇA PINTADA G | C34: 1600 | D34: 500 | F34: 4000 | J34: =SUM(C34:I34) -> 6100
A35: 374859 | B35: 1 PAR MEIA BEMOL GATO PT G | C35: 2400 | F35: 4000
A36: 382306 | B36: Bola de futebol Bemol BL002 Br | E36: 800
A37: 382305 | B37: Bola de Futebol Bemol Recreativa Br | E37: 1200

Sheet Consolidado
A2: PROCESSOTIMBRO | B2: Pedido | C2: Produto | D2: Data do pedido | E2: Conclusãodeprodução | F2: Final | G2: HBL | H2: Ncontrole | I2: CIAMarítima | J2: Navio | K2: Valor | L2: ETD | M2: ETA | N2: Comentários
A3: BEMOL 5 | B3: 4508208614 | C3: AIRFRYER3,5L | D3: 45789 | E3: 45834 | F3: 45837 | G3: NBBLU25016330 | H3: MSDU7864062 | I3: MSC | J3: LOG-INEXPERIENCE/016S | K3: 5900 | L3: 45854 | M3: 45916 | N3: CONCLUÍDO
A4: BEMOL 6 | B4: 4508208616 | C4: LINHABEAUTY+ESPREMEDORBH3326 | D4: 45793 | E4: 45847 | F4: 45852 | G4: NBBLU25016481 | H4: MSNU9503623 | I4: MSC | J4: LOG-INEVOLUTION/042S | K4: 5900 | L4: 45879 | M4: 45930 | N4: CONCLUÍDO
A5: BEMOL 7 | B5: 4508208537 | C5: FERRO/ESPREMEDOR/VAPORIZADOR/CAÇAROLA | D5: 45793 | E5: 45854 | F5: 45855 | G5: NBBLU25016516 | H5: MSBU8716226 | I5: MSC | J5: LOG-INEVOLUTION/042S | K5: 5900 | L5: 45879 | M5: 45930 | N5: CONCLUÍDO
A6: BEMOL 11 | B6: 4508206547 | C6: AIRFRYER12L+SANDUICHEIRA | D6: 45838 | E6: 46262 | F6: 45898 | G6: NBBLU25017501 | H6: FDCU0035202 | I6: HapagLLoyd | J6: KUALALUMPUREXPRESS | K6: 4000 | L6: 45908 | M6: 45970 | N6: CONCLUÍDO
A7: BEMOL 8 | B7: 4508208626 | C7: LIQUIDIFICADORES+ COPO | D7: 45845 | E7: 45893 | F7: 45896 | G7: SNBLU25012968 | H7: UETU8288620 | I7: MSC | J7: MSCANTONELLAUX536A | K7: 4000 | L7: 45906 | M7: 45974 | N7: CONCLUÍDO
A8: BEMOL 12 | B8: 4508208624 | C8: LIQUIDIFICADORES+SANDUICHEIRA+MINIPR.+jUICERJE678G | D8: 45845 | E8: 45909 | F8: 45910 | G8: NBBLU25018167 | H8: ESHU7234223 | I8: Cosco | J8: COSCOSHIPPINGPENGBO/16 | K8: 4000 | L8: 45915 | M8: 45976 | N8: CONCLUÍDO
A9: BEMOL 9 | B9: 4508208633 | C9: VIDROSREPOSIÇÃO01 | D9: 45842 | E9: 45907 | F9: 45908 | G9: QOBLU25009926 | H9: MSNU9540355 | I9: MSC | J9: LOG-INEXPERIENCE/018S | K9: 3500 | L9: 45911 | M9: 45972 | N9: CONCLUÍDO
A10: BEMOL 13 | B10: 4508214286 | C10: FORNOELÉTRICO | D10: 45854 | E10: 45894 | F10: 45895 | G10: SNBLU25013124 | H10: TGBU7569191 | I10: MSC | J10: LOG-INPOLARIS/125S | K10: 3500 | L10: 45918 | M10: 45979 | N10: CONCLUÍDO
A11: BEMOL 14 | B11: 4508235799 | C11: VIDROSREPOSIÇÃO02 | D11: 45852 | E11: 45930 | F11: 45930 | G11: QOBLU25010198 | H11: MSBU8122306 MEDU7313566 | I11: nsolida | J11: LOG-INPOLARIS/125S | K11: 5800 | L11: 45961 | M11: 46013 | N11: CONCLUÍDO
A12: BEMOL 10 | B12: 4508360745 | C12: MÁQUINADEGELO+(3)SUPORTETV+LIQUIDIFICADORGSE019 | D12: 45876 | E12: 45928 | F12: 45929 | G12: NBBLU25018879 | H12: MSMU7127483 | I12: MSC | J12: MSCLORENZAUX541A | K12: 2900 | L12: 45947 | M12: 46020 | N12: CONCLUÍDO
A13: BEMOL 19 | B13: 4508591119 | C13: VIDROSREPOSIÇÃO3A-CTNR1 | D13: 45876 | E13: 45960 | F13: 45966 | G13: ONEYTA5RA9176400 | H13: ONEU1824259 | I13: ONE | J13: MANZANILLO | K13: 5202.53 | L13: 45989 | M13: 46051 | N13: CONCLUÍDO
A14: BEMOL 19 | B14: 4508591119 | C14: VIDROSREPOSIÇÃO3B-CTNR2 | D14: 45876 | E14: 45960 | F14: 45966 | G14: ONEYTA5RA9176400 | H14: ONEU1834365 | I14: ONE | J14: MANZANILLO | K14: 5202.53 | L14: 45989 | M14: 46051 | N14: CONCLUÍDO
A15: BEMOL 20 | B15: 4508436265 | C15: AIRFRYER12L+GRILL+FERROÀSECO | D15: 45908 | E15: 45966 | F15: 45975 | G15: SHYY25114820 | H15: ONEU6318757 | I15: ONE | K15: 2754 | L15: 45988 | M15: 46034 | N15: CONCLUÍDO
A16: BEMOL 21 | B16: 4508436285 | C16: VIDROSREPOSIÇÃO4+Led002 | D16: 45902 | E16: 45976 | F16: 45977 | G16: ONEYTA5RA5881300 | H16: TCNU6619092 | I16: ONE | K16: 2679 | L16: 45993 | M16: 46063 | N16: CONCLUÍDO
A17: BEMOL 25 | B17: 4508532679 | C17: BEBEDOUROBAUMONYLRLW2540TBSBR | D17: 45929 | E17: 45985 | F17: 26/112025 | G17: NBBLU25020450 | H17: FFAU2354768 | I17: MSC | J17: MSCKATRINAUX548A | K17: 2459.85 | L17: 45992 | M17: 46056 | N17: CONCLUÍDO
A18: BEMOL 25 | B18: 4508532679 | C18: BEBEDOUROBAUMONYLRLW2540LBBR+BEBEDOUROBAUMONYLRLW2540LBBPT | D18: 45929 | E18: 45985 | F18: 45987 | G18: NBBLU25020450 | H18: MEDU8128285 | I18: MSC | J18: MSCKATRINAUX548A | K18: 2459.85 | L18: 45992 | M18: 46056 | N18: CONCLUÍDO
A19: BEMOL 25 | B19: 4508532679 | C19: BEBEDOUROBAUMONYLRLW2540LBBR+BEBEDOUROBAUMONYLRLW2540LBBPT | D19: 45929 | E19: 45985 | F19: 45987 | G19: NBBLU25020450 | H19: MSMU6226537 | I19: MSC | J19: MSCKATRINAUX548A | K19: 2459.85 | L19: 45992 | M19: 46056 | N19: CONCLUÍDO
A20: BEMOL 25 | B20: 4508532679 | C20: BEBEDOUROBAUMONYLRLW2540LBBR+BEBEDOUROBAUMONYLRLW2540LBBPT | D20: 45929 | E20: 45985 | F20: 45987 | G20: NBBLU25020450 | H20: MSNU5842887 | I20: MSC | J20: MSCKATRINAUX548A | K20: 2459.85 | L20: 45992 | M20: 46056 | N20: CONCLUÍDO
A21: BEMOL 25 | B21: 4508532679 | C21: BEBEDOUROBAUMONYLRLW2540LBBR+BEBEDOUROBAUMONYLRLW2540LBBPT | D21: 45929 | E21: 45985 | F21: 45987 | G21: NBBLU25020450 | H21: TCLU7779400 | I21: MSC | J21: MSCKATRINAUX548A | K21: 2459.85 | L21: 45992 | M21: 46056 | N21: CONCLUÍDO
A22: BEMOL 25 | B22: 4508532679 | C22: BEBEDOUROBAUMONYLRLW2540LBBR+BEBEDOUROBAUMONYLRLW2540LBBPT | D22: 45929 | E22: 45985 | F22: 45987 | G22: NBBLU25020450 | H22: TCNU8726382 | I22: MSC | J22: MSCKATRINAUX548A | K22: 2459.85 | L22: 45992 | M22: 46056 | N22: CONCLUÍDO
A23: BEMOL 25 | B23: 4508532679 | C23: BEBEDOUROBAUMONYYLRLW2540LBSBR | D23: 45929 | E23: 45985 | F23: 45987 | G23: NBBLU25020450 | H23: UETU7070845 | I23: MSC | J23: MSCKATRINAUX548A | K23: 2459.85 | L23: 45992 | M23: 46056 | N23: CONCLUÍDO
A24: BEMOL 27 | B24: 4508417096 | C24: AIRFRYER3,5L | D24: 45971 | E24: 46013 | F24: 46013 | G24: NBBLU25020986 | H24: MSNU8455500 | I24: MSC | J24: MSCAURIGAUX552A | K24: 2663 | L24: 46026 | M24: 46084 | N24: CONCLUÍDO
A25: BEMOL 26 | B25: 4508490039 | C25: AIRFRYER12L | D25: 45971 | E25: 46000 | F25: 46002 | G25: NBBLU25020957 | H25: BMOU6778070 | I25: MSC | J25: MSCAURIGAUX552A | K25: 2663 | L25: 46026 | M25: 46084 | N25: CONCLUÍDO
A26: BEMOL 29 | B26: 4508490029 | C26: FERROAVAPOR+FRIGOBARHC46 | D26: 45973 | E26: 46007 | F26: 46007 | G26: NBBLU5020956 | H26: TCLU7890497 | I26: MSC | J26: MSCAURIGAUX552A | K26: 2663 | L26: 46026 | M26: 46084 | N26: CONCLUÍDO
A27: BEMOL 29 | B27: 4508490029 | C27: FERROAVAPOR+FRIGOBARHC46 | D27: 45973 | E27: 46006 | F27: 46007 | G27: NBBLU25020836 | H27: MSMU5480383 | I27: MSC | J27: MSCDENISSEXUX551A | K27: 2663 | L27: 46384 | M27: 46077 | N27: CONCLUÍDO
A28: BEMOL 22 | B28: 4508645458 | C28: Reposição05A-2Containers | D28: 45960 | E28: 46001 | F28: 46002 | G28: TAO31126537 | H28: MSDU5974230 | I28: MSC | K28: 2538.09 | L28: 46034 | M28: 46084 | N28: CONCLUÍDO
A29: BEMOL 23 | B29: 4508657825 | C29: Reposição05B | D29: 45960 | E29: 46011 | F29: 46012 | G29: TAO31126537 | H29: MEDU7602018 | I29: MSC | K29: 2538.09 | L29: 46034 | M29: 46084 | N29: CONCLUÍDO
A30: BEMOL 37 | B30: 4508696481 | C30: FORNOELÉTRICO | D30: 45992 | E30: 46021 | F30: 45677 | G30: CAN31112406 | H30: TGBU5940960 | I30: HAPAG-LLOYD | J30: MSCSARYA | K30: 2006 | L30: 46058 | M30: 46114 | N30: CONCLUÍDO
A31: BEMOL 37 | B31: 4508696481 | C31: FORNOELÉTRICO | D31: 45992 | E31: 46021 | F31: 45677 | G31: CAN31112406 | H31: FANU3854801 | I31: HAPAG-LLOYD | J31: MSCSARYA | K31: 2006 | L31: 46058 | M31: 46114 | N31: CONCLUÍDO
A32: BEMOL 31 | B32: 4508532742 | C32: REPOSIÇÃODEVIDROS6 | D32: 46006 | E32: 46052 | F32: 46052 | G32: CKBLU26005229 | H32: MSNU5267237 | I32: AMTRANS | K32: 2050 | L32: 46086 | M32: 46147 | N32: CONCLUÍDO
A33: BEMOL 33 | B33: 4508770727 | C33: BEAUTYEAIRFRYER3,5l | D33: 46006 | E33: 46096 | F33: 46097 | G33: CKBLU26005229 | H33: BMOU6580654 | I33: AMTRANS | K33: 2050 | L33: 46092 | M33: 46153 | N33: CONCLUÍDO
A34: BEMOL 35 | B34: 4508750228 | C34: FORNOELÉTRICO | D34: 46014 | E34: 46054 | F34: 46055 | G34: SZXS074568 | H34: MSMU4423326 | I34: MSC | J34: NCBREDA | K34: 1900 | L34: 46064 | M34: 46140 | N34: CONCLUÍDO
A35: BEMOL 35 | B35: 4508750228 | C35: FORNOELÉTRICO | D35: 46014 | E35: 46054 | F35: 46055 | G35: SZXS074568 | H35: MSDU5172851 | I35: MSC | J35: NCBREDA | K35: 1900 | L35: 46064 | M35: 46140 | N35: CONCLUÍDO
A36: BEMOL 35 | B36: 4508750228 | C36: FORNOELÉTRICO | D36: 46014 | E36: 46054 | F36: 46055 | G36: SZXS074568 | H36: TGBU4396106 | I36: MSC | J36: NCBREDA | K36: 1900 | L36: 46064 | M36: 46140 | N36: CONCLUÍDO
A37: BEMOL 35 | B37: 4508750228 | C37: FORNOELÉTRICO | D37: 46014 | E37: 46054 | F37: 46055 | G37: SZXS074568 | H37: MSMU6142797 | I37: MSC | J37: NCBREDA | K37: 1900 | L37: 46064 | M37: 46140 | N37: CONCLUÍDO
A38: BEMOL 35 | B38: 4508750228 | C38: FORNOELÉTRICO | D38: 46014 | E38: 46054 | F38: 46055 | G38: SZXS074568 | H38: MSMU6958287 | I38: MSC | J38: NCBREDA | K38: 1900 | L38: 46064 | M38: 46140 | N38: CONCLUÍDO
A39: BEMOL 35 | B39: 4508750228 | C39: FORNOELÉTRICO | D39: 46014 | E39: 46054 | F39: 46055 | G39: SZXS074568 | H39: MSDU6329101 | I39: MSC | J39: NCBREDA | K39: 1900 | L39: 46064 | M39: 46140 | N39: CONCLUÍDO
A40: BEMOL 34 | B40: 4508779388 | C40: REPOSIÇÃODEVIDRO7A | D40: 46014 | E40: 46049 | F40: 46050 | G40: SHA31176965 | H40: BMOU4956439 | I40: MSC | J40: ZHONGCHENG99 | K40: 2250 | L40: 46086 | M40: 46156 | N40: CONCLUÍDO
A41: BEMOL 34 | B41: 4508779388 | C41: REPOSIÇÃODEVIDRO7B | D41: 46014 | E41: 46049 | F41: 46050 | G41: SHA31176965 | H41: HAMU4323916 | I41: MSC | J41: ZHONGCHENG99 | K41: 2250 | L41: 46086 | M41: 46156 | N41: CONCLUÍDO
A42: BEMOL 36 | B42: 4508751729 | C42: FERROSECO+MINIPROCESSADOR+PRANCHASD-515 | D42: 46014 | E42: 46090 | F42: 46091 | G42: NGB31166038 | H42: HAMU1718065 | I42: HAPAG-LLOYD | J42: SANTACATARINAEXPRESS | K42: 3573.0755 | L42: 46126 | M42: 46205
A43: BEMOL 36 | B43: 4508751729 | C43: FERROSECO+MINIPROCESSADOR+PRANCHASD-515 | D43: 46014 | E43: 46101 | F43: 46102 | G43: NGB31166038 | H43: HLXU8221843 | I43: HAPAG-LLOYD | J43: SANTACATARINAEXPRESS | K43: 3573.0755 | L43: 46126 | M43: 46205
A44: BEMOL 42 | B44: 4508576884 | C44: ASSADEIRAS | D44: 46063 | E44: 46096 | F44: 46107 | G44: SHA31178711 | H44: FANU1271087 | I44: HapagLLoyd | J44: ZHONGCHENG99 | K44: 2600 | L44: 46114 | M44: 46205 | N44: CONCLUÍDO
A45: BEMOL 42 | B45: 4508576884 | C45: ASSADEIRAS | D45: 46063 | E45: 46096 | F45: 46107 | G45: SHA31178711 | H45: HAMU1390865 | I45: HapagLLoyd | J45: ZHONGCHENG99 | K45: 2600 | L45: 46114 | M45: 46205 | N45: CONCLUÍDO
A46: BEMOL 42 | B46: 4508576884 | C46: ASSADEIRAS | D46: 46063 | E46: 46096 | F46: 46107 | G46: SHA31178711 | H46: HLXU8347322 | I46: HapagLLoyd | J46: ZHONGCHENG99 | K46: 2600 | L46: 46114 | M46: 46205 | N46: CONCLUÍDO
A47: BEMOL 40 | B47: 4508559921 | C47: FORNOELÉTRICO60L | D47: 46055 | E47: 46099 | F47: 46099 | G47: CAN31113002 | H47: FANU1271087 | I47: HapagLLoyd | J47: SANTACATARINAEXPRESS | K47: 2600 | L47: 46126 | M47: 46205 | N47: CONCLUÍDO
A48: BEMOL 40 | B48: 4508559921 | C48: FORNOELÉTRICO60L | D48: 46055 | E48: 46099 | F48: 46099 | G48: CAN31113002 | H48: HAMU1390865 | I48: HapagLLoyd | J48: SANTACATARINAEXPRESS | K48: 2600 | L48: 46126 | M48: 46205 | N48: CONCLUÍDO
A49: BEMOL 40 | B49: 4508559921 | C49: FORNOELÉTRICO60L | D49: 46055 | E49: 46099 | F49: 46099 | G49: CAN31113002 | H49: HLXU8347322 | I49: HapagLLoyd | J49: SANTACATARINAEXPRESS | K49: 2600 | L49: 46126 | M49: 46205 | N49: CONCLUÍDO
A50: BEMOL 38 | B50: 4508840421 | C50: LENÇOISESTAMPADOSELISOS | D50: 46084 | E50: 46134 | F50: 46135 | G50: KHI2062MUN | H50: TCNU6401006 | I50: MAERSK | K50: 2156 | L50: 46147 | M50: 46242
A51: BEMOL 39 | B51: 4508577003(EmProdução) | C51: BATEDEIRAPLANETÁRIA | D51: Novo desenvolvimento | E51: 46265 | F51: Em andamento | G51: - | H51: - | I51: - | J51: - | K51: - | L51: - | M51: - | N51: Emprodução-Final01/09
A52: BEMOL 43 | B52: 4508840505 | C52: SECADORPREMIUM + CHURRASQUEIRA | D52: Novo desenvolvimento | E52: 46249 | F52: Em andamento | G52: - | H52: - | I52: -
A53: BEMOL 41 | B53: Criar Pedido | C53: CAFETEIRAEMIXER | D53: Novo desenvolvimento | E53: 46234 | F53: Em andamento | G53: - | H53: - | I53: -
A54: BEMOL 45 | B54: 4508894878 | C54: MAQUINADEGELO+VAPORIZADOR+SUPORTEDETV+LIQUIDIFICADORVIDRO | D54: 46090 | E54: 46139 | F54: Em andamento | G54: 1074377332 | H54: FSCU8231725 | I54: HAPAG-LLOYD | K54: 2650 | L54: 46169 | M54: 46233
A55: BEMOL 46 | B55: Criar Pedido(EmProdução) | C55: EDREDONS | D55: 46160 | E55: 46226 | F55: - | G55: - | H55: - | I55: - | N55: Emprodução-Final22/07
A56: BEMOL 47 | B56: 4508840296 | C56: FORNOELÉTRICO60LTS | D56: 46090 | E56: 46150 | F56: Em andamento | G56: CAN31113229 | H56: HAMU1899636 | I56: HAPAG-LLOYD | K56: 2606 | L56: 46162 | M56: 46233
A57: BEMOL 48 | B57: 4508840510 | C57: AIRFRYER12L | D57: 46093 | E57: 46147 | F57: Em andamento | G57: NGB31167475 | H57: GAOU7397863 | I57: MSC | K57: 2656 | L57: 46172 | M57: 46231
A58: BEMOL 49 | B58: 4508840536 | C58: GRILL+ESCOVASECADOR+SANDUICHEIRA+CHAPINHA+ESPREMEDOR | D58: 46093 | E58: 46162 | F58: Em andamento | G58: NGB31168106 | H58: MSBU5188110 | I58: MSC | K58: 4400 | L58: 46176 | M58: 46239
A59: BEMOL 51 | B59: 4508699466 | C59: POTESDEVIDRO | D59: 46093 | E59: 46177 | F59: Em andamento
A60: BEMOL 50 | B60: 4508840545 | C60: BEAUTYCHUMBO+AIRFRYER12L+TRAVESSAS | D60: 46108 | E60: 46177 | F60: Em andamento | G60: NGBS000622 | H60: FANU3565630 | I60: HAPAG-LLOYD | K60: 2796 | L60: 46191 | M60: 46247
A61: BEMOL 50 | B61: 4508840545 | C61: BEAUTYCHUMBO+AIRFRYER12L+TRAVESSAS | D61: 46108 | E61: 46177 | F61: Em andamento | G61: NGBS000622 | H61: HLBU1619885 | I61: HAPAG-LLOYD | K61: 2796 | L61: 46191 | M61: 46247
A62: BEMOL 52 | B62: 4508894889 | C62: COPOLIQUIDIFICADORGSE019 | D62: - | E62: 46178 | F62: Em andamento | G62: - | H62: - | I62: -
A63: BEMOL 53 | B63: 4508727560 | C63: POTESDEVIDRO | D63: 46139 | E63: 46198 | F63: Em andamento | G63: - | H63: - | I63: HAPAG-LLOYD | K63: 7400 | L63: 46205 | M63: 46266
A64: BEMOL 53 | B64: 4508727560 | C64: POTESDEVIDRO | D64: 46139 | E64: 46198 | F64: Em andamento | G64: - | H64: - | I64: HAPAG-LLOYD | K64: 7400 | L64: 46205 | M64: 46266
A65: BEMOL 53 | B65: 4508727560 | C65: POTESDEVIDRO | D65: 46139 | E65: 46198 | F65: Em andamento | G65: - | H65: - | I65: HAPAG-LLOYD | K65: 7400 | L65: 46205 | M65: 46266
A66: BEMOL 54 | B66: 4508894894 | C66: AIRFRYER12L | D66: 46139 | E66: 46190 | F66: Em andamento | G66: - | H66: - | I66: MAERSK | K66: 3975 | L66: 46203 | M66: 46246
A67: BEMOL 55 | B67: 4508727727 | C67: FRIGOBARHC46L | D67: 46139 | E67: 46172 | F67: Em andamento | G67: NGBS001342 | H67: 4508727727 | I67: SCANGLOBAL | K67: 8356 | L67: 46183 | M67: 46246
A68: BEMOL 55 | B68: 4508727727 | C68: FRIGOBARHC46L | D68: 46139 | E68: 46172 | F68: Em andamento | G68: NGBS001342 | H68: 4508727727 | I68: SCANGLOBAL | K68: 8356 | L68: 46183 | M68: 46246
A69: BEMOL 56 | B69: Criar Pedido | C69: SUPORTEDETV+FERRO+LIQUIDIFICADOR+VAPORIZADOR+CHAPINHA | D69: 46139 | E69: 46188 | F69: Em andamento | G69: NGBS003530 | H69: BMOU6023258 | I69: HAPAG-LLOYD | K69: 7400 | L69: 46204 | M69: 46259
A70: BEMOL 57 | B70: 4508894854 | C70: AIRFRYER3,5L+GRILL | D70: 46139 | E70: 46183 | F70: Em andamento | G70: NGBS003532 | H70: MEDU7000900 | I70: HAPAG-LLOYD | K70: 7400 | L70: 46205 | M70: 46259
A71: BEMOL 58 | B71: =_xlfn.XLOOKUP(A71,'Base de Dados'!D:D,'Base de Dados'!C:C) -> 4508894918 | C71: BEBEDOUROS | D71: 46139 | E71: 46205 | F71: Em andamento | G71: - | H71: - | I71: MSC | K71: =77173.53/10 -> 7717.353
A72: BEMOL 58 | B72: =_xlfn.XLOOKUP(A72,'Base de Dados'!D:D,'Base de Dados'!C:C) -> 4508894918 | C72: BEBEDOUROS | D72: 46139 | E72: 46205 | F72: Em andamento | G72: - | H72: - | I72: MSC | K72: =77173.53/10 -> 7717.353
A73: BEMOL 58 | B73: =_xlfn.XLOOKUP(A73,'Base de Dados'!D:D,'Base de Dados'!C:C) -> 4508894918 | C73: BEBEDOUROS | D73: 46139 | E73: 46205 | F73: Em andamento | G73: - | H73: - | I73: MSC | K73: =77173.53/10 -> 7717.353
A74: BEMOL 58 | B74: =_xlfn.XLOOKUP(A74,'Base de Dados'!D:D,'Base de Dados'!C:C) -> 4508894918 | C74: BEBEDOUROS | D74: 46139 | E74: 46205 | F74: Em andamento | G74: - | H74: - | I74: MSC | K74: =77173.53/10 -> 7717.353
A75: BEMOL 58 | B75: =_xlfn.XLOOKUP(A75,'Base de Dados'!D:D,'Base de Dados'!C:C) -> 4508894918 | C75: BEBEDOUROS | D75: 46139 | E75: 46205 | F75: Em andamento | G75: - | H75: - | I75: MSC | K75: =77173.53/10 -> 7717.353
A76: BEMOL 58 | B76: =_xlfn.XLOOKUP(A76,'Base de Dados'!D:D,'Base de Dados'!C:C) -> 4508894918 | C76: BEBEDOUROS | D76: 46139 | E76: 46205 | F76: Em andamento | G76: - | H76: - | I76: MSC | K76: =77173.53/10 -> 7717.353
A77: BEMOL 58 | B77: =_xlfn.XLOOKUP(A77,'Base de Dados'!D:D,'Base de Dados'!C:C) -> 4508894918 | C77: BEBEDOUROS | D77: 46139 | E77: 46205 | F77: Em andamento | G77: - | H77: - | I77: MSC | K77: =77173.53/10 -> 7717.353
A78: BEMOL 58 | B78: =_xlfn.XLOOKUP(A78,'Base de Dados'!D:D,'Base de Dados'!C:C) -> 4508894918 | C78: BEBEDOUROS | D78: 46139 | E78: 46205 | F78: Em andamento | G78: - | H78: - | I78: MSC | K78: =77173.53/10 -> 7717.353
A79: BEMOL 58 | B79: =_xlfn.XLOOKUP(A79,'Base de Dados'!D:D,'Base de Dados'!C:C) -> 4508894918 | C79: BEBEDOUROS | D79: 46139 | E79: 46205 | F79: Em andamento | G79: - | H79: - | I79: MSC | K79: =77173.53/10 -> 7717.353
A80: BEMOL 58 | B80: =_xlfn.XLOOKUP(A80,'Base de Dados'!D:D,'Base de Dados'!C:C) -> 4508894918 | C80: BEBEDOUROS | D80: 46139 | E80: 46205 | F80: Em andamento | G80: - | H80: - | I80: MSC | K80: =77173.53/10 -> 7717.353
A81: BEMOL 58 | B81: =_xlfn.XLOOKUP(A81,'Base de Dados'!D:D,'Base de Dados'!C:C) -> 4508894918 | C81: BEBEDOUROS | D81: 46139 | E81: 46205 | F81: Em andamento | G81: - | H81: - | I81: MSC | K81: =77173.53/10 -> 7717.353
A82: BEMOL 58 | B82: =_xlfn.XLOOKUP(A82,'Base de Dados'!D:D,'Base de Dados'!C:C) -> 4508894918 | C82: BEBEDOUROS | D82: 46139 | E82: 46205 | F82: Em andamento | G82: - | H82: - | I82: MSC | K82: =77173.53/10 -> 7717.353
A83: BEMOL 59 | B83: =_xlfn.XLOOKUP(A83,'Base de Dados'!D:D,'Base de Dados'!C:C) -> 4508894928 | C83: AIRFRYER12L | D83: 46147 | E83: 46198 | F83: Em andamento | G83: T617271627444 | I83: MAERSK | K83: 3975 | L83: 46204 | M83: 46246
A84: BEMOL 59 | B84: =_xlfn.XLOOKUP(A84,'Base de Dados'!D:D,'Base de Dados'!C:C) -> 4508894928 | C84: AIRFRYER12L | D84: 46147 | E84: 46198 | F84: Em andamento | G84: T617271627444 | I84: MAERSK | K84: 3975 | L84: 46204 | M84: 46246
A85: BEMOL 60 | B85: =_xlfn.XLOOKUP(A85,'Base de Dados'!D:D,'Base de Dados'!C:C) -> 4508896119 | C85: BEBEDOUROYLR-LW-2-5-40LB | D85: 46147 | E85: 46203 | F85: Em andamento | L85: 46211 | M85: 46268
A86: BEMOL 61 | B86: =_xlfn.XLOOKUP(A86,'Base de Dados'!D:D,'Base de Dados'!C:C) -> 4508894942 | C86: AIRFRYER12L+SECADOR+MÁQUINADEGELO | D86: 46147 | E86: 46212 | F86: Em andamento
A87: BEMOL 62 | B87: =_xlfn.XLOOKUP(A87,'Base de Dados'!D:D,'Base de Dados'!C:C) -> 4508897826 | C87: POTESDEVIDRO | D87: 46147 | E87: 46199 | F87: Em andamento | I87: HAPAG-LLOYD | K87: 7600
A88: BEMOL 63 | B88: =_xlfn.XLOOKUP(A88,'Base de Dados'!D:D,'Base de Dados'!C:C) -> 4508896055 | C88: COBRELEITO | D88: 46160 | E88: 46225 | F88: Em andamento
A89: BEMOL 64 | B89: =_xlfn.XLOOKUP(A89,'Base de Dados'!D:D,'Base de Dados'!C:C) -> 4508896073 | C89: TOALHASELENÇÓIS | D89: 46155 | E89: 46230 | F89: Em andamento
A90: BEMOL 66 | B90: =_xlfn.XLOOKUP(A90,'Base de Dados'!D:D,'Base de Dados'!C:C) -> 4508918015 | C90: TOALHAS | D90: 46182 | E90: 46231 | F90: Em andamento
A91: BEMOL 65 | B91: =_xlfn.XLOOKUP(A91,'Base de Dados'!D:D,'Base de Dados'!C:C) -> 4508896020 | C91: AIRFRYER3,5L | D91: 46182 | E91: 46223 | F91: Em andamento
A92: BEMOL 67 | B92: =_xlfn.XLOOKUP(A92,'Base de Dados'!D:D,'Base de Dados'!C:C) -> 4508896009 | C92: AIRFRYER12L | D92: 46182 | E92: 46244 | F92: Em andamento
A93: BEMOL 68 | B93: =_xlfn.XLOOKUP(A93,'Base de Dados'!D:D,'Base de Dados'!C:C) -> 4508896000 | C93: FRIGOBAR46L | D93: 46182 | E93: 46236 | F93: Em andamento
A94: BEMOL 69 | B94: =_xlfn.XLOOKUP(A94,'Base de Dados'!D:D,'Base de Dados'!C:C) -> 4508895990 | C94: MAQDEGELO+CHAPINHA+SECADOR | D94: 46182 | E94: 46244 | F94: Em andamento
A95: BEMOL 70 | B95: =_xlfn.XLOOKUP(A95,'Base de Dados'!D:D,'Base de Dados'!C:C) -> 4508856527 | C95: FERROSDEPASSAR+ESPREMEDORBH3326 | D95: 46182 | E95: 46261 | F95: Em andamento
A96: BEMOL 71 | B96: =_xlfn.XLOOKUP(A96,'Base de Dados'!D:D,'Base de Dados'!C:C) -> 4508856516 | C96: SUPORTEDETV+GRILL+ESPREMEDOR+MINIPROCESSADOR+VAPORIZADOR | D96: 46182 | E96: 46261 | F96: Em andamento
A97: BEMOL 72 | B97: =_xlfn.XLOOKUP(A97,'Base de Dados'!D:D,'Base de Dados'!C:C) -> 4508890168 | C97: SUPORTES DE TV + SANDUICHEIRA | D97: 46217 | E97: 46273 | F97: Em andamento

Sheet MRP IMP
A1: #VALUE! | D1: #VALUE! | F1: Data do pedido | G1: 46213 | H1: =_xlfn.XLOOKUP(H4,Consolidado!$A:$A,Consolidado!$D:$D) -> 46014 | I1: =_xlfn.XLOOKUP(I4,Consolidado!$A:$A,Consolidado!$D:$D) -> 46084 | J1: =_xlfn.XLOOKUP(J4,Consolidado!$A:$A,Consolidado!$D:$D) -> Novo desenvolvimento | K1: =_xlfn.XLOOKUP(K4,Consolidado!$A:$A,Consolidado!$D:$D) -> Novo desenvolvimento | L1: 46100 | M1: 46504 | N1: =_xlfn.XLOOKUP(N4,Consolidado!$A:$A,Consolidado!$D:$D) -> #N/A | O1: =_xlfn.XLOOKUP(O4,Consolidado!$A:$A,Consolidado!$D:$D) -> Novo desenvolvimento | P1: =_xlfn.XLOOKUP(P4,Consolidado!$A:$A,Consolidado!$D:$D) -> 46090 | Q1: =_xlfn.XLOOKUP(Q4,Consolidado!$A:$A,Consolidado!$D:$D) -> 46160 | R1: =_xlfn.XLOOKUP(R4,Consolidado!$A:$A,Consolidado!$D:$D) -> 46090 | S1: =_xlfn.XLOOKUP(S4,Consolidado!$A:$A,Consolidado!$D:$D) -> 46093 | T1: =_xlfn.XLOOKUP(T4,Consolidado!$A:$A,Consolidado!$D:$D) -> 46093 | U1: =_xlfn.XLOOKUP(U4,Consolidado!$A:$A,Consolidado!$D:$D) -> 46108 | ... AS1: =_xlfn.XLOOKUP(AS4,Consolidado!$A:$A,Consolidado!$D:$D) -> #N/A
F2: Saída - ETD | G2: =G1+45 -> 46258 | H2: 46092 | I2: 46064 | J2: 46126 | K2: =_xlfn.XLOOKUP(K4,Consolidado!$A:$A,Consolidado!$E:$E) -> 46234 | L2: =_xlfn.XLOOKUP(L4,Consolidado!$A:$A,Consolidado!$E:$E) -> #N/A | M2: =_xlfn.XLOOKUP(M4,Consolidado!$A:$A,Consolidado!$E:$E) -> #N/A | N2: =_xlfn.XLOOKUP(N4,Consolidado!$A:$A,Consolidado!$E:$E) -> #N/A | O2: =_xlfn.XLOOKUP(O4,Consolidado!$A:$A,Consolidado!$E:$E) -> 46249 | P2: =_xlfn.XLOOKUP(P4,Consolidado!$A:$A,Consolidado!$E:$E) -> 46139 | Q2: =_xlfn.XLOOKUP(Q4,Consolidado!$A:$A,Consolidado!$E:$E) -> 46226 | R2: =_xlfn.XLOOKUP(R4,Consolidado!$A:$A,Consolidado!$E:$E) -> 46150 | ... AS2: =_xlfn.XLOOKUP(AS4,Consolidado!$A:$A,Consolidado!$E:$E) -> #N/A
F3: Previsão de Chegada - ETA | G3: =G2+60 -> 46318 | H3: 46153 | I3: 46142 | J3: 46187 | K3: =K2+60 -> 46294 | L3: =L2+60 -> #N/A | M3: =M2+60 -> #N/A | N3: =N2+60 -> #N/A | O3: =O2+60 -> 46309 | P3: 46191 | Q3: =Q2+60 -> 46286 | R3: =R2+60 -> 46210 | S3: =S2+60 -> 46207 | T3: =T2+60 -> 46222 | U3: =U2+60 -> 46237 | V3: =V2+60 -> 46237 | W3: =W2+60 -> 46238 | X3: =X2+60 -> 46258 | ... AS3: =AS2+60 -> #N/A
A4: Qtd | B4: Categoria | C4: GM9 Descrição | D4: Trade | E4: Código | F4: Descrição | G4: PI-BAUMON-032026 | H4: Bemol 36 | I4: Bemol 38 | J4: Bemol 39 | K4: Bemol 41 | L4: Elox 01 19/03/2026 | M4: Elox 02 27/04/2027 | N4: Elox 03 05/06/2026 | O4: Bemol 43 | P4: Bemol 45 | Q4: Bemol 46 | R4: Bemol 47 | S4: Bemol 48 | T4: Bemol 49 | U4: Bemol 50 | V4: Bemol 51 | W4: Bemol 52 | X4: Bemol 53 | Y4: Bemol 54 | Z4: Bemol 55 | AA4: Bemol 56 | AB4: Bemol 57 | AC4: Bemol 58 | AD4: Bemol 59 | AE4: Bemol 60 | AF4: Bemol 61 | AG4: Bemol 62 | AH4: Bemol 63 | AI4: Bemol 64 | AJ4: Bemol 65 | AK4: Bemol 66 | AL4: Bemol 67 | AM4: Bemol 68 | AN4: Bemol 69 | AO4: Bemol 70 | AP4: Bemol 71 | AQ4: Bemol 72 | AR4: Bemol 73 | AS4: Bemol 74 | AT4: Acumulado
A5: 1 | B5: 111001012 | C5: FRITADEIRA | D5: Timbro | E5: 238697 | F5: FRITAD BAUMON AIR FRYER 35L YJ-613D PT | H5: 1628 | AB5: 1400 | AT5: =SUM(G5:AS5) -> 3028
A6: 2 | B6: 111001012 | C6: FRITADEIRA | D6: Timbro | E6: 238698 | F6: FRITAD BAUMON AIR FRYER 12L GSE021 PT | S6: 1112 | U6: 1150 | Y6: 1112 | AD6: 2224 | AF6: 476 | AL6: 2224 | AT6: =SUM(G6:AS6) -> 8298 | AW6: 373758 | AX6: 9000
A7: 3 | B7: 111001005 | C7: CAFETEIRA | D7: Timbro | E7: 238699 | F7: CAFETEIRA BAUMON 108TS PT/PR | AT7: =SUM(G7:AS7) -> 0 | AW7: 370451 | AX7: 5000
A8: 4 | B8: 111001020 | C8: SANDUICHEIRA | D8: Timbro | E8: 238700 | F8: SANDUICHEIRA BAUMON FS-8009C PT | H8: 3804 | T8: 3000 | AQ8: 3900 | AT8: =SUM(G8:AS8) -> 10704 | AW8: 370452 | AX8: 2000
A9: 5 | B9: 111001013 | C9: GRILL | D9: Timbro | E9: 238721 | F9: GRILL BAUMON 9228D PT | T9: 1920 | AB9: 2004 | AP9: 1920 | AT9: =SUM(G9:AS9) -> 5844 | AW9: 370453 | AX9: 2004
A10: 6 | B10: 111003005 | C10: FERRO SECO | D10: Timbro | E10: 238722 | F10: FERRO BAUMON SECO LM-209A AZ | H10: 2892 | AO10: 2400 | AT10: =SUM(G10:AS10) -> 5292 | AW10: 238700 | AX10: 3900
A11: 7 | B11: 111003001 | C11: FERRO À VAPOR | D11: Timbro | E11: 238723 | F11: FERRO BAUMON VAPOR LM-2262 AZ | AA11: 2400 | AO11: 2400 | AT11: =SUM(G11:AS11) -> 4800
A12: 8 | B12: 127001014 | C12: POTES | D12: Timbro | E12: 267869 | F12: POTE HERM BAUMON RET 400ML C/ TAMPA R145 | X12: 1008 | AT12: =SUM(G12:AS12) -> 1008
A13: 9 | B13: 127001014 | C13: POTES | D13: Timbro | E13: 267870 | F13: POTE HERM BAUMON RET 630ML C/ TAMPA R170 | X13: 12960 | AT13: =SUM(G13:AS13) -> 12960
A14: 10 | B14: 127001014 | C14: POTES | D14: Timbro | E14: 267931 | F14: POTE HERM BAUMON 1410ML R220-2FULL | AT14: =SUM(G14:AS14) -> 0
A15: 11 | B15: 127001014 | C15: POTES | D15: Timbro | E15: 267932 | F15: POTE HERM BAUMON 1040ML C/TAM R195-2FULL | AG15: 1872 | AT15: =SUM(G15:AS15) -> 1872
A16: 12 | B16: 127001014 | C16: POTES | D16: Timbro | E16: 267936 | F16: POTE HERM BAUMON QD 750ML C/TAMP S150-2 | X16: 1440 | AG16: 2304 | AT16: =SUM(G16:AS16) -> 3744
A17: 13 | B17: 127001014 | C17: POTES | D17: Timbro | E17: 267937 | F17: POTE HERM BAUMON RET1020ML C/TAMP S195-3 | AG17: 1512 | AT17: =SUM(G17:AS17) -> 1512
A18: 14 | B18: 127001014 | C18: POTES | D18: Timbro | E18: 267938 | F18: POTE HERM BAUMON RET1430ML C/TAMP R220-3 | V18: 2820 | AG18: 1572 | AT18: =SUM(G18:AS18) -> 4392
A19: 15 | B19: 127001002 | C19: ASSADEIRAS/FÔRMAS | D19: Timbro | E19: 267939 | F19: ASSAD BAUMON VDR RET1600ML C/TAMP GB1600 | AG19: 1512 | AT19: =SUM(G19:AS19) -> 1512
A20: 16 | B20: 127001002 | C20: ASSADEIRAS/FÔRMAS | D20: Timbro | E20: 267940 | F20: ASSAD BAUMON VIDRO OVAL 3000ML OVAL-3000 | AG20: 1500 | AT20: =SUM(G20:AS20) -> 1500
A21: 17 | B21: 127001002 | C21: ASSADEIRAS/FÔRMAS | D21: Timbro | E21: 267941 | F21: ASSAD BAUMON VIDRO QUAD 1800ML GB-S1800 | AT21: =SUM(G21:AS21) -> 0
A22: 18 | B22: 127001006 | C22: CAÇAROLA | D22: Timbro | E22: 267942 | F22: CAÇAROLA BAUMON VIDRO 1000ML GC-1000 | AT22: =SUM(G22:AS22) -> 0
A23: 19 | B23: 127001006 | C23: CAÇAROLA | D23: Timbro | E23: 267943 | F23: CAÇAROLA BAUMON VIDRO 1500ML GC-1500 | AG23: 1992 | AT23: =SUM(G23:AS23) -> 1992
A24: 20 | B24: 127001006 | C24: CAÇAROLA | D24: Timbro | E24: 267944 | F24: CAÇAROLA BAUMON VIDRO 2000ML GC-2000 | AG24: 2040 | AT24: =SUM(G24:AS24) -> 2040
A25: 21 | B25: 127001002 | C25: ASSADEIRAS/FÔRMAS | D25: Timbro | E25: 267945 | F25: ASSADEIRA BAUMON VIDRO 1800ML GC-O1800 | AT25: =SUM(G25:AS25) -> 0
A26: 22 | B26: 127001001 | C26: ACESSÓRIOS DE COZINHA | D26: Timbro | E26: 267946 | F26: COPO MEDIDOR BAUMON VDR 500ML LB-500P | AG26: 1500 | AT26: =SUM(G26:AS26) -> 1500
A27: 23 | B27: 127001001 | C27: ACESSÓRIOS DE COZINHA | D27: Timbro | E27: 267947 | F27: COPO MEDIDOR BAUMON VDR 1000ML LB-1000P | AG27: 1584 | AT27: =SUM(G27:AS27) -> 1584
A28: 24 | B28: 127001014 | C28: POTES | D28: Timbro | E28: 268132 | F28: POTE HERM BAUMON RET 2260ML C/TAMP JL002 | V28: 2820 | X28: 7824 | AT28: =SUM(G28:AS28) -> 10644
A29: 25 | B29: 127001014 | C29: POTES | D29: Timbro | E29: 268133 | F29: POTE HERM BAUMON 1040ML C/TAMP R195 | X29: 4704 | AT29: =SUM(G29:AS29) -> 4704
A30: 26 | B30: 127001014 | C30: POTES | D30: Timbro | E30: 269686 | F30: POTE HERM BAUMON RET 630ML R170-2FULL AZ | AG30: 1512 | AT30: =SUM(G30:AS30) -> 1512
A31: 27 | B31: 127001002 | C31: ASSADEIRAS/FÔRMAS | D31: Timbro | E31: 367983 | F31: ASSADEIRA BAUMON OVAL 2800ML GC-02800 | V31: 2802 | X31: 9030 | AT31: =SUM(G31:AS31) -> 11832
A32: 28 | B32: 127001002 | C32: ASSADEIRAS/FÔRMAS | D32: Timbro | E32: 367984 | F32: ASSADEIRA BAUMON OVAL 2400ML GC-2400 | V32: 2802 | X32: 3588 | AT32: =SUM(G32:AS32) -> 6390
A33: 29 | B33: 127001027 | C33: SALADEIRAS/SOPEIRAS | D33: Timbro | E33: 367985 | F33: SALADEIRA BAUMON 880ML S880B-S | AT33: =SUM(G33:AS33) -> 0
A34: 30 | B34: 127001027 | C34: SALADEIRAS/SOPEIRAS | D34: Timbro | E34: 367986 | F34: SALADEIRA BAUMON 2400ML S2400B-S | AT34: =SUM(G34:AS34) -> 0
A35: 31 | B35: 127001027 | C35: SALADEIRAS/SOPEIRAS | D35: Timbro | E35: 367987 | F35: SALADEIRA BAUMON 3300ML S3300B-S | AT35: =SUM(G35:AS35) -> 0
A36: 32 | B36: 127001003 | C36: BANDEJAS/TRAVESSAS/BAIXELAS | D36: Timbro | E36: 383492 | F36: TRAVESSA BAUMON OVAL VIDRO C/TAMPA 2,4L | U36: 1254 | AT36: =SUM(G36:AS36) -> 1254
A37: 33 | B37: 127001003 | C37: BANDEJAS/TRAVESSAS/BAIXELAS | D37: Timbro | E37: 383493 | F37: TRAVESSA BAUMON OVAL VIDRO C/TAMPA 3L | AT37: =SUM(G37:AS37) -> 0
A38: 34 | B38: 127001003 | C38: BANDEJAS/TRAVESSAS/BAIXELAS | D38: Timbro | E38: 383494 | F38: TRAVESSA BAUMON OVAL VIDRO C/TAMPA 4L | U38: 420 | AT38: =SUM(G38:AS38) -> 420
A39: 35 | B39: 127001003 | C39: BANDEJAS/TRAVESSAS/BAIXELAS | D39: Timbro | E39: 383495 | F39: TRAVESSA BAUMON RETANGULAR C/TAMPA 1,6L | AT39: =SUM(G39:AS39) -> 0
A40: 36 | B40: 127001003 | C40: BANDEJAS/TRAVESSAS/BAIXELAS | D40: Timbro | E40: 383496 | F40: TRAVESSA BAUMON RETANGULAR C/TAMPA 2,2L | AT40: =SUM(G40:AS40) -> 0
A41: 37 | B41: 127001003 | C41: BANDEJAS/TRAVESSAS/BAIXELAS | D41: Timbro | E41: 383497 | F41: TRAVESSA BAUMON RETANGULAR C/TAMPA 3L | U41: 870 | AT41: =SUM(G41:AS41) -> 870
A42: 38 | B42: 110001009 | C42: SECADOR | D42: Timbro | E42: 272958 | F42: Secador de cabelo Baumon SD-808 | H42: 3000 | AF42: 1920 | AN42: 3636 | AT42: =SUM(G42:AS42) -> 8556
A43: 39 | B43: 110001004 | C43: CHAPA | D43: Timbro | E43: 272956 | F43: Chapinha Baumon SD-515 | H43: 2016 | AN43: 3000 | AT43: =SUM(G43:AS43) -> 5016
A44: 40 | B44: 110001004 | C44: CHAPA | D44: Timbro | E44: 272957 | F44: Chapinha Baumon SD-510 | H44: 3240 | T44: 1920 | AA44: 2160 | AT44: =SUM(G44:AS44) -> 7320
A45: 41 | B45: 110001006 | C45: ESCOVA SECADORA/MODELADORA | D45: Timbro | E45: 272959 | F45: Escova secadora Baumon SD-917 | T45: 2004 | U45: 2400 | AT45: =SUM(G45:AS45) -> 4404
A46: 42 | B46: 110001004 | C46: CHAPA | D46: Timbro | E46: 394254 | F46: Chapa Baumon GSD-510 Chumbo | U46: 2400 | AT46: =SUM(G46:AS46) -> 2400
A47: 43 | B47: 110001004 | C47: CHAPA | D47: Timbro | E47: 394253 | F47: Chapa Baumon GSD-927 Chumbo | U47: 2400 | AT47: =SUM(G47:AS47) -> 2400
A48: 44 | B48: 110001006 | C48: ESCOVA SECADORA/MODELADORA | D48: Timbro | E48: 394252 | F48: Escova rotativa Baumon GSD927 cz | U48: 2400 | AT48: =SUM(G48:AS48) -> 2400
A49: 45 | B49: 110001009 | C49: SECADOR | D49: Timbro | E49: 394251 | F49: Secador de cabelo Baumon GSD808 Cz | U49: 2400 | AT49: =SUM(G49:AS49) -> 2400
A50: 46 | B50: 111001010 | C50: ESPREMEDOR ELÉTRICO | D50: Timbro | E50: 272951 | F50: Espremedor de frutas Baumon BH-3326 | T50: 1200 | AO50: 2400 | AT50: =SUM(G50:AS50) -> 3600
A51: 47 | B51: 111003002 | C51: FERRO À VAPOR/SPRAY | D51: Timbro | E51: 272954 | F51: Ferro de passar Cerâmica Baumon DM-2088 | AO51: 2400 | AT51: =SUM(G51:AS51) -> 2400
A52: 48 | B52: 111001010 | C52: ESPREMEDOR ELÉTRICO | D52: Timbro | E52: 272750 | F52: Espremedor de frutas Baumon JE678G | AP52: 3000 | AT52: =SUM(G52:AS52) -> 3000
A53: 49 | B53: 111003006 | C53: VAPORIZADOR | D53: Timbro | E53: 272955 | F53: Vaporizador Portátil Baumon QH-08BK | P53: 1520 | AA53: 1600 | AP53: 1600 | AT53: =SUM(G53:AS53) -> 4720
A54: 50 | B54: 111001001 | C54: ACESSÓRIOS DE ELETROPORTÁTEIS | D54: Timbro | E54: 272748 | F54: Copo de vidro Baumon KP-1805 | AT54: =SUM(G54:AS54) -> 0
A55: 51 | B55: 111001017 | C55: LIQUIDIFICADOR ACIMA DE 3 VEL | D55: Timbro | E55: 272749 | F55: Liquidificador Baumon KP-1805 | P55: 1000 | AA55: 1220 | AT55: =SUM(G55:AS55) -> 2220
A56: 52 | B56: 111001016 | C56: LIQUIDIFICADOR ATÉ 3 VEL | D56: Timbro | E56: 354935 | F56: Liquidificador Baumon GSE019 | W56: 992 | AT56: =SUM(G56:AS56) -> 992
A57: 53 | B57: 111001019 | C57: PROCESSADOR DE ALIMENTOS | D57: Timbro | E57: 272953 | F57: Mini Processador WC-P02 | H57: 4008 | AP57: 3000 | AT57: =SUM(G57:AS57) -> 7008
A58: 54 | B58: 117001006 | C58: FORNO ELÉTRICO | D58: Timbro | E58: 358232 | F58: Forno Elét bancada Baumon 48L JK48A PT | AT58: =SUM(G58:AS58) -> 0
A59: 55 | B59: 117001006 | C59: FORNO ELÉTRICO | D59: Timbro | E59: 387147 | F59: Forno Elét bancada Baumon 60L JK60A PT | R59: 500 | AT59: =SUM(G59:AS59) -> 500
A60: 56 | B60: 117006005 | C60: FRIGOBAR | D60: Timbro | E60: 358229 | F60: Frigobar Baumon 46L HC46 BR | Z60: 1160 | AM60: 1160 | AT60: =SUM(G60:AS60) -> 2320
A61: 57 | B61: 117006005 | C61: FRIGOBAR | D61: Timbro | E61: 358230 | F61: Frigobar Baumon 87L HC87 BR | AT61: =SUM(G61:AS61) -> 0
A62: 58 | B62: 117006005 | C62: FRIGOBAR | D62: Timbro | E62: 358231 | F62: Frigobar Baumon 112L BCD112 BR | AT62: =SUM(G62:AS62) -> 0
A63: 59 | B63: 111001019 | C63: PROCESSADOR DE ALIMENTOS | D63: Timbro | E63: 358233 | F63: Máquina de gelo Baumon HC-2 PT | P63: 800 | AF63: 800 | AN63: 1400 | AT63: =SUM(G63:AS63) -> 3000
A64: 60 | B64: 117001002 | C64: BEBEDOURO DE MESA | D64: Timbro | E64: 358234 | F64: Bebedouro de Mesa Baumon YLRLW2540TBS BR | AC64: 1480 | AT64: =SUM(G64:AS64) -> 1480
A65: 61 | B65: 117001001 | C65: BEBEDOURO DE COLUNA | D65: Timbro | E65: 358235 | F65: Bebedouro Baumon YLRLW2540LB BR | AC65: 1180 | AE65: 630 | AT65: =SUM(G65:AS65) -> 1810
A66: 62 | B66: 117001001 | C66: BEBEDOURO DE COLUNA | D66: Timbro | E66: 358236 | F66: Bebedouro Baumon YLRLW2540LBB PT | AC66: 3450 | AT66: =SUM(G66:AS66) -> 3450
A67: 63 | B67: 117001001 | C67: BEBEDOURO DE COLUNA | D67: Timbro | E67: 358237 | F67: Bebedouro Baumon YLRLW2540LBS BR | AC67: 1300 | AT67: =SUM(G67:AS67) -> 1300
A68: 64 | B68: 130001013 | C68: SUPORTES | D68: Timbro | E68: 370451 | F68: Sup p/TV Baumon Fixo LCD-800 PT | AA68: 5000 | AQ68: 5000 | AT68: =SUM(G68:AS68) -> 10000
A69: 65 | B69: 130001013 | C69: SUPORTES | D69: Timbro | E69: 373758 | F69: Sup p/TV Baumon Universal YN-LED002 PT | AP69: 3000 | AQ69: 9000 | AT69: =SUM(G69:AS69) -> 12000
A70: 66 | B70: 130001013 | C70: SUPORTES | D70: Timbro | E70: 370452 | F70: Sup p/TV Baumon fixo YN-109MF PT | AA70: 2200 | AQ70: 2000 | AT70: =SUM(G70:AS70) -> 4200
A71: 67 | B71: 130001013 | C71: SUPORTES | D71: Timbro | E71: 370453 | F71: Sup p/TV Baumon Articulado YN-927AT PT | P71: 2004 | AA71: 900 | AQ71: 2004 | AT71: =SUM(G71:AS71) -> 4908
A72: 68 | B72: 107001003 | C72: LENÇOL | D72: Timbro | E72: 373481 | F72: Jogo de Cama solteiro Baumon 100% penteado 180 fios azul | I72: 300 | AT72: =SUM(G72:AS72) -> 300
A73: 69 | B73: 107001003 | C73: LENÇOL | D73: Timbro | E73: 373482 | F73: Jogo de Cama solteiro Baumon 100% penteado 180 fios bege | I73: 300 | AT73: =SUM(G73:AS73) -> 300
A74: 70 | B74: 107001003 | C74: LENÇOL | D74: Timbro | E74: 373483 | F74: Jogo de Cama solteiro Baumon 100% penteado 180 fios verde | AT74: =SUM(G74:AS74) -> 0
A75: 71 | B75: 107001003 | C75: LENÇOL | D75: Timbro | E75: 387143 | F75: Jogo de Cama solteiro Baumon 100% penteado 180 fios rosa | I75: 300 | AT75: =SUM(G75:AS75) -> 300
A76: 72 | B76: 107001003 | C76: LENÇOL | D76: Timbro | E76: 373484 | F76: Jogo de cama casal Baumon 100% penteado 200 fios azul | I76: 372 | AT76: =SUM(G76:AS76) -> 372
A77: 73 | B77: 107001003 | C77: LENÇOL | D77: Timbro | E77: 373485 | F77: Jogo de cama casal Baumon 100% penteado 200 fios bege | I77: 372 | AT77: =SUM(G77:AS77) -> 372
A78: 74 | B78: 107001003 | C78: LENÇOL | D78: Timbro | E78: 373486 | F78: Jogo de cama casal Baumon 100% penteado 200 fios verde | I78: 372 | AT78: =SUM(G78:AS78) -> 372
A79: 75 | B79: 107001003 | C79: LENÇOL | D79: Timbro | E79: 387144 | F79: Jogo de cama casal Baumon 100% penteado 200 fios Branco | I79: 372 | AI79: 360 | AK79: 360 | AT79: =SUM(G79:AS79) -> 1092
A80: 76 | B80: 107001003 | C80: LENÇOL | D80: Timbro | E80: 373487 | F80: Jogo de cama Queen Baumon 100% penteado 200 fios Azul | I80: 380 | AT80: =SUM(G80:AS80) -> 380
A81: 77 | B81: 107001003 | C81: LENÇOL | D81: Timbro | E81: 373488 | F81: Jogo de cama Queen Baumon 100% penteado 200 fios bege | I81: 380 | AT81: =SUM(G81:AS81) -> 380
A82: 78 | B82: 107001003 | C82: LENÇOL | D82: Timbro | E82: 373489 | F82: Jogo de cama Queen Baumon 100% penteado 200 fios verde | I82: 380 | AT82: =SUM(G82:AS82) -> 380
A83: 79 | B83: 107001003 | C83: LENÇOL | D83: Timbro | E83: 387145 | F83: Jogo de cama Queen Baumon 100% penteado 200 fios Branco | I83: 380 | AI83: 350 | AK83: 350 | AT83: =SUM(G83:AS83) -> 1080
A84: 80 | B84: 107001003 | C84: LENÇOL | D84: Timbro | E84: 373490 | F84: Jogo de cama King Baumon 100% penteado 200 fios Azul | I84: 352 | AT84: =SUM(G84:AS84) -> 352
A85: 81 | B85: 107001003 | C85: LENÇOL | D85: Timbro | E85: 373491 | F85: Jogo de cama King Baumon 100% penteado 200 fios Bege | I85: 352 | AT85: =SUM(G85:AS85) -> 352
A86: 82 | B86: 107001003 | C86: LENÇOL | D86: Timbro | E86: 373492 | F86: Jogo de cama King Baumon 100% penteado 200 fios Verde | I86: 352 | AT86: =SUM(G86:AS86) -> 352
A87: 83 | B87: 107001003 | C87: LENÇOL | D87: Timbro | E87: 387146 | F87: Jogo de cama King Baumon 100% penteado 200 fios Branco | I87: 352 | AI87: 352 | AK87: 352 | AT87: =SUM(G87:AS87) -> 1056
A88: 84 | B88: 107001003 | C88: LENÇOL | D88: Timbro | E88: 387131 | F88: JG 4P CAMA CASAL BAUMON T-200 PARIS | AI88: 252 | AK88: 252 | AT88: =SUM(G88:AS88) -> 504
A89: 85 | B89: 107001003 | C89: LENÇOL | D89: Timbro | E89: 387132 | F89: JG 4P CAMA CASAL BAUMON T-200 SEVILHA | AI89: 252 | AK89: 252 | AT89: =SUM(G89:AS89) -> 504
A90: 86 | B90: 107001003 | C90: LENÇOL | D90: Timbro | E90: 387133 | F90: JG 4P CAMA CASAL BAUMON T-200 LISBOA | AI90: 252 | AK90: 252 | AT90: =SUM(G90:AS90) -> 504
A91: 87 | B91: 107001003 | C91: LENÇOL | D91: Timbro | E91: 387134 | F91: JG 4P CAMA CASAL BAUMON T-200 ISTAMBUL | AI91: 252 | AK91: 252 | AT91: =SUM(G91:AS91) -> 504
A92: 88 | B92: 107001003 | C92: LENÇOL | D92: Timbro | E92: 387135 | F92: JG 4P CAMA QUEEN BAUMON T-200 PARIS | AI92: 250 | AK92: 250 | AT92: =SUM(G92:AS92) -> 500
A93: 89 | B93: 107001003 | C93: LENÇOL | D93: Timbro | E93: 387136 | F93: JG 4P CAMA QUEEN BAUMON T-200 SEVILHA | AI93: 250 | AK93: 250 | AT93: =SUM(G93:AS93) -> 500
A94: 90 | B94: 107001003 | C94: LENÇOL | D94: Timbro | E94: 387137 | F94: JG 4P CAMA QUEEN BAUMON T-200 LISBOA | AI94: 250 | AK94: 250 | AT94: =SUM(G94:AS94) -> 500
A95: 91 | B95: 107001003 | C95: LENÇOL | D95: Timbro | E95: 387138 | F95: JG 4P CAMA QUEEN BAUMON T-200 ISTAMBU | AI95: 250 | AK95: 250 | AT95: =SUM(G95:AS95) -> 500
A96: 92 | B96: 107001003 | C96: LENÇOL | D96: Timbro | E96: 387139 | F96: JG 4P CAMA KING BAUMON T-200 PARIS | AI96: 256 | AK96: 256 | AT96: =SUM(G96:AS96) -> 512
A97: 93 | B97: 107001003 | C97: LENÇOL | D97: Timbro | E97: 387140 | F97: JG 4P CAMA KING BAUMON T-200 SEVILHA | AI97: 256 | AK97: 256 | AT97: =SUM(G97:AS97) -> 512
A98: 94 | B98: 107001003 | C98: LENÇOL | D98: Timbro | E98: 387141 | F98: JG 4P CAMA KING BAUMON T-200 LISBOA | AI98: 256 | AK98: 256 | AT98: =SUM(G98:AS98) -> 512
A99: 95 | B99: 107001003 | C99: LENÇOL | D99: Timbro | E99: 387142 | F99: JG 4P CAMA KING BAUMON T-200 ISTAMBUL | AI99: 256 | AK99: 256 | AT99: =SUM(G99:AS99) -> 512
... A102: 98 | B102: 107001004 | C102: TOALHA DE BANHO | D102: Timbro | E102: 373495 | F102: 1 toalha 100% algodão Baumon (126cm x 68 cm) 500 GSM + Rosto rosa | AI102: 792 | AK102: 792 | AT102: =SUM(G102:AS102) -> 1584
...

Sheet Base de Dados
A1: Qtd | B1: Forn. | C1: Pedido de compra | D1: INVOICE | E1: HBL | F1: Container | G1: Variedade de SKU | H1: Produtos | I1: Profundidade de SKU Container | J1: Custo em Dólar ($) | K1: Processo | L1: Modal | M1: Valor Mercadoria (R$) | N1: Frete (R$) | O1: Seguro (R$) | P1: SISCOMEX | Q1: Despachante | R1: Frete Local | S1: COFINS | T1: PIS | U1: Total | V1: % Frete | W1: Localização | X1: Status | Y1: DIAS ATÉ CHEGADA | Z1: ESTIMATIVA CHEGADA | AA1: PRONTIDÃO
A2: 1 | B2: TIMBRO SWISS SA | C2: 4508010244 | D2: BEMOL003A | E2: NBOMAU25010624 | F2: MSMU4593106 | G2: =COUNTIF(Precificação!A:A,'Base de Dados'!D25) -> 7 | H2: CAFETEIRA , SANDUICHEIRA E GRILL | I2: =SUMIF(Precificação!A:A,D2,Precificação!F:F) -> 7074 | J2: 58189.26 | K2: 2025000082 | L2: Marítimo | M2: 330817.58 | N2: 36953.8 | O2: 181.93 | P2: 192.79 | Q2: 1537.1 | R2: 1300 | S2: 35507.49 | T2: 7727.02 | U2: =SUM(M2:T2) -> 414217.71 | V2: =N2/M2 -> 0.11170446 | W2: CHINA | X2: =IF(K2<>"", "CONCLUÍDO", IF(E2<>"", "EM TRÂNSITO", "EM PRODUÇÃO")) -> CONCLUÍDO | Z2: 46026
A3: =A2+1 -> 2 | B3: TIMBRO SWISS SA | C3: 4508031503 | D3: BEMOL003B | E3: NBOMAU25010647 | F3: MSBU8251514 | G3: =COUNTIF(Precificação!A:A,'Base de Dados'!D26) -> 1 | H3: CAFETEIRA ,FERROS E GRILL | I3: =SUMIF(Precificação!A:A,D3,Precificação!F:F) -> 8630 | J3: 62940.5 | K3: 2025000097 | L3: Marítimo | M3: 361416.94 | N3: 37324.3 | O3: 198.79 | P3: 254.49 | Q3: 1537.1 | R3: 1300 | S3: 38497.72 | T3: 8377.74 | U3: =SUM(M3:T3) -> 448907.08 | V3: =N3/M3 -> 0.10327214 | W3: CHINA | X3: =IF(K3<>"", "CONCLUÍDO", IF(E3<>"", "EM TRÂNSITO", "EM PRODUÇÃO")) -> CONCLUÍDO | Z3: 46026
A4: =A3+1 -> 3 | B4: TIMBRO SWISS SA | C4: 4508173581 | D4: BEMOL004 | E4: NBOMAU25040862 | F4: MEDU4437814/ MSNU7504404 | G4: =COUNTIF(Precificação!A:A,'Base de Dados'!D27) -> 15 | H4: VIDROS BAUMON | I4: =SUMIF(Precificação!A:A,D4,Precificação!F:F) -> 37782 | J4: 68555.52 | K4: 2025000164 | L4: Marítimo | M4: 378515.59 | N4: 29815.02 | O4: 208.15 | P4: 254.49 | Q4: 1537.1 | R4: 1300 | S4: 39423.99 | T4: 8579.32 | U4: =SUM(M4:T4) -> 459633.66 | V4: =N4/M4 -> 0.078768275 | W4: CHINA | X4: =IF(K4<>"", "CONCLUÍDO", IF(E4<>"", "EM TRÂNSITO", "EM PRODUÇÃO")) -> CONCLUÍDO | Z4: 46026
A5: =A4+1 -> 4 | B5: TIMBRO SWISS SA | C5: 4508529711 | D5: BEMOL 10 | E5: NBBLU25018879 | F5: MSMU7127483 | G5: =COUNTIF(Precificação!A:A,'Base de Dados'!D23) -> 7 | H5: MÁQ. DE GELO + (3) SUP DE TV + MINI PROC + ESPREMEDOR | I5: =SUMIF(Precificação!A:A,D5,Precificação!F:F) -> 18234 | J5: 86089.58 | K5: 2026000006 | L5: Marítimo | M5: 464528.27 | N5: 16164.31 | O5: 255.51 | P5: 254.49 | Q5: 1549 | R5: 1300 | S5: 46411.46 | T5: 10099.89 | U5: =SUM(M5:T5) -> 540562.93 | V5: =N5/M5 -> 0.034797258 | W5: CHINA | X5: =IF(K5<>"", "CONCLUÍDO", IF(E5<>"", "EM TRÂNSITO", "EM PRODUÇÃO")) -> CONCLUÍDO | Z5: 45988
A6: =A5+1 -> 5 | B6: TIMBRO SWISS SA | C6: 4508525585 | D6: BEMOL 14 | E6: QOBLU25010198 | F6: MSBU8122306/ MEDU8122306 | G6: =COUNTIF(Precificação!A:A,'Base de Dados'!D22) -> 1 | H6: VIDROS BOROSSILICATO - REPOSIÇÃO 02 | I6: =SUMIF(Precificação!A:A,D6,Precificação!F:F) -> 24720 | J6: 56730.42 | K6: 2026000001 | L6: Marítimo | M6: 314224.12 | N6: 32125.62 | O6: 172.81 | P6: 192.79 | Q6: 1549 | R6: 1300 | S6: 33439.42 | T6: 7276.97 | U6: =SUM(M6:T6) -> 390280.73 | V6: =N6/M6 -> 0.10223792 | W6: CHINA | X6: =IF(K6<>"", "CONCLUÍDO", IF(E6<>"", "EM TRÂNSITO", "EM PRODUÇÃO")) -> CONCLUÍDO | Z6: 45990
A7: =A6+1 -> 6 | B7: TIMBRO SWISS SA | C7: 4508684160 | D7: BEMOL 17 | E7: KHI1847MUN | F7: HAMU2329387 | G7: =COUNTIF(Precificação!A:A,'Base de Dados'!D13) -> 10 | H7: JOGO DE CAMA | I7: =SUMIF(Precificação!A:A,D7,Precificação!F:F) -> 10800 | J7: 103783.24 | K7: 2026000103 | L7: Marítimo | M7: 542869.37 | N7: 15200.7 | O7: 298.57 | P7: 192.79 | Q7: 1537.1 | R7: 1300 | S7: 57232.81 | T7: 11725.75 | U7: =SUM(M7:T7) -> 630357.09 | V7: =N7/M7 -> 0.028000659 | W7: CHINA | X7: =IF(K7<>"", "CONCLUÍDO", IF(E7<>"", "EM TRÂNSITO", "EM PRODUÇÃO")) -> CONCLUÍDO | Z7: 46020
A8: =A7+1 -> 7 | B8: TIMBRO SWISS SA | C8: 4508624477 | D8: BEMOL 18 | E8: I245708 | F8: SEM CTN | G8: =COUNTIF(Precificação!A:A,'Base de Dados'!D3) -> 4 | H8: LENÇÓIS BAUMON | I8: =SUMIF(Precificação!A:A,D8,Precificação!F:F) -> 2564 | J8: 42092.08 | K8: 2026000062 | L8: Aéreo | M8: 218904.07 | N8: 31063.2 | O8: 117.64 | P8: 154.23 | Q8: 1537.1 | R8: 1300 | S8: 20109.87 | T8: 4120.05 | U8: =SUM(M8:T8) -> 277306.16 | V8: =N8/M8 -> 0.14190325 | W8: CHINA | X8: =IF(K8<>"", "CONCLUÍDO", IF(E8<>"", "EM TRÂNSITO", "EM PRODUÇÃO")) -> CONCLUÍDO | Z8: 46020
A9: =A8+1 -> 8 | B9: TIMBRO SWISS SA | C9: 4508591119 | D9: BEMOL 19 | E9: KDBW25110028 | F9: ONEU1824259 | G9: =COUNTIF(Precificação!A:A,'Base de Dados'!D2) -> 3 | H9: POTES/TRAVESSAS/SALEIRAS | I9: =SUMIF(Precificação!A:A,D9,Precificação!F:F) -> 33816 | J9: 63051.04 | K9: 2026000040 | L9: Marítimo | M9: 326843.98 | N9: 27007.6 | O9: 117.64 | P9: 154.23 | Q9: 1537.1 | R9: 1300 | S9: 20109.87 | T9: 4120.05 | U9: =SUM(M9:T9) -> 381190.47 | V9: =N9/M9 -> 0.082631475 | W9: CHINA | X9: =IF(K9<>"", "CONCLUÍDO", IF(E9<>"", "EM TRÂNSITO", "EM PRODUÇÃO")) -> CONCLUÍDO | Z9: 46020
A10: =A9+1 -> 9 | B10: TIMBRO SWISS SA | C10: 4508436265 | D10: BEMOL 20 | E10: SHYY25114820 | F10: ONEU6318757 | G10: =COUNTIF(Precificação!A:A,'Base de Dados'!D24) -> 2 | H10: FRITADEIRA AIR FRYER 12 L + SANDUICHEIRA + FERRO SECO | I10: =SUMIF(Precificação!A:A,D10,Precificação!F:F) -> 6104 | J10: 57048.8 | K10: 2026000015 | L10: Marítimo | M10: 359379.14 | N10: 14506.06 | O10: 168.71 | P10: 223.64 | Q10: 1549 | R10: 1300 | S10: 31014.33 | T10: 6749.23 | U10: =SUM(M10:T10) -> 414890.11 | V10: =N10/M10 -> 0.040364224 | W10: CHINA | X10: =IF(K10<>"", "CONCLUÍDO", IF(E10<>"", "EM TRÂNSITO", "EM PRODUÇÃO")) -> CONCLUÍDO | Z10: 46026
A11: =A10+1 -> 10 | B11: TIMBRO SWISS SA | C11: 4508615909 | D11: BEMOL 21 | E11: KDBW25110063 | F11: TCNU6619092 | G11: =COUNTIF(Precificação!A:A,'Base de Dados'!D8) -> 4 | H11: VIDROS REPOSIÇÃO 4 + LED 002 | I11: =SUMIF(Precificação!A:A,D11,Precificação!F:F) -> 22384 | J11: 50232.4 | K11: 2026000053 | L11: Marítimo | M11: 262655.17 | N11: 12026.24 | O11: 144.47 | P11: 192.79 | Q11: 1537.1 | R11: 1300 | S11: 131724.89 | T11: 28665.51 | U11: =SUM(M11:T11) -> 438246.17 | V11: =N11/M11 -> 0.045787182 | W11: CHINA | X11: =IF(K11<>"", "CONCLUÍDO", IF(E11<>"", "EM TRÂNSITO", "EM PRODUÇÃO")) -> CONCLUÍDO | Z11: 46036
A12: =A11+1 -> 11 | B12: TIMBRO SWISS SA | C12: 4508645458 | D12: BEMOL 22 | E12: TAO31126537 | F12: MEDU7602018 / BMOU6778070 | G12: =COUNTIF(Precificação!A:A,'Base de Dados'!D11) -> 7 | H12: RECOMPRA VIDRO | I12: =SUMIF(Precificação!A:A,D12,Precificação!F:F) -> 28042 | J12: 62843.66 | K12: 2026000080 | L12: Marítimo | M12: 332254.43 | N12: 24225.03 | O12: 212.06 | P12: 192.79 | Q12: 1537.1 | R12: 1300 | S12: 34420.73 | T12: 7490.52 | U12: =SUM(M12:T12) -> 401632.66 | V12: =N12/M12 -> 0.072911082 | W12: CHINA | X12: =IF(K12<>"", "CONCLUÍDO", IF(E12<>"", "EM TRÂNSITO", "EM PRODUÇÃO")) -> CONCLUÍDO | Z12: 46061
A13: =A12+1 -> 12 | B13: TIMBRO SWISS SA | C13: 4508657825 | D13: BEMOL 23 | E13: TAO31126540 | F13: MSDU7322380 | G13: =COUNTIF(Precificação!A:A,'Base de Dados'!D12) -> 15 | H13: RECOMPRA VIDRO | I13: =SUMIF(Precificação!A:A,D13,Precificação!F:F) -> 20752 | J13: 34978.32 | K13: 2026000086 | L13: Marítimo | M13: 168515.84 | N13: 12027.03 | O13: 107.32 | P13: 154.23 | Q13: 1537.1 | R13: 1300 | S13: 17432.74 | T13: 3793.64 | U13: =SUM(M13:T13) -> 204867.9 | V13: =N13/M13 -> 0.071370323 | W13: CHINA | X13: =IF(K13<>"", "CONCLUÍDO", IF(E13<>"", "EM TRÂNSITO", "EM PRODUÇÃO")) -> CONCLUÍDO | Z13: 46071
A14: =A13+1 -> 13 | B14: TIMBRO SWISS SA | C14: 4508803268 | D14: BEMOL 24 | E14: KHI1874MUN | F14: FANU3705454 | G14: =COUNTIF(Precificação!A:A,'Base de Dados'!D17) -> 1 | H14: CAMA, MESA E BANHO | I14: =SUMIF(Precificação!A:A,D14,Precificação!F:F) -> 10436 | J14: 61996.38 | K14: 2026000140 | L14: Marítimo | M14: 303776.06 | N14: 14484.1 | O14: 167.09 | P14: 154.23 | Q14: 1537.1 | R14: 1300 | S14: 32638.79 | T14: 6686.97 | U14: =SUM(M14:T14) -> 360744.34 | V14: =N14/M14 -> 0.047680189 | W14: CHINA | X14: =IF(K14<>"", "CONCLUÍDO", IF(E14<>"", "EM TRÂNSITO", "EM PRODUÇÃO")) -> CONCLUÍDO | Z14: 46112
A15: =A14+1 -> 14 | B15: TIMBRO SWISS SA | C15: 4508532679 | D15: BEMOL 25 | E15: NBBLU25020450 | F15: FFAU2354768/ MEDU8128285/ MSMU6226537/MSNU5842887/ TCLU7779400/ TCNU8726382/ UETU7070845 | G15: =COUNTIF(Precificação!A:A,'Base de Dados'!D5) -> 5 | H15: BEBEDOUROS | I15: =SUMIF(Precificação!A:A,D15,Precificação!F:F) -> 5595 | J15: 243932.75 | K15: 2026000045 | L15: Marítimo | M15: 691179.5 | N15: 77292.6 | O15: 705.41 | P15: 223.64 | Q15: 1537.1 | R15: 1300 | S15: 131724.92 | T15: 28665.53 | U15: =SUM(M15:T15) -> 932628.7 | V15: =N15/M15 -> 0.1118271 | W15: CHINA | X15: =IF(K15<>"", "CONCLUÍDO", IF(E15<>"", "EM TRÂNSITO", "EM PRODUÇÃO")) -> CONCLUÍDO | Z15: 46045
A16: =A15+1 -> 15 | B16: TIMBRO SWISS SA | C16: 4508642248 | D16: BEMOL 26 | E16: NBBLU25020957 | F16: BMOU6778070 | G16: =COUNTIF(Precificação!A:A,'Base de Dados'!D7) -> 17 | H16: AIRFRYER 12L | I16: =SUMIF(Precificação!A:A,D16,Precificação!F:F) -> 1112 | J16: 42044.72 | K16: 2026000074 | L16: Marítimo | M16: 222290.43 | N16: 12551.5 | O16: 122.24 | P16: 154.23 | Q16: 1537.1 | R16: 1300 | S16: 22674.04 | T16: 4934.25 | U16: =SUM(M16:T16) -> 265563.79 | V16: =N16/M16 -> 0.056464419 | W16: CHINA | X16: =IF(K16<>"", "CONCLUÍDO", IF(E16<>"", "EM TRÂNSITO", "EM PRODUÇÃO")) -> CONCLUÍDO | Z16: 46060
A17: =A16+1 -> 16 | B17: TIMBRO SWISS SA | C17: 4508642952 | D17: BEMOL 27 | E17: NBBLU25020986 | F17: MSNU8455500 | G17: =COUNTIF(Precificação!A:A,'Base de Dados'!D9) -> 15 | H17: AIRFRYER 3,5L | I17: =SUMIF(Precificação!A:A,D17,Precificação!F:F) -> 2112 | J17: 36072.96 | K17: 2026000077 | L17: Marítimo | M17: 190717.74 | N17: 12270.97 | O17: 104.89 | P17: 154.23 | Q17: 1537.1 | R17: 1300 | S17: 19598.53 | T17: 4264.97 | U17: =SUM(M17:T17) -> 229948.43 | V17: =N17/M17 -> 0.064340999 | W17: CHINA | X17: =IF(K17<>"", "CONCLUÍDO", IF(E17<>"", "EM TRÂNSITO", "EM PRODUÇÃO")) -> CONCLUÍDO | Z17: 46073
A18: =A17+1 -> 17 | B18: TIMBRO SWISS SA | C18: 4508628310 | D18: BEMOL 28 | E18: NBBLU25020836 | F18: MSMU5480383 | G18: =COUNTIF(Precificação!A:A,'Base de Dados'!D6) -> 14 | H18: FRIGOBAR | I18: =SUMIF(Precificação!A:A,D18,Precificação!F:F) -> 575 | J18: 28359 | K18: 2026000068 | L18: Marítimo | M18: 146564.98 | N18: 12002.01 | O18: 80.62 | P18: 154.23 | Q18: 1537.1 | R18: 1300 | S18: 15309.49 | T18: 3331.6 | U18: =SUM(M18:T18) -> 180280.03 | V18: =N18/M18 -> 0.081888661 | W18: CHINA | X18: =IF(K18<>"", "CONCLUÍDO", IF(E18<>"", "EM TRÂNSITO", "EM PRODUÇÃO")) -> CONCLUÍDO | Z18: 46020
A19: =A18+1 -> 18 | B19: TIMBRO SWISS SA | C19: 4508645302 | D19: BEMOL 29 | E19: NBBLU25020956 | F19: TCLU7890497 | G19: =COUNTIF(Precificação!A:A,'Base de Dados'!D10) -> 3 | H19: FRIGOBAR HC46 + FERRO A VAPOR | I19: =SUMIF(Precificação!A:A,D19,Precificação!F:F) -> 2525 | J19: 32826 | K19: 2026000078 | L19: Marítimo | M19: 173551.06 | N19: 11102.7 | O19: 95.43 | P19: 192.79 | Q19: 1537.1 | R19: 1300 | S19: 17966.7 | T19: 3909.85 | U19: =SUM(M19:T19) -> 209655.63 | V19: =N19/M19 -> 0.06397368 | W19: CHINA | X19: =IF(K19<>"", "CONCLUÍDO", IF(E19<>"", "EM TRÂNSITO", "EM PRODUÇÃO")) -> CONCLUÍDO | Z19: 46067
A20: =A19+1 -> 19 | B20: TIMBRO SWISS SA | C20: 4508532742 | D20: BEMOL 31 | E20: CKBLU26005229 | F20: BMOU6580654/MSNU5267237 | G20: =COUNTIF(Precificação!A:A,'Base de Dados'!D16) -> 1 | H20: 9 POTES DE VIDRO | I20: =SUMIF(Precificação!A:A,D20,Precificação!F:F) -> 42972 | J20: 69733.56 | K20: 2026000132 | L20: Marítimo | M20: 345787.8 | N20: 23048.04 | O20: 190.17 | P20: 192.79 | Q20: 1537.1 | R20: 1300 | S20: 35611 | T20: 7749.54 | U20: =SUM(M20:T20) -> 415416.44 | V20: =N20/M20 -> 0.066653711 | W20: CHINA | X20: =IF(K20<>"", "CONCLUÍDO", IF(E20<>"", "EM TRÂNSITO", "EM PRODUÇÃO")) -> CONCLUÍDO | Z20: 46112
A21: =A20+1 -> 20 | B21: TIMBRO SWISS SA | C21: 4508626352 | D21: BEMOL 32 | E21: MFS-193 | F21: MFS-193 | G21: =COUNTIF(Precificação!A:A,'Base de Dados'!D4) -> 19 | H21: LENÇÓIS | I21: =SUMIF(Precificação!A:A,D21,Precificação!F:F) -> 2442 | J21: 13618.8 | K21: 2026000064 | L21: Aéreo | M21: 70825.93 | N21: 125250.42 | O21: 117.64 | P21: 154.23 | Q21: 1537.1 | R21: 1300 | S21: 20109.87 | T21: 4120.05 | U21: =SUM(M21:T21) -> 223415.24 | V21: =N21/M21 -> 1.7684261 | W21: CHINA | X21: =IF(K21<>"", "CONCLUÍDO", IF(E21<>"", "EM TRÂNSITO", "EM PRODUÇÃO")) -> CONCLUÍDO | Z21: 46020
A22: =A21+1 -> 21 | B22: TIMBRO SWISS SA | C22: 4508770727 | D22: BEMOL 33 | E22: NGB31164863 | F22: TGBU6867268 | G22: =COUNTIF(Precificação!A:A,'Base de Dados'!D18) -> 1 | H22: AIR FREYER | I22: =SUMIF(Precificação!A:A,D22,Precificação!F:F) -> 2112 | J22: 36072.96 | K22: 2026000148 | L22: Marítimo | M22: 179675.81 | N22: 14599.02 | O22: 115.66 | P22: 154.23 | Q22: 1537.1 | R22: 1300 | S22: 18758.68 | T22: 4082.2 | U22: =SUM(M22:T22) -> 220222.7 | V22: =N22/M22 -> 0.081252006 | W22: CHINA | X22: =IF(K22<>"", "CONCLUÍDO", IF(E22<>"", "EM TRÂNSITO", "EM PRODUÇÃO")) -> CONCLUÍDO | Z22: 46156
A23: =A22+1 -> 22 | B23: TIMBRO SWISS SA | C23: 4508779388 | D23: BEMOL 34 | E23: SHA31176965 | F23: HAMU4323916/BMOU4956439 | G23: =COUNTIF(Precificação!A:A,'Base de Dados'!D19) -> 2 | H23: VIDROS REP BAUMON | I23: =SUMIF(Precificação!A:A,D23,Precificação!F:F) -> 31572 | J23: 65027.52 | K23: 2026000152 | L23: Marítimo | M23: 327595.64 | N23: 27204.12 | O23: 180 | P23: 154.23 | Q23: 1537.1 | R23: 1300 | S23: 34255.57 | T23: 7454.59 | U23: =SUM(M23:T23) -> 399681.25 | V23: =N23/M23 -> 0.083041765 | W23: CHINA | X23: =IF(K23<>"", "CONCLUÍDO", IF(E23<>"", "EM TRÂNSITO", "EM PRODUÇÃO")) -> CONCLUÍDO | Z23: 46109
A24: =A23+1 -> 23 | B24: TIMBRO SWISS SA | C24: 4508750228 | D24: BEMOL 35 | E24: SZXS074568 | F24: MSDU5172851 MSDU6329101 MSMU4423326 MSMU6142797 MSMU6958287 TGBU4396106 | G24: =COUNTIF(Precificação!A:A,'Base de Dados'!D15) -> 9 | H24: POTES | I24: =SUMIF(Precificação!A:A,D24,Precificação!F:F) -> 6632 | J24: 110222.68 | K24: 2026000133 | L24: Marítimo | M24: 546561.2 | N24: 60618.32 | O24: 300.6 | P24: 192.79 | Q24: 1537.1 | R24: 1300 | S24: 58621.94 | T24: 12757.08 | U24: =SUM(M24:T24) -> 681889.03 | V24: =N24/M24 -> 0.11090857 | W24: CHINA | X24: =IF(K24<>"", "CONCLUÍDO", IF(E24<>"", "EM TRÂNSITO", "EM PRODUÇÃO")) -> CONCLUÍDO | Z24: 46020
A25: =A24+1 -> 24 | B25: TIMBRO SWISS SA | C25: 4508751729 | D25: BEMOL 36 | E25: NGB31166038 | F25: HAMU1718065/ HLXU8221843 | G25: =COUNTIF(Precificação!A:A,'Base de Dados'!D28) -> 1 | H25: AIR FRYER 3,5L + PROCESSADOR+ SANDUICHEIRA+ FERRO+ CHAPINHA | I25: =SUMIF(Precificação!A:A,D25,Precificação!F:F) -> 20588 | J25: 134205.56 | K25: 2026000217 | L25: Marítimo | M25: 686810.37 | N25: 28719.97 | O25: 427.47 | P25: 331.62 | Q25: 1537.1 | R25: 1500 | S25: 69089.89 | T25: 15035.08 | U25: =SUM(M25:T25) -> 803451.5 | V25: =N25/M25 -> 0.041816448 | W25: CHINA | X25: =IF(K25<>"", "CONCLUÍDO", IF(E25<>"", "EM TRÂNSITO", "EM PRODUÇÃO")) -> CONCLUÍDO | Z25: 46150
A26: =A25+1 -> 25 | B26: TIMBRO SWISS SA | C26: 4508696481 | D26: BEMOL 37 | E26: CAN31112406 | F26: TGBU5940960/FANU3854801 | G26: =COUNTIF(Precificação!A:A,'Base de Dados'!D14) -> 18 | H26: FORNO ELÉTRICO 46L | I26: =SUMIF(Precificação!A:A,D26,Precificação!F:F) -> 1282 | J26: 39524.06 | K26: 2026000106 | L26: Marítimo | M26: 204161.53 | N26: 20723.99 | O26: 112.3 | P26: 154.23 | Q26: 1537.1 | R26: 1300 | S26: 21712.29 | T26: 4724.95 | U26: =SUM(M26:T26) -> 254426.39 | V26: =N26/M26 -> 0.10150781 | W26: CHINA | X26: =IF(K26<>"", "CONCLUÍDO", IF(E26<>"", "EM TRÂNSITO", "EM PRODUÇÃO")) -> CONCLUÍDO | Z26: 46081
A27: =A26+1 -> 26 | B27: TIMBRO SWISS SA | C27: 4508840421 | D27: BEMOL 38 | E27: KHI2062MUN | F27: TCNU6401006 | G27: =COUNTIF(Precificação!A:A,'Base de Dados'!D31) -> 6 | H27: CAMA, MESA E BANHO | I27: =SUMIF(Precificação!A:A,D27,Precificação!F:F) -> 5316 | J27: 78626.8 | L27: Marítimo | M27: 0 | N27: 0 | O27: 0 | P27: 0 | Q27: 1537.1 | R27: 1300 | S27: 0 | T27: 0 | U27: =SUM(M27:T27) -> 2837.1 | W27: CHINA | X27: =IF(K27<>"", "CONCLUÍDO", IF(E27<>"", "EM TRÂNSITO", "EM PRODUÇÃO")) -> EM TRÂNSITO | Y27: =Tabela2[[#This Row],[ESTIMATIVA CHEGADA]]-TODAY() -> 1 | Z27: 46242
A28: =A27+1 -> 27 | B28: TIMBRO SWISS SA | C28: 4508577003 | D28: BEMOL 39 | G28: =COUNTIF(Precificação!A:A,'Base de Dados'!D38) -> 9 | H28: BATEDEIRAS | I28: =SUMIF(Precificação!A:A,D28,Precificação!F:F) -> 1760 | J28: 56320 | L28: Marítimo | M28: 0 | N28: 0 | O28: 0 | P28: 0 | Q28: 1537.1 | R28: 1300 | S28: 0 | T28: 0 | U28: =SUM(M28:T28) -> 2837.1 | W28: CHINA | X28: =IF(K28<>"", "CONCLUÍDO", IF(E28<>"", "EM TRÂNSITO", "EM PRODUÇÃO")) -> EM PRODUÇÃO | Y28: =Tabela2[[#This Row],[ESTIMATIVA CHEGADA]]-TODAY() -> 84 | Z28: =Tabela2[[#This Row],[PRONTIDÃO]]+60 -> 46325 | AA28: 46265
A29: =A28+1 -> 28 | B29: TIMBRO SWISS SA | C29: 4508559921 | D29: BEMOL 40 | E29: CAN31113002 | F29: HLBU2443445/ UACU5972213/ HAMU1170011 | G29: =COUNTIF(Precificação!A:A,'Base de Dados'!D21) -> 6 | H29: FORNO 60L | I29: =SUMIF(Precificação!A:A,D29,Precificação!F:F) -> 1575 | J29: 64118.25 | K29: 2026000211 | L29: Marítimo | M29: 327567.32 | N29: 44344.38 | O29: 219.73 | P29: 154.23 | Q29: 1537.1 | R29: 1300 | S29: 35910.68 | T29: 7814.76 | U29: =SUM(M29:T29) -> 418848.2 | V29: =N29/M29 -> 0.13537486 | W29: CHINA | X29: =IF(K29<>"", "CONCLUÍDO", IF(E29<>"", "EM TRÂNSITO", "EM PRODUÇÃO")) -> CONCLUÍDO | Z29: 46159
A30: =A29+1 -> 29 | B30: TIMBRO SWISS SA | C30: Criar Ordem | D30: BEMOL 41 | G30: =COUNTIF(Precificação!A:A,'Base de Dados'!D32) -> 1 | H30: CAFETEIRAEMIXER | I30: =SUMIF(Precificação!A:A,D30,Precificação!F:F) -> 0 | J30: 48031.6 | L30: Marítimo | M30: 0 | N30: 0 | O30: 0 | P30: 0 | Q30: 1537.1 | R30: 1300 | S30: 0 | T30: 0 | U30: =SUM(M30:T30) -> 2837.1 | W30: CHINA | X30: =IF(K30<>"", "CONCLUÍDO", IF(E30<>"", "EM TRÂNSITO", "EM PRODUÇÃO")) -> EM PRODUÇÃO | Y30: =Tabela2[[#This Row],[ESTIMATIVA CHEGADA]]-TODAY() -> 66 | Z30: =Tabela2[[#This Row],[PRONTIDÃO]]+60 -> 46307 | AA30: 46247
A31: =A30+1 -> 30 | B31: TIMBRO SWISS SA | C31: 4508751681 | D31: BEMOL 42 | E31: SHA31178711 | F31: FANU1271087/ HAMU1390865/ HLXU8347322 | G31: =COUNTIF(Precificação!A:A,'Base de Dados'!D20) -> 9 | H31: POTES VDR COM TAMPA | I31: =SUMIF(Precificação!A:A,D31,Precificação!F:F) -> 34966 | J31: 87103.88 | K31: 2026000202 | L31: Marítimo | M31: 450475.1 | N31: 47171.08 | O31: 293.6 | P31: 154.23 | Q31: 1537.1 | R31: 1300 | S31: 48051.19 | T31: 10456.74 | U31: =SUM(M31:T31) -> 559439.04 | V31: =N31/M31 -> 0.10471407 | W31: CHINA | X31: =IF(K31<>"", "CONCLUÍDO", IF(E31<>"", "EM TRÂNSITO", "EM PRODUÇÃO")) -> CONCLUÍDO | Z31: 46156
A32: =A31+1 -> 31 | B32: TIMBRO SWISS SA | C32: 4508840505 | D32: BEMOL 43 | G32: =COUNTIF(Precificação!A:A,'Base de Dados'!D34) -> 18 | H32: SECADOR DE CABELO | CONCLUSÃO EM JULHO | I32: =SUMIF(Precificação!A:A,D32,Precificação!F:F) -> 2004 | J32: 46552.92 | L32: Marítimo | M32: 0 | N32: 0 | O32: 0 | P32: 0 | Q32: 1537.1 | R32: 1300 | S32: 0 | T32: 0 | U32: =SUM(M32:T32) -> 2837.1 | W32: CHINA | X32: =IF(K32<>"", "CONCLUÍDO", IF(E32<>"", "EM TRÂNSITO", "EM PRODUÇÃO")) -> EM PRODUÇÃO | Y32: =Tabela2[[#This Row],[ESTIMATIVA CHEGADA]]-TODAY() -> 68 | Z32: =Tabela2[[#This Row],[PRONTIDÃO]]+60 -> 46309 | AA32: 46249
A33: =A32+1 -> 32 | B33: TIMBRO SWISS SA | C33: 4508894878 | D33: BEMOL 45 | E33: 1074377332 | F33: FSCU8231725 | G33: =COUNTIF(Precificação!A:A,'Base de Dados'!D43) -> 1 | H33: LIQUIDIFICADOR, MÁQUINA, SUPORTE E VAPORIZADOR | I33: =SUMIF(Precificação!A:A,D33,Precificação!F:F) -> 5324 | J33: 89848.96 | K33: 2026000235 | L33: Marítimo | M33: 0 | N33: 0 | O33: 0 | P33: 0 | Q33: 1537.1 | R33: 1300 | S33: 0 | T33: 0 | U33: =SUM(M33:T33) -> 2837.1 | W33: CHINA | X33: =IF(K33<>"", "CONCLUÍDO", IF(E33<>"", "EM TRÂNSITO", "EM PRODUÇÃO")) -> CONCLUÍDO | Z33: 46233
A34: =A33+1 -> 33 | B34: TIMBRO SWISS SA | C34: 4508897867 | D34: BEMOL 46 | E34: SHAS010316 | G34: =COUNTIF(Precificação!A:A,'Base de Dados'!D44) -> 7 | H34: EDREDOM | I34: =SUMIF(Precificação!A:A,D34,Precificação!F:F) -> 8112 | J34: 163113.6 | L34: Marítimo | M34: 0 | N34: 0 | O34: 0 | P34: 0 | Q34: 1537.1 | R34: 1300 | S34: 0 | T34: 0 | U34: =SUM(M34:T34) -> 2837.1 | X34: =IF(K34<>"", "CONCLUÍDO", IF(E34<>"", "EM TRÂNSITO", "EM PRODUÇÃO")) -> EM TRÂNSITO | Y34: =Tabela2[[#This Row],[ESTIMATIVA CHEGADA]]-TODAY() -> 53 | Z34: 46294
A35: =A34+1 -> 34 | B35: TIMBRO SWISS SA | C35: 4508840296 | D35: BEMOL 47 | E35: CAN31113229 | F35: HAMU1899636 | G35: =COUNTIF(Precificação!A:A,'Base de Dados'!D33) -> 4 | H35: FORNO ELETRICO | I35: =SUMIF(Precificação!A:A,D35,Precificação!F:F) -> 500 | J35: 20355 | K35: 2026000234 | L35: Marítimo | M35: 0 | N35: 0 | O35: 0 | P35: 0 | Q35: 1537.1 | R35: 1300 | S35: 0 | T35: 0 | U35: =SUM(M35:T35) -> 2837.1 | W35: CHINA | X35: =IF(K35<>"", "CONCLUÍDO", IF(E35<>"", "EM TRÂNSITO", "EM PRODUÇÃO")) -> CONCLUÍDO | Z35: 46233
A36: =A35+1 -> 35 | B36: TIMBRO SWISS SA | C36: 4508840510 | D36: BEMOL 48 | E36: NGB31167475 | F36: GAOU7397863 | G36: =COUNTIF(Precificação!A:A,'Base de Dados'!D35) -> 1 | H36: AIRFRYER 12L | I36: =SUMIF(Precificação!A:A,D36,Precificação!F:F) -> 1112 | J36: 42044.72 | K36: 2026000228 | L36: Marítimo | M36: 0 | N36: 0 | O36: 0 | P36: 0 | Q36: 1537.1 | R36: 1300 | S36: 0 | T36: 0 | U36: =SUM(M36:T36) -> 2837.1 | W36: CHINA | X36: =IF(K36<>"", "CONCLUÍDO", IF(E36<>"", "EM TRÂNSITO", "EM PRODUÇÃO")) -> CONCLUÍDO | Z36: 46231
A37: =A36+1 -> 36 | B37: TIMBRO SWISS SA | C37: 4508840536 | D37: BEMOL 49 | E37: NGB31168106 | F37: MSBU5188110 | G37: =COUNTIF(Precificação!A:A,'Base de Dados'!D36) -> 1 | H37: GRILL, ESCOVA SECADORA, CHAPINHA, SANDUICHEIRA E ESPREMEDOR DE FRUTAS | I37: =SUMIF(Precificação!A:A,D37,Precificação!F:F) -> 10044 | J37: 14886 | K37: 2026000238 | L37: Marítimo | M37: 0 | N37: 0 | O37: 0 | P37: 0 | Q37: 1537.1 | R37: 1300 | S37: 0 | T37: 0 | U37: =SUM(M37:T37) -> 2837.1 | W37: CHINA | X37: =IF(K37<>"", "CONCLUÍDO", IF(E37<>"", "EM TRÂNSITO", "EM PRODUÇÃO")) -> CONCLUÍDO | Z37: 46238
A38: =A37+1 -> 37 | B38: TIMBRO SWISS SA | C38: 4508840545 | D38: BEMOL 50 | E38: NGBS000622 | F38: FANU3565630/ HLBU1619885 | G38: =COUNTIF(Precificação!A:A,'Base de Dados'!D37) -> 5 | H38: BEAUTY CHUMBO + AIR FRYER+ TRAVESSAS | I38: =SUMIF(Precificação!A:A,D38,Precificação!F:F) -> 15694 | J38: 125124.1 | L38: Marítimo | M38: 0 | N38: 0 | O38: 0 | P38: 0 | Q38: 1537.1 | R38: 1300 | S38: 0 | T38: 0 | U38: =SUM(M38:T38) -> 2837.1 | W38: CHINA | X38: =IF(K38<>"", "CONCLUÍDO", IF(E38<>"", "EM TRÂNSITO", "EM PRODUÇÃO")) -> EM TRÂNSITO | Y38: =Tabela2[[#This Row],[ESTIMATIVA CHEGADA]]-TODAY() -> 26 | Z38: 46267
A39: =A38+1 -> 38 | B39: TIMBRO SWISS SA | C39: 4508699466 | D39: BEMOL 51 | E39: SHAS003420 | F39: MSNU9335746 | G39: =COUNTIF(Precificação!A:A,'Base de Dados'!D39) -> 4 | H39: POTES DE VIDROS | I39: =SUMIF(Precificação!A:A,D39,Precificação!F:F) -> 11244 | J39: 30226.2 | L39: Marítimo | M39: 0 | N39: 0 | O39: 0 | P39: 0 | Q39: 1537.1 | R39: 1300 | S39: 0 | T39: 0 | U39: =SUM(M39:T39) -> 2837.1 | W39: CHINA | X39: =IF(K39<>"", "CONCLUÍDO", IF(E39<>"", "EM TRÂNSITO", "EM PRODUÇÃO")) -> EM TRÂNSITO | Y39: =Tabela2[[#This Row],[ESTIMATIVA CHEGADA]]-TODAY() -> 32 | Z39: 46273
A40: =A39+1 -> 39 | B40: TIMBRO SWISS SA | C40: 4508894889 | D40: BEMOL 52 | F40: SEM CTN | G40: =COUNTIF(Precificação!A:A,'Base de Dados'!D45) -> 2 | H40: COPO LIQUIDIFICADOR GSE019 | I40: =SUMIF(Precificação!A:A,D40,Precificação!F:F) -> 992 | J40: 1517.76 | L40: Aéreo | M40: 0 | N40: 0 | O40: 0 | P40: 0 | Q40: 1537.1 | R40: 1300 | S40: 0 | T40: 0 | U40: =SUM(M40:T40) -> 2837.1 | X40: =IF(K40<>"", "CONCLUÍDO", IF(E40<>"", "EM TRÂNSITO", "EM PRODUÇÃO")) -> EM PRODUÇÃO | Z40: 46238
A41: =A40+1 -> 40 | B41: TIMBRO SWISS SA | C41: 4508727560 | D41: BEMOL 53 | E41: SHAS004358 | F41: MSDU4316830/ MSDU4659212/ MSDU4740833 | G41: =COUNTIF(Precificação!A:A,'Base de Dados'!D40) -> 1 | H41: VIDRARIA | I41: =SUMIF(Precificação!A:A,D41,Precificação!F:F) -> 40554 | J41: 81436.5 | L41: Marítimo | M41: 0 | N41: 0 | O41: 0 | P41: 0 | Q41: 1537.1 | R41: 1300 | S41: 0 | T41: 0 | U41: =SUM(M41:T41) -> 2837.1 | W41: CHINA | X41: =IF(K41<>"", "CONCLUÍDO", IF(E41<>"", "EM TRÂNSITO", "EM PRODUÇÃO")) -> EM TRÂNSITO | Y41: =Tabela2[[#This Row],[ESTIMATIVA CHEGADA]]-TODAY() -> 38 | Z41: 46279
A42: =A41+1 -> 41 | B42: TIMBRO SWISS SA | C42: 4508894894 | D42: BEMOL 54 | E42: T617271853968 | F42: TCKU7711589 | G42: =COUNTIF(Precificação!A:A,'Base de Dados'!D46) -> 4 | H42: AIR FRYER 12L | I42: =SUMIF(Precificação!A:A,D42,Precificação!F:F) -> 1112 | J42: 42044.72 | L42: Marítimo | M42: 0 | N42: 0 | O42: 0 | P42: 0 | Q42: 1537.1 | R42: 1300 | S42: 0 | T42: 0 | U42: =SUM(M42:T42) -> 2837.1 | W42: CHINA | X42: =IF(K42<>"", "CONCLUÍDO", IF(E42<>"", "EM TRÂNSITO", "EM PRODUÇÃO")) -> EM TRÂNSITO | Y42: =Tabela2[[#This Row],[ESTIMATIVA CHEGADA]]-TODAY() -> 5 | Z42: 46246
A43: =A42+1 -> 42 | B43: TIMBRO SWISS SA | C43: 4508727727 | D43: BEMOL 55 | E43: NGBS001342 | F43: FFAU3779582/ MSCU5385072 | G43: =COUNTIF(Precificação!A:A,'Base de Dados'!D47) -> 1 | H43: FRIGOBAR 46L | I43: =SUMIF(Precificação!A:A,D43,Precificação!F:F) -> 1160 | J43: 16704 | L43: Marítimo | M43: 0 | N43: 0 | O43: 0 | P43: 0 | Q43: 1537.1 | R43: 1300 | S43: 0 | T43: 0 | U43: =SUM(M43:T43) -> 2837.1 | W43: CHINA | X43: =IF(K43<>"", "CONCLUÍDO", IF(E43<>"", "EM TRÂNSITO", "EM PRODUÇÃO")) -> EM TRÂNSITO | Y43: =Tabela2[[#This Row],[ESTIMATIVA CHEGADA]]-TODAY() -> 11 | Z43: 46252
A44: =A43+1 -> 43 | B44: TIMBRO SWISS SA | C44: 4508894905 | D44: BEMOL 56 | E44: NGBS003530 | F44: BMOU6023258 | G44: =COUNTIF(Precificação!A:A,'Base de Dados'!D47) -> 1 | H44: SUPORTE DE TV + FERRO + LIQUID + VAPOR + CHAPINHA | I44: =SUMIF(Precificação!A:A,D44,Precificação!F:F) -> 15480 | J44: 96451.8 | L44: Marítimo | M44: 0 | N44: 0 | O44: 0 | P44: 0 | Q44: 1537.1 | R44: 1300 | S44: 0 | T44: 0 | U44: =SUM(M44:T44) -> 2837.1 | W44: CHINA | X44: =IF(K44<>"", "CONCLUÍDO", IF(E44<>"", "EM TRÂNSITO", "EM PRODUÇÃO")) -> EM TRÂNSITO | Y44: =Tabela2[[#This Row],[ESTIMATIVA CHEGADA]]-TODAY() -> 34 | Z44: 46275
A45: =A44+1 -> 44 | B45: TIMBRO SWISS SA | C45: 4508894854 | D45: BEMOL 57 | E45: NGBS003532 | F45: MEDU7000900 | G45: =COUNTIF(Precificação!A:A,'Base de Dados'!D29) -> 1 | H45: FRITADERIA + GRILL | I45: =SUMIF(Precificação!A:A,D45,Precificação!F:F) -> 3404 | J45: 45855.8 | L45: Marítimo | M45: 0 | N45: 0 | O45: 0 | P45: 0 | Q45: 1537.1 | R45: 1300 | S45: 0 | T45: 0 | U45: =SUM(M45:T45) -> 2837.1 | W45: CHINA | X45: =IF(K45<>"", "CONCLUÍDO", IF(E45<>"", "EM TRÂNSITO", "EM PRODUÇÃO")) -> EM TRÂNSITO | Y45: =Tabela2[[#This Row],[ESTIMATIVA CHEGADA]]-TODAY() -> 34 | Z45: 46275
A46: =A45+1 -> 45 | B46: TIMBRO SWISS SA | C46: 4508894918 | D46: BEMOL 58 | E46: NGBS004955 | F46: MEDU7104674/ MEDU7435939/ MSBU8205972/ MSDU7814550/ MSMU4759389/ MSMU6056019/ MSMU6236793/ MSNU5027600/ MSNU6653609/ SEKU6681461 | G46: =COUNTIF(Precificação!A:A,'Base de Dados'!D48) -> 1 | H46: BEBEDOURO (10 CNTRS) | I46: =SUMIF(Precificação!A:A,D46,Precificação!F:F) -> 7410 | J46: 335154.3 | L46: Marítimo | M46: 0 | N46: 0 | O46: 0 | P46: 0 | Q46: 1537.1 | R46: 1300 | S46: 0 | T46: 0 | U46: =SUM(M46:T46) -> 2837.1 | W46: CHINA | X46: =IF(K46<>"", "CONCLUÍDO", IF(E46<>"", "EM TRÂNSITO", "EM PRODUÇÃO")) -> EM TRÂNSITO | Y46: =Tabela2[[#This Row],[ESTIMATIVA CHEGADA]]-TODAY() -> 32 | Z46: 46273
A47: =A46+1 -> 46 | B47: TIMBRO SWISS SA | C47: 4508894928 | D47: BEMOL 59 | E47: T617271627444 | F47: MRKU4285878/ CAJU5011195 | G47: =COUNTIF(Precificação!A:A,'Base de Dados'!D49) -> 3 | H47: AIR FRYER 12L - 2 CNTR | I47: =SUMIF(Precificação!A:A,D47,Precificação!F:F) -> 2224 | J47: 84089.44 | L47: Marítimo | M47: 0 | N47: 0 | O47: 0 | P47: 0 | Q47: 1537.1 | R47: 1300 | S47: 0 | T47: 0 | U47: =SUM(M47:T47) -> 2837.1 | W47: CHINA | X47: =IF(K47<>"", "CONCLUÍDO", IF(E47<>"", "EM TRÂNSITO", "EM PRODUÇÃO")) -> EM TRÂNSITO | Y47: =Tabela2[[#This Row],[ESTIMATIVA CHEGADA]]-TODAY() -> 5 | Z47: 46246
A48: =A47+1 -> 47 | B48: TIMBRO SWISS SA | C48: 4508896119 | D48: BEMOL 60 | E48: NGBS004115 | F48: TEMU8206647 | G48: =COUNTIF(Precificação!A:A,'Base de Dados'!D50) -> 11 | H48: BEBEDOURO - 1 CNTR | I48: =SUMIF(Precificação!A:A,D48,Precificação!F:F) -> 630 | J48: 30057.3 | L48: Marítimo | M48: 0 | N48: 0 | O48: 0 | P48: 0 | Q48: 1537.1 | R48: 1300 | S48: 0 | T48: 0 | U48: =SUM(M48:T48) -> 2837.1 | W48: CHINA | X48: =IF(K48<>"", "CONCLUÍDO", IF(E48<>"", "EM TRÂNSITO", "EM PRODUÇÃO")) -> EM TRÂNSITO | Y48: =Tabela2[[#This Row],[ESTIMATIVA CHEGADA]]-TODAY() -> 27 | Z48: 46268
A49: =A48+1 -> 48 | B49: TIMBRO SWISS SA | C49: 4508894942 | D49: BEMOL 61 | E49: NGBS004954 | F49: MSMU4796145 | G49: =COUNTIF(Precificação!A:A,'Base de Dados'!D51) -> 19 | H49: AIRFRYER 12L + SECADOR + MÁQ DE GELO - 1 CNTR | I49: =SUMIF(Precificação!A:A,D49,Precificação!F:F) -> 3196 | J49: 65328.76 | L49: Marítimo | M49: 0 | N49: 0 | O49: 0 | P49: 0 | Q49: 1537.1 | R49: 1300 | S49: 0 | T49: 0 | U49: =SUM(M49:T49) -> 2837.1 | W49: CHINA | X49: =IF(K49<>"", "CONCLUÍDO", IF(E49<>"", "EM TRÂNSITO", "EM PRODUÇÃO")) -> EM TRÂNSITO | Y49: =Tabela2[[#This Row],[ESTIMATIVA CHEGADA]]-TODAY() -> 31 | Z49: 46272 | AA49: 46212
A50: =A49+1 -> 49 | B50: TIMBRO SWISS SA | C50: 4508897826 | D50: BEMOL 62 | E50: SHAS006514 | F50: MSGU5188566 | G50: =COUNTIF(Precificação!A:A,'Base de Dados'!D53) -> 0 | H50: POTES DE VIDRO - 1 CNTR - | I50: =SUMIF(Precificação!A:A,D50,Precificação!F:F) -> 18900 | J50: 36991.32 | L50: Marítimo | M50: 0 | N50: 0 | O50: 0 | P50: 0 | Q50: 1537.1 | R50: 1300 | S50: 0 | T50: 0 | U50: =SUM(M50:T50) -> 2837.1 | W50: CHINA | X50: =IF(K50<>"", "CONCLUÍDO", IF(E50<>"", "EM TRÂNSITO", "EM PRODUÇÃO")) -> EM TRÂNSITO | Y50: =Tabela2[[#This Row],[ESTIMATIVA CHEGADA]]-TODAY() -> 46 | Z50: 46287
A51: =A50+1 -> 50 | B51: TIMBRO SWISS SA | C51: 4508896055 | D51: BEMOL 63 | G51: =COUNTIF(Precificação!A:A,'Base de Dados'!D54) -> 1 | H51: COBRE LEITO | I51: =SUMIF(Precificação!A:A,D51,Precificação!F:F) -> 8172 | J51: 61192.08 | L51: Marítimo | M51: 0 | N51: 0 | O51: 0 | P51: 0 | Q51: 1537.1 | R51: 1300 | S51: 0 | T51: 0 | U51: =SUM(M51:T51) -> 2837.1 | W51: CHINA | X51: =IF(K51<>"", "CONCLUÍDO", IF(E51<>"", "EM TRÂNSITO", "EM PRODUÇÃO")) -> EM PRODUÇÃO | Y51: =Tabela2[[#This Row],[ESTIMATIVA CHEGADA]]-TODAY() -> 59 | Z51: =Tabela2[[#This Row],[PRONTIDÃO]]+60 -> 46300 | AA51: 46240
A52: =A51+1 -> 51 | B52: TIMBRO SWISS SA | C52: 4508918015 | D52: BEMOL 66 | G52: =COUNTIF(Precificação!A:A,'Base de Dados'!D52) -> 4 | H52: CAMA, MESA E BANHO | I52: =SUMIF(Precificação!A:A,D52,Precificação!F:F) -> 7914 | J52: 32007.6 | L52: Marítimo | M52: 0 | N52: 0 | O52: 0 | P52: 0 | Q52: 1537.1 | R52: 1300 | S52: 0 | T52: 0 | U52: =SUM(M52:T52) -> 2837.1 | W52: =_xlfn.XLOOKUP(Tabela2[[#This Row],[INVOICE]],#REF!,#REF!) -> #REF! | X52: =IF(K52<>"", "CONCLUÍDO", IF(E52<>"", "EM TRÂNSITO", "EM PRODUÇÃO")) -> EM PRODUÇÃO | Y52: =Tabela2[[#This Row],[ESTIMATIVA CHEGADA]]-TODAY() -> 112 | Z52: =Tabela2[[#This Row],[PRONTIDÃO]]+66 -> 46353 | AA52: 46287
A53: =A51+1 -> 51 | B53: TIMBRO SWISS SA | C53: 4508896073 | D53: BEMOL 64 | G53: =COUNTIF(Precificação!A:A,'Base de Dados'!D55) -> 1 | H53: CAMA, MESA E BANHO | I53: =SUMIF(Precificação!A:A,D53,Precificação!F:F) -> 0 | J53: 95077.96 | L53: Marítimo | M53: 0 | N53: 0 | O53: 0 | P53: 0 | Q53: 1537.1 | R53: 1300 | S53: 0 | T53: 0 | U53: =SUM(M53:T53) -> 2837.1 | W53: CHINA | X53: =IF(K53<>"", "CONCLUÍDO", IF(E53<>"", "EM TRÂNSITO", "EM PRODUÇÃO")) -> EM PRODUÇÃO | Y53: =Tabela2[[#This Row],[ESTIMATIVA CHEGADA]]-TODAY() -> 49 | Z53: 46290
A54: =A53+1 -> 52 | B54: TIMBRO SWISS SA | C54: 4508896020 | D54: BEMOL 65 | E54: NGBS006963 | F54: MSMU8895974 | G54: =COUNTIF(Precificação!A:A,'Base de Dados'!D56) -> 1 | H54: AIR FRYER 3,5L - PRONTIDÃO 20/07 | I54: =SUMIF(Precificação!A:A,D54,Precificação!F:F) -> 2112 | J54: 37593.6 | L54: Marítimo | M54: 0 | N54: 0 | O54: 0 | P54: 0 | Q54: 1537.1 | R54: 1300 | S54: 0 | T54: 0 | U54: =SUM(M54:T54) -> 2837.1 | W54: CHINA | X54: =IF(K54<>"", "CONCLUÍDO", IF(E54<>"", "EM TRÂNSITO", "EM PRODUÇÃO")) -> EM TRÂNSITO | Y54: =Tabela2[[#This Row],[ESTIMATIVA CHEGADA]]-TODAY() -> 51 | Z54: =Tabela2[[#This Row],[PRONTIDÃO]]+69 -> 46292 | AA54: 46223
A55: =A54+1 -> 53 | B55: TIMBRO SWISS SA | C55: 4508896009 | D55: BEMOL 67 | G55: =COUNTIF(Precificação!A:A,'Base de Dados'!D57) -> 3 | H55: AIR FRYER 12L - PRONTIDÃO 10/08 | I55: =SUMIF(Precificação!A:A,D55,Precificação!F:F) -> 2224 | J55: 84089.44 | L55: Marítimo | M55: 0 | N55: 0 | O55: 0 | P55: 0 | Q55: 1537.1 | R55: 1300 | S55: 0 | T55: 0 | U55: =SUM(M55:T55) -> 2837.1 | W55: CHINA | X55: =IF(K55<>"", "CONCLUÍDO", IF(E55<>"", "EM TRÂNSITO", "EM PRODUÇÃO")) -> EM PRODUÇÃO | Y55: =Tabela2[[#This Row],[ESTIMATIVA CHEGADA]]-TODAY() -> 73 | Z55: =Tabela2[[#This Row],[PRONTIDÃO]]+60 -> 46314 | AA55: 46254
A56: =A55+1 -> 54 | B56: TIMBRO SWISS SA | C56: 4508896000 | D56: BEMOL 68 | E56: NGBS006964 | G56: =COUNTIF(Precificação!A:A,'Base de Dados'!D58) -> 4 | H56: FRIGOBAR 46L - PRONTIDÃO 02/08 | I56: =SUMIF(Precificação!A:A,D56,Precificação!F:F) -> 1160 | J56: 59693.6 | L56: Marítimo | M56: 0 | N56: 0 | O56: 0 | P56: 0 | Q56: 1537.1 | R56: 1300 | S56: 0 | T56: 0 | U56: =SUM(M56:T56) -> 2837.1 | W56: CHINA | X56: =IF(K56<>"", "CONCLUÍDO", IF(E56<>"", "EM TRÂNSITO", "EM PRODUÇÃO")) -> EM TRÂNSITO | Y56: =Tabela2[[#This Row],[ESTIMATIVA CHEGADA]]-TODAY() -> 56 | Z56: =Tabela2[[#This Row],[PRONTIDÃO]]+60 -> 46297 | AA56: 46237
A57: =A56+1 -> 55 | B57: TIMBRO SWISS SA | C57: 4508895990 | D57: BEMOL 69 | G57: =COUNTIF(Precificação!A:A,'Base de Dados'!D59) -> 5 | H57: MÁQUINA DE GELO + SECADOR + CHAPINHA - PRONTIDÃO 10/08 | I57: =SUMIF(Precificação!A:A,D57,Precificação!F:F) -> 8036 | J57: 98682.56 | L57: Marítimo | M57: 0 | N57: 0 | O57: 0 | P57: 0 | Q57: 1537.1 | R57: 1300 | S57: 0 | T57: 0 | U57: =SUM(M57:T57) -> 2837.1 | W57: CHINA | X57: =IF(K57<>"", "CONCLUÍDO", IF(E57<>"", "EM TRÂNSITO", "EM PRODUÇÃO")) -> EM PRODUÇÃO | Y57: =Tabela2[[#This Row],[ESTIMATIVA CHEGADA]]-TODAY() -> 59 | Z57: =Tabela2[[#This Row],[PRONTIDÃO]]+60 -> 46300 | AA57: 46240
A58: =A57+1 -> 56 | B58: TIMBRO SWISS SA | C58: 4508856527 | D58: BEMOL 70 | G58: =COUNTIF(Precificação!A:A,'Base de Dados'!D42) -> 1 | H58: FERROS DE PASSAR + ESPREMEDOR | I58: =SUMIF(Precificação!A:A,D58,Precificação!F:F) -> 9600 | J58: 74880 | L58: Marítimo | M58: 0 | N58: 0 | O58: 0 | P58: 0 | Q58: 1537.1 | R58: 1300 | S58: 0 | T58: 0 | U58: =SUM(M58:T58) -> 2837.1 | W58: CHINA | X58: =IF(K58<>"", "CONCLUÍDO", IF(E58<>"", "EM TRÂNSITO", "EM PRODUÇÃO")) -> EM PRODUÇÃO | Y58: =Tabela2[[#This Row],[ESTIMATIVA CHEGADA]]-TODAY() -> 80 | Z58: =Tabela2[[#This Row],[PRONTIDÃO]]+60 -> 46321 | AA58: 46261
A59: =A58+1 -> 57 | B59: TIMBRO SWISS SA | C59: 4508856516 | D59: BEMOL 71 | G59: =COUNTIF(Precificação!A:A,'Base de Dados'!D41) -> 7 | H59: SUP.TV + ESPREMEDOR + PROCESSADOR + GRILL + VAP. | I59: =SUMIF(Precificação!A:A,D59,Precificação!F:F) -> 12520 | J59: 85678 | L59: Marítimo | M59: 0 | N59: 0 | O59: 0 | P59: 0 | Q59: 1537.1 | R59: 1300 | S59: 0 | T59: 0 | U59: =SUM(M59:T59) -> 2837.1 | W59: CHINA | X59: =IF(K59<>"", "CONCLUÍDO", IF(E59<>"", "EM TRÂNSITO", "EM PRODUÇÃO")) -> EM PRODUÇÃO | Y59: =Tabela2[[#This Row],[ESTIMATIVA CHEGADA]]-TODAY() -> 80 | Z59: =Tabela2[[#This Row],[PRONTIDÃO]]+60 -> 46321 | AA59: 46261
A60: =A59+1 -> 58 | B60: TIMBRO SWISS SA | C60: 4508890168 | D60: BEMOL 72 | G60: =COUNTIF(Precificação!A:A,'Base de Dados'!D60) -> 5 | H60: SUPORTES DE TV + SANDUICHEIRA - PRONTIDÃO 18/09 | I60: =SUMIF(Precificação!A:A,D60,Precificação!F:F) -> 21904 | J60: 74301.16 | L60: Marítimo | M60: 0 | N60: 0 | O60: 0 | P60: 0 | Q60: 1537.1 | R60: 1300 | S60: 0 | T60: 0 | U60: =SUM(M60:T60) -> 2837.1 | W60: CHINA | X60: =IF(K60<>"", "CONCLUÍDO", IF(E60<>"", "EM TRÂNSITO", "EM PRODUÇÃO")) -> EM PRODUÇÃO | Y60: =Tabela2[[#This Row],[ESTIMATIVA CHEGADA]]-TODAY() -> 103 | Z60: =Tabela2[[#This Row],[PRONTIDÃO]]+60 -> 46344 | AA60: 46284
A61: =A60+1 -> 59 | B61: ELOX TRANDING | C61: Criar Ordem | D61: INV-000261-26 | E61: SHXY260600685 | F61: MRSU6818984 | G61: =COUNTIF(Precificação!A:A,'Base de Dados'!D61) -> 1 | H61: BAUMON PULSE B97A SPEAKER BOX | I61: =SUMIF(Precificação!A:A,D61,Precificação!F:F) -> 1400 | J61: 42700 | L61: Marítimo | M61: 0 | N61: 0 | O61: 0 | P61: 0 | Q61: 1537.1 | R61: 1300 | S61: 0 | T61: 0 | U61: =SUM(M61:T61) -> 2837.1 | W61: CHINA | X61: =IF(K61<>"", "CONCLUÍDO", IF(E61<>"", "EM TRÂNSITO", "EM PRODUÇÃO")) -> EM TRÂNSITO | Y61: =Tabela2[[#This Row],[ESTIMATIVA CHEGADA]]-TODAY() -> 22.125 | Z61: =_xlfn.XLOOKUP(Tabela2[[#This Row],[INVOICE]],[1]Processes!$AH:$AH,[1]Processes!$BA:$BA) -> 46263.125
A62: =A61+1 -> 60 | B62: ELOX TRANDING | C62: Criar Ordem | D62: INV-000273-26 | E62: SHXY260600685 | F62: UETU5919825 | G62: =COUNTIF(Precificação!A:A,'Base de Dados'!D62) -> 1 | H62: BAUMON PULSE B97A SPEAKER BOX | I62: =SUMIF(Precificação!A:A,D62,Precificação!F:F) -> 1427 | J62: 43523.5 | L62: Marítimo | M62: 0 | N62: 0 | O62: 0 | P62: 0 | Q62: 1537.1 | R62: 1300 | S62: 0 | T62: 0 | U62: =SUM(M62:T62) -> 2837.1 | W62: CHINA | X62: =IF(K62<>"", "CONCLUÍDO", IF(E62<>"", "EM TRÂNSITO", "EM PRODUÇÃO")) -> EM TRÂNSITO | Y62: =Tabela2[[#This Row],[ESTIMATIVA CHEGADA]]-TODAY() -> 22.125 | Z62: =_xlfn.XLOOKUP(Tabela2[[#This Row],[INVOICE]],[1]Processes!$AH:$AH,[1]Processes!$BA:$BA) -> 46263.125
A63: =A62+1 -> 61 | B63: ELOX TRANDING | C63: Criar Ordem | D63: INV-000276-26 | E63: T617271410904 | F63: MRKU3053610/MRSU4903217/TCKU7909656 | G63: =COUNTIF(Precificação!A:A,'Base de Dados'!D63) -> 3 | H63: FREEZER VERTICAL 180L BD180U+ F. HORIZONTAL 100L BD100Q + F. HORIZ 150L BD150Q | I63: =SUMIF(Precificação!A:A,D63,Precificação!F:F) -> 607 | J63: 47455 | L63: Marítimo | M63: 0 | N63: 0 | O63: 0 | P63: 0 | Q63: 1537.1 | R63: 1300 | S63: 0 | T63: 0 | U63: =SUM(M63:T63) -> 2837.1 | W63: CHINA | X63: =IF(K63<>"", "CONCLUÍDO", IF(E63<>"", "EM TRÂNSITO", "EM PRODUÇÃO")) -> EM TRÂNSITO | Y63: =Tabela2[[#This Row],[ESTIMATIVA CHEGADA]]-TODAY() -> -1.875 | Z63: =_xlfn.XLOOKUP(Tabela2[[#This Row],[INVOICE]],[1]Processes!$AH:$AH,[1]Processes!$BA:$BA) -> 46239.125
A64: =A63+1 -> 62 | B64: ELOX TRANDING | C64: Criar Ordem | D64: INV-000277-26 | E64: T617272018241 | F64: GESU6167258/MIEU0024916/MRSU3491352/MRSU4730699/TCNU6501005/MRSU5693250 | G64: =COUNTIF(Precificação!A:A,'Base de Dados'!D64) -> 3 | H64: FREEZER VERTICAL 180L BD180U + F. HORIZONTAL 100L BD100Q + F. HORIZ 150L BD150Q | I64: =SUMIF(Precificação!A:A,D64,Precificação!F:F) -> 1266 | J64: 94581 | L64: Marítimo | M64: 0 | N64: 0 | O64: 0 | P64: 0 | Q64: 1537.1 | R64: 1300 | S64: 0 | T64: 0 | U64: =SUM(M64:T64) -> 2837.1 | W64: CHINA | X64: =IF(K64<>"", "CONCLUÍDO", IF(E64<>"", "EM TRÂNSITO", "EM PRODUÇÃO")) -> EM TRÂNSITO | Y64: =Tabela2[[#This Row],[ESTIMATIVA CHEGADA]]-TODAY() -> 5.125 | Z64: =_xlfn.XLOOKUP(Tabela2[[#This Row],[INVOICE]],[1]Processes!$AH:$AH,[1]Processes!$BA:$BA) -> 46246.125
A65: =A64+1 -> 63 | B65: ELOX TRANDING | C65: Criar Ordem | D65: INV-000283-26 | G65: =COUNTIF(Precificação!A:A,'Base de Dados'!D65) -> 1 | H65: SPEAKER PARTYBOX PARTY500 2MIC | I65: =SUMIF(Precificação!A:A,D65,Precificação!F:F) -> 500 | J65: 37950 | L65: Marítimo | M65: 0 | N65: 0 | O65: 0 | P65: 0 | Q65: 1537.1 | R65: 1300 | S65: 0 | T65: 0 | U65: =SUM(M65:T65) -> 2837.1 | W65: CHINA | X65: =IF(K65<>"", "CONCLUÍDO", IF(E65<>"", "EM TRÂNSITO", "EM PRODUÇÃO")) -> EM PRODUÇÃO | Z65: =_xlfn.XLOOKUP(Tabela2[[#This Row],[INVOICE]],[1]Processes!$AH:$AH,[1]Processes!$BA:$BA)
A66: =A65+1 -> 64 | B66: ELOX TRANDING | C66: Criar Ordem | D66: INV-000305-26 | E66: SZXS079788 | F66: CMAU3762621 | G66: =COUNTIF(Precificação!A:A,'Base de Dados'!D66) -> 3 | H66: B. RIO NEGRO OP16 COTTON NETWORK + B. NETWORK RIO IÇA OP19 COTTON AZ + B. RIO APUÍ OP20 POLYESTER NETWORK | I66: =SUMIF(Precificação!A:A,D66,Precificação!F:F) -> 1400 | J66: 17067.6 | L66: Marítimo | M66: 0 | N66: 0 | O66: 0 | P66: 0 | Q66: 1537.1 | R66: 1300 | S66: 0 | T66: 0 | U66: =SUM(M66:T66) -> 2837.1 | W66: CHINA | X66: =IF(K66<>"", "CONCLUÍDO", IF(E66<>"", "EM TRÂNSITO", "EM PRODUÇÃO")) -> EM TRÂNSITO | Y66: =Tabela2[[#This Row],[ESTIMATIVA CHEGADA]]-TODAY() -> 35.125 | Z66: =_xlfn.XLOOKUP(Tabela2[[#This Row],[INVOICE]],[1]Processes!$AH:$AH,[1]Processes!$BA:$BA) -> 46276.125
A67: =A66+1 -> 65 | B67: ELOX TRANDING | C67: Criar Ordem | D67: INV-000307-26 | E67: SHXY260600684 | F67: MRSU9786113 / MRKU3489840 | G67: =COUNTIF(Precificação!A:A,'Base de Dados'!D67) -> 3 | H67: B. BT KARAOKE 2MIC PT/RX SOUND SYSTEM + B. BT KARAOKE 2MIC SOUND SYSTEM + B. BT KARAOKE 2MIC SOUND SYSTEM | I67: =SUMIF(Precificação!A:A,D67,Precificação!F:F) -> 1481 | J67: 88731.13 | L67: Marítimo | M67: 0 | N67: 0 | O67: 0 | P67: 0 | Q67: 1537.1 | R67: 1300 | S67: 0 | T67: 0 | U67: =SUM(M67:T67) -> 2837.1 | W67: CHINA | X67: =IF(K67<>"", "CONCLUÍDO", IF(E67<>"", "EM TRÂNSITO", "EM PRODUÇÃO")) -> EM TRÂNSITO | Y67: =Tabela2[[#This Row],[ESTIMATIVA CHEGADA]]-TODAY() -> 15.125 | Z67: =_xlfn.XLOOKUP(Tabela2[[#This Row],[INVOICE]],[1]Processes!$AH:$AH,[1]Processes!$BA:$BA) -> 46256.125
A68: =A67+1 -> 66 | B68: ELOX TRANDING | C68: Criar Ordem | D68: INV-000321-26 | G68: =COUNTIF(Precificação!A:A,'Base de Dados'!D68) -> 2 | H68: B. BT KARAOKE 2MIC PT/RX SOUND SYSTEM + B. BT KARAOKE 2MIC PT SOUND SYSTEM | I68: =SUMIF(Precificação!A:A,D68,Precificação!F:F) -> 119 | J68: 9736.87 | L68: Marítimo | M68: 0 | N68: 0 | O68: 0 | P68: 0 | Q68: 1537.1 | R68: 1300 | S68: 0 | T68: 0 | U68: =SUM(M68:T68) -> 2837.1 | W68: CHINA | X68: =IF(K68<>"", "CONCLUÍDO", IF(E68<>"", "EM TRÂNSITO", "EM PRODUÇÃO")) -> EM PRODUÇÃO | Z68: =_xlfn.XLOOKUP(Tabela2[[#This Row],[INVOICE]],[1]Processes!$AH:$AH,[1]Processes!$BA:$BA)
A69: =A68+1 -> 67 | B69: TECHFRIO (BE JAY) | C69: 4508845852 | D69: PI-BAUMON-012026 | E69: KDBW26040037 | F69: NYKU5281532/ TRHU6082999/ NYKU4830047/ TCLU4867282/ TGBU9981947/ FCIU9770980 / FFAU6814500/ BEAU5375352/ TRHU6869789 / TGBU4681211 / TCLU7800873 / ONEU6925318/ MOTU5810610/ BSIU9861250/ CAIU9457638 | G69: =COUNTIF(Precificação!A:A,'Base de Dados'!D69) -> 4 | H69: SPLITS BAUMON | I69: =SUMIF(Precificação!A:A,D69,Precificação!F:F) -> 4495 | J69: 790311.5 | K69: 2026000199 | L69: Marítimo | M69: 4101084.4 | N69: 247524.84 | O69: 2580.8 | P69: 254.49 | Q69: 1537.1 | R69: 1300 | S69: 419889.84 | T69: 91375 | U69: =SUM(M69:T69) -> 4865546.5 | V69: =N69/M69 -> 0.060355948 | W69: CHINA | X69: =IF(K69<>"", "CONCLUÍDO", IF(E69<>"", "EM TRÂNSITO", "EM PRODUÇÃO")) -> CONCLUÍDO
A70: =A69+1 -> 68 | B70: TECHFRIO (BE JAY) | C70: 4508894343 | D70: PI-BAUMON-022026 | E70: CAN31113615-001 | F70: CAAU7709620/ NYKU4393630/ BEAU5275646/ TCLU6281686/ ONEU5340484/ ONEU0137900/ TCKU7917902/ TRHU6080390/ TCNU6057523/ ONEU1839290 | G70: =COUNTIF(Precificação!A:A,'Base de Dados'!D70) -> 3 | H70: SPLITS BAUMON | I70: =SUMIF(Precificação!A:A,D70,Precificação!F:F) -> 3080 | J70: 521928.4 | K70: 2026000218 | L70: Marítimo | M70: 2656302.4 | N70: 49960 | O70: 341.63 | P70: 223.64 | Q70: 1537.1 | R70: 1300 | S70: 281037.68 | T70: 61158.46 | U70: =SUM(M70:T70) -> 3051860.9 | V70: =N70/M70 -> 0.0188081 | W70: CHINA | X70: =IF(K70<>"", "CONCLUÍDO", IF(E70<>"", "EM TRÂNSITO", "EM PRODUÇÃO")) -> CONCLUÍDO | Y70: =Tabela2[[#This Row],[ESTIMATIVA CHEGADA]]-TODAY() -> 1 | Z70: 46242
A71: =A70+1 -> 69 | B71: TECHFRIO (BE JAY) | C71: 4508897788 | D71: PI-BAUMON-032026 | G71: =COUNTIF(Precificação!A:A,'Base de Dados'!D71) -> 5 | H71: SPLITS BAUMON | I71: =SUMIF(Precificação!A:A,D71,Precificação!F:F) -> 6122 | J71: 2000 | L71: Marítimo | M71: 0 | N71: 0 | O71: 0 | P71: 0 | Q71: 1537.1 | R71: 1300 | T71: 0 | U71: =SUM(M71:T71) -> 2837.1 | W71: CHINA | X71: =IF(K71<>"", "CONCLUÍDO", IF(E71<>"", "EM TRÂNSITO", "EM PRODUÇÃO")) -> EM PRODUÇÃO | Y71: =Tabela2[[#This Row],[ESTIMATIVA CHEGADA]]-TODAY() -> 77 | Z71: 46318
A72: =A71+1 -> 70 | B72: TIMBRO SWISS SA | C72: Criar Ordem | D72: A DEFINIR | G72: 0 | H72: REPOSIÇÃO COBRE LEITO + EDREDONS | I72: =SUMIF(Precificação!A:A,D72,Precificação!F:F) -> 16284 | J72: 224305.68 | L72: Marítimo | M72: 0 | N72: 0 | O72: 0 | P72: 0 | T72: 0 | U72: =SUM(M72:T72) -> 0 | W72: CHINA | X72: EM PRODUÇÃO | Y72: =Tabela2[[#This Row],[ESTIMATIVA CHEGADA]]-TODAY() -> 103 | Z72: =Tabela2[[#This Row],[PRONTIDÃO]]+60 -> 46344 | AA72: 19/09/2026
A73: =A72+1 -> 71 | B73: TECHFRIO (BE JAY) | C73: Criar Ordem | D73: PI-BAUMON-042026 | G73: =COUNTIF(Precificação!A:A,'Base de Dados'!D73) -> 5 | H73: SPLIT BAUMON COM WIFI | I73: =SUMIF(Precificação!A:A,D73,Precificação!F:F) -> 3481 | J73: 629851.94 | L73: Marítimo | M73: 0 | N73: 0 | O73: 0 | P73: 0 | T73: 0 | U73: =SUM(M73:T73) -> 0 | W73: CHINA | X73: =IF(K73<>"", "CONCLUÍDO", IF(E73<>"", "EM TRÂNSITO", "EM PRODUÇÃO")) -> EM PRODUÇÃO | Y73: =Tabela2[[#This Row],[ESTIMATIVA CHEGADA]]-TODAY() -> 102 | Z73: =Tabela2[[#This Row],[PRONTIDÃO]]+60 -> 46343 | AA73: 46283
A74: =A73+1 -> 72 | B74: ELOX TRANDING | C74: Criar Ordem | D74: INV-000342-26 | G74: =COUNTIF(Precificação!A:A,'Base de Dados'!D74) -> 1 | H74: CAIXA DE SOM BLUETOOTH | I74: =SUMIF(Precificação!A:A,D74,Precificação!F:F) -> 800 | J74: 7120 | L74: Marítimo | M74: 0 | N74: 0 | O74: 0 | P74: 0 | T74: 0 | U74: =SUM(M74:T74) -> 0 | W74: CHINA | X74: =IF(K74<>"", "CONCLUÍDO", IF(E74<>"", "EM TRÂNSITO", "EM PRODUÇÃO")) -> EM PRODUÇÃO
A75: =A74+1 -> 73 | B75: ELOX TRANDING | C75: Criar Ordem | D75: INV-000341-26 | E75: SZXS080348 | G75: =COUNTIF(Precificação!A:A,'Base de Dados'!D75) -> 2 | H75: BAUMON BT KARAOKE 2MIC PT SOUND SYSTEM | I75: =SUMIF(Precificação!A:A,D75,Precificação!F:F) -> 119 | J75: 10223.71 | L75: Marítimo | M75: 0 | N75: 0 | O75: 0 | P75: 0 | T75: 0 | U75: =SUM(M75:T75) -> 0 | W75: CHINA | X75: =IF(K75<>"", "CONCLUÍDO", IF(E75<>"", "EM TRÂNSITO", "EM PRODUÇÃO")) -> EM TRÂNSITO | Y75: =Tabela2[[#This Row],[ESTIMATIVA CHEGADA]]-TODAY() -> 53 | Z75: 46294 | AA75: 07/31/2026
A76: =A75+1 -> 74 | B76: ELOX TRANDING | C76: Criar Ordem | D76: INV-000332-26 | G76: =COUNTIF(Precificação!A:A,'Base de Dados'!D76) -> 2 | I76: =SUMIF(Precificação!A:A,D76,Precificação!F:F) -> 1000 | J76: 13125 | L76: Marítimo | M76: 0 | N76: 0 | O76: 0 | P76: 0 | T76: 0 | U76: =SUM(M76:T76) -> 0 | W76: CHINA | X76: =IF(K76<>"", "CONCLUÍDO", IF(E76<>"", "EM TRÂNSITO", "EM PRODUÇÃO")) -> EM PRODUÇÃO
A77: =A76+1 -> 75 | B77: ELOX TRANDING | C77: Criar Ordem | D77: INV-000334-26 | G77: =COUNTIF(Precificação!A:A,'Base de Dados'!D77) -> 1 | H77: BAUMON PULSE B97A SPEAKER BOX | I77: =SUMIF(Precificação!A:A,D77,Precificação!F:F) -> 2936 | J77: 16800 | L77: Marítimo | M77: 0 | N77: 0 | O77: 0 | P77: 0 | T77: 0 | U77: =SUM(M77:T77) -> 0 | W77: CHINA | X77: =IF(K77<>"", "CONCLUÍDO", IF(E77<>"", "EM TRÂNSITO", "EM PRODUÇÃO")) -> EM PRODUÇÃO
A78: =A77+1 -> 76 | B78: ELOX TRANDING | C78: Criar Ordem | D78: INV-000339-26 | G78: =COUNTIF(Precificação!A:A,'Base de Dados'!D78) -> 1 | H78: BAUMON SOUND WAVE WIRELESS HEADPHONE BLACK | I78: =SUMIF(Precificação!A:A,D78,Precificação!F:F) -> 1000 | J78: 94025.4 | L78: Marítimo | M78: 0 | N78: 0 | O78: 0 | P78: 0 | T78: 0 | U78: =SUM(M78:T78) -> 0 | W78: CHINA | X78: =IF(K78<>"", "CONCLUÍDO", IF(E78<>"", "EM TRÂNSITO", "EM PRODUÇÃO")) -> EM PRODUÇÃO
A79: =A78+1 -> 77 | B79: ELOX TRANDING | C79: Criar Ordem | D79: PI-BMO-260615-A | G79: =COUNTIF(Precificação!A:A,'Base de Dados'!D79) -> 2 | H79: AR COND, JANELA BAUMON | I79: =SUMIF(Precificação!A:A,D79,Precificação!F:F) -> 4200 | J79: 532942.6 | L79: Marítimo | M79: 0 | N79: 0 | O79: 0 | P79: 0 | T79: 0 | U79: =SUM(M79:T79) -> 0 | W79: CHINA | X79: =IF(K79<>"", "CONCLUÍDO", IF(E79<>"", "EM TRÂNSITO", "EM PRODUÇÃO")) -> EM PRODUÇÃO | Y79: =Tabela2[[#This Row],[ESTIMATIVA CHEGADA]]-TODAY() -> 63 | Z79: =Tabela2[[#This Row],[PRONTIDÃO]]+60 -> 46304 | AA79: 46244
A80: =A79+1 -> 78 | B80: ELOX TRANDING | C80: Criar Ordem | D80: PI-BMO-260615-B | G80: =COUNTIF(Precificação!A:A,'Base de Dados'!D80) -> 2 | H80: AR COND, JANELA BAUMON | I80: =SUMIF(Precificação!A:A,D80,Precificação!F:F) -> 3529 | J80: 446551.35 | L80: Marítimo | M80: 0 | N80: 0 | O80: 0 | P80: 0 | T80: 0 | U80: =SUM(M80:T80) -> 0 | W80: CHINA | X80: =IF(K80<>"", "CONCLUÍDO", IF(E80<>"", "EM TRÂNSITO", "EM PRODUÇÃO")) -> EM PRODUÇÃO | Y80: =Tabela2[[#This Row],[ESTIMATIVA CHEGADA]]-TODAY() -> 94 | Z80: =Tabela2[[#This Row],[PRONTIDÃO]]+60 -> 46335 | AA80: 46275
A81: =A80+1 -> 79 | B81: ELOX TRANDING | C81: Criar Ordem | D81: PI-BMO-260615-C | G81: =COUNTIF(Precificação!A:A,'Base de Dados'!D81) -> 2 | H81: AR COND, JANELA BAUMON | I81: =SUMIF(Precificação!A:A,D81,Precificação!F:F) -> 1429 | J81: 180080.05 | L81: Marítimo | M81: 0 | N81: 0 | O81: 0 | P81: 0 | T81: 0 | U81: =SUM(M81:T81) -> 0 | W81: CHINA | X81: =IF(K81<>"", "CONCLUÍDO", IF(E81<>"", "EM TRÂNSITO", "EM PRODUÇÃO")) -> EM PRODUÇÃO | Y81: =Tabela2[[#This Row],[ESTIMATIVA CHEGADA]]-TODAY() -> 124 | Z81: =Tabela2[[#This Row],[PRONTIDÃO]]+60 -> 46365 | AA81: =AA80+30 -> 46305

Sheet Precificação
A1: INVOICE | B1: Fornecedor | C1: Status | D1: Cód | E1: Descrição | F1: Qtd | G1: Custo individual UDS | H1: Taxa dolar DI | I1: Custo individual BRL | J1: Custo Total | K1: % Participação | L1: Frete BRL | M1: Custo total + Frete BRL | N1: Custo individual com frete BRL | O1: MARK UP | P1: Preço de venda | Q1: Margem | R1: MARK UP CATEGORIA | S1: Ganho de Margem | T1: Preço produto similar | U1: Dif de preço | V1: GM9 | W1: DESCRIÇÃO GM9
A2: BEMOL 34 | B2: =_xlfn.XLOOKUP(A2,'Base de Dados'!D:D,'Base de Dados'!B:B) -> TIMBRO SWISS SA | C2: =_xlfn.XLOOKUP(PRECIFICAÇÃO[[#This Row],[INVOICE]],'Base de Dados'!D:D,'Base de Dados'!X:X) -> CONCLUÍDO | D2: 267869 | E2: POTE BAUMON HERMÉT 400ML RET C/T R145 | F2: 2052 | G2: 0.74 | H2: 5.0378 | I2: =H2*G2 -> 3.727972 | J2: =I2*F2 -> 7649.7985 | K2: =J2/_xlfn.XLOOKUP(A2,'Base de Dados'!D:D,'Base de Dados'!M:M) -> 0.023351344 | L2: =K2*_xlfn.XLOOKUP(A2,'Base de Dados'!D:D,'Base de Dados'!N:N) -> 635.25277 | M2: =J2+L2 -> 8285.0513 | N2: =M2/F2 -> 4.0375494 | O2: =R2-0.1 -> 0.4092054 | P2: =ROUND(N2/O2,0) -> 10 | Q2: =(P2-N2)/P2 -> 0.59624506 | R2: 0.5092054 | S2: =Q2-R2 -> 0.087039663 | T2: =P2+10 -> 20 | U2: =(T2-P2)/T2 -> 0.5 | V2: 127001014 | W2: POTES
A3: BEMOL 34 | B3: =_xlfn.XLOOKUP(A3,'Base de Dados'!D:D,'Base de Dados'!B:B) -> TIMBRO SWISS SA | C3: =_xlfn.XLOOKUP(PRECIFICAÇÃO[[#This Row],[INVOICE]],'Base de Dados'!D:D,'Base de Dados'!X:X) -> CONCLUÍDO | D3: 267937 | E3: POTE BAUMON HERMÉT 1020ML RET C/T S195-3 | F3: 744 | G3: 1.79 | H3: 5.0378 | I3: =H3*G3 -> 9.017662 | J3: =I3*F3 -> 6709.1405 | K3: =J3/_xlfn.XLOOKUP(A3,'Base de Dados'!D:D,'Base de Dados'!M:M) -> 0.020479945 | L3: =K3*_xlfn.XLOOKUP(A3,'Base de Dados'!D:D,'Base de Dados'!N:N) -> 557.13887 | M3: =J3+L3 -> 7266.2794 | N3: =M3/F3 -> 9.7665046 | O3: =R3-0.1 -> 0.4092054 | P3: =ROUND(N3/O3,0) -> 24 | Q3: =(P3-N3)/P3 -> 0.59306231 | R3: 0.5092054 | S3: =Q3-R3 -> 0.08385691 | T3: =P3+10 -> 34 | U3: =(T3-P3)/T3 -> 0.29411765 | V3: 127001014 | W3: POTES
A4: BEMOL 34 | B4: =_xlfn.XLOOKUP(A4,'Base de Dados'!D:D,'Base de Dados'!B:B) -> TIMBRO SWISS SA | C4: =_xlfn.XLOOKUP(PRECIFICAÇÃO[[#This Row],[INVOICE]],'Base de Dados'!D:D,'Base de Dados'!X:X) -> CONCLUÍDO | D4: 267941 | E4: ASSAD BAUMON QUAD 1800ML VDR GB-S1800 | F4: 2496 | G4: 1.53 | H4: 5.0378 | I4: =H4*G4 -> 7.707834 | J4: =I4*F4 -> 19238.754 | K4: =J4/_xlfn.XLOOKUP(A4,'Base de Dados'!D:D,'Base de Dados'!M:M) -> 0.058727136 | L4: =K4*_xlfn.XLOOKUP(A4,'Base de Dados'!D:D,'Base de Dados'!N:N) -> 1597.6201 | M4: =J4+L4 -> 20836.374 | N4: =M4/F4 -> 8.3479061 | O4: =R4-0.1 -> 0.42527551 | P4: =ROUND(N4/O4,0) -> 20 | Q4: =(P4-N4)/P4 -> 0.58260469 | R4: 0.52527551 | S4: =Q4-R4 -> 0.057329181 | T4: =P4+10 -> 30 | U4: =(T4-P4)/T4 -> 0.33333333 | V4: 127001002 | W4: ASSADEIRAS/FÔRMAS
A5: BEMOL 34 | B5: =_xlfn.XLOOKUP(A5,'Base de Dados'!D:D,'Base de Dados'!B:B) -> TIMBRO SWISS SA | C5: =_xlfn.XLOOKUP(PRECIFICAÇÃO[[#This Row],[INVOICE]],'Base de Dados'!D:D,'Base de Dados'!X:X) -> CONCLUÍDO | D5: 267942 | E5: CAÇAROLA BAUMON 1000ML VIDRO GC-1000 | F5: 2496 | G5: 1.46 | H5: 5.0378 | I5: =H5*G5 -> 7.355188 | J5: =I5*F5 -> 18358.549 | K5: =J5/_xlfn.XLOOKUP(A5,'Base de Dados'!D:D,'Base de Dados'!M:M) -> 0.056040273 | L5: =K5*_xlfn.XLOOKUP(A5,'Base de Dados'!D:D,'Base de Dados'!N:N) -> 1524.5263 | M5: =J5+L5 -> 19883.076 | N5: =M5/F5 -> 7.9659758 | O5: =R5-0.1 -> 0.44079732 | P5: =ROUND(N5/O5,0) -> 18 | Q5: =(P5-N5)/P5 -> 0.55744579 | R5: 0.54079732 | S5: =Q5-R5 -> 0.01664847 | T5: =P5+10 -> 28 | U5: =(T5-P5)/T5 -> 0.35714286 | V5: 127001006 | W5: CAÇAROLA
A6: BEMOL 34 | B6: =_xlfn.XLOOKUP(A6,'Base de Dados'!D:D,'Base de Dados'!B:B) -> TIMBRO SWISS SA | C6: =_xlfn.XLOOKUP(PRECIFICAÇÃO[[#This Row],[INVOICE]],'Base de Dados'!D:D,'Base de Dados'!X:X) -> CONCLUÍDO | D6: 267945 | E6: ASSADEIRA BAUMON 1800ML VDR GC-O1800 | F6: 7800 | G6: 3.01 | H6: 5.0378 | I6: =H6*G6 -> 15.163778 | J6: =I6*F6 -> 118277.47 | K6: =J6/_xlfn.XLOOKUP(A6,'Base de Dados'!D:D,'Base de Dados'!M:M) -> 0.36104714 | L6: =K6*_xlfn.XLOOKUP(A6,'Base de Dados'!D:D,'Base de Dados'!N:N) -> 9821.9697 | M6: =J6+L6 -> 128099.44 | N6: =M6/F6 -> 16.423005 | O6: =R6-0.1 -> 0.42527551 | P6: =ROUND(N6/O6,0) -> 39 | Q6: =(P6-N6)/P6 -> 0.57889731 | R6: 0.52527551 | S6: =Q6-R6 -> 0.053621799 | T6: =P6+10 -> 49 | U6: =(T6-P6)/T6 -> 0.20408163 | V6: 127001002 | W6: ASSADEIRAS/FÔRMAS
A7: BEMOL 34 | B7: =_xlfn.XLOOKUP(A7,'Base de Dados'!D:D,'Base de Dados'!B:B) -> TIMBRO SWISS SA | C7: =_xlfn.XLOOKUP(PRECIFICAÇÃO[[#This Row],[INVOICE]],'Base de Dados'!D:D,'Base de Dados'!X:X) -> CONCLUÍDO | D7: 268132 | E7: POTE BAUMON HERMÉT 2260ML RET C/T JL002 | F7: 12984 | G7: 2.11 | H7: 5.0378 | I7: =H7*G7 -> 10.629758 | J7: =I7*F7 -> 138016.78 | K7: =J7/_xlfn.XLOOKUP(A7,'Base de Dados'!D:D,'Base de Dados'!M:M) -> 0.42130224 | L7: =K7*_xlfn.XLOOKUP(A7,'Base de Dados'!D:D,'Base de Dados'!N:N) -> 11461.157 | M7: =J7+L7 -> 149477.93 | N7: =M7/F7 -> 11.512472 | O7: =R7-0.1 -> 0.4092054 | P7: =ROUND(N7/O7,0) -> 28 | Q7: =(P7-N7)/P7 -> 0.58884029 | R7: 0.5092054 | S7: =Q7-R7 -> 0.079634891 | T7: =P7+10 -> 38 | U7: =(T7-P7)/T7 -> 0.26315789 | V7: 127001014 | W7: POTES
A8: BEMOL 34 | B8: =_xlfn.XLOOKUP(A8,'Base de Dados'!D:D,'Base de Dados'!B:B) -> TIMBRO SWISS SA | C8: =_xlfn.XLOOKUP(PRECIFICAÇÃO[[#This Row],[INVOICE]],'Base de Dados'!D:D,'Base de Dados'!X:X) -> CONCLUÍDO | D8: 268133 | E8: POTE BAUMON HERMÉT 1040ML C/T R195 | F8: 3000 | G8: 1.28 | H8: 5.0378 | I8: =H8*G8 -> 6.448384 | J8: =I8*F8 -> 19345.152 | K8: =J8/_xlfn.XLOOKUP(A8,'Base de Dados'!D:D,'Base de Dados'!M:M) -> 0.059051921 | L8: =K8*_xlfn.XLOOKUP(A8,'Base de Dados'!D:D,'Base de Dados'!N:N) -> 1606.4556 | M8: =J8+L8 -> 20951.608 | N8: =M8/F8 -> 6.9838692 | O8: =R8-0.1 -> 0.4092054 | P8: =ROUND(N8/O8,0) -> 17 | Q8: =(P8-N8)/P8 -> 0.58918417 | R8: 0.5092054 | S8: =Q8-R8 -> 0.079978766 | T8: =P8+10 -> 27 | U8: =(T8-P8)/T8 -> 0.37037037 | V8: 127001014 | W8: POTES
A9: BEMOL 27 | B9: =_xlfn.XLOOKUP(A9,'Base de Dados'!D:D,'Base de Dados'!B:B) -> TIMBRO SWISS SA | C9: =_xlfn.XLOOKUP(PRECIFICAÇÃO[[#This Row],[INVOICE]],'Base de Dados'!D:D,'Base de Dados'!X:X) -> CONCLUÍDO | D9: 238697 | E9: FRITAD BAUMON AIR FRYER 3,5L YJ-613D PT | F9: 2112 | G9: 17.08 | H9: 5.287 | I9: =H9*G9 -> 90.30196 | J9: =I9*F9 -> 190717.74 | K9: =J9/_xlfn.XLOOKUP(A9,'Base de Dados'!D:D,'Base de Dados'!M:M) -> 1 | L9: =K9*_xlfn.XLOOKUP(A9,'Base de Dados'!D:D,'Base de Dados'!N:N) -> 12270.97 | M9: =J9+L9 -> 202988.71 | N9: =M9/F9 -> 96.112078 | O9: =R9-0.1 -> 0.39270865 | P9: =ROUND(N9/O9,0) -> 245 | Q9: =(P9-N9)/P9 -> 0.6077058 | R9: 0.49270865 | S9: =Q9-R9 -> 0.11499715 | T9: =P9+10 -> 255 | U9: =(T9-P9)/T9 -> 0.039215686 | V9: 111001012 | W9: FRITADEIRA
A10: BEMOL 29 | B10: =_xlfn.XLOOKUP(A10,'Base de Dados'!D:D,'Base de Dados'!B:B) -> TIMBRO SWISS SA | C10: =_xlfn.XLOOKUP(PRECIFICAÇÃO[[#This Row],[INVOICE]],'Base de Dados'!D:D,'Base de Dados'!X:X) -> CONCLUÍDO | D10: 358229 | E10: FRIGOBAR BAUMON 46L HC46 BR | F10: 425 | G10: 49.32 | H10: 5.287 | I10: =H10*G10 -> 260.75484 | J10: =I10*F10 -> 110820.81 | K10: =J10/_xlfn.XLOOKUP(A10,'Base de Dados'!D:D,'Base de Dados'!M:M) -> 0.63854872 | L10: =K10*_xlfn.XLOOKUP(A10,'Base de Dados'!D:D,'Base de Dados'!N:N) -> 7089.6149 | M10: =J10+L10 -> 117910.42 | N10: =M10/F10 -> 277.43629 | O10: =R10-0.1 -> 0.35806811 | P10: =ROUND(N10/O10,0) -> 775 | Q10: =(P10-N10)/P10 -> 0.64201769 | R10: 0.45806811 | S10: =Q10-R10 -> 0.18394959 | T10: =P10+10 -> 785 | U10: =(T10-P10)/T10 -> 0.012738854 | V10: 117006005 | W10: FRIGOBAR
A11: BEMOL 29 | B11: =_xlfn.XLOOKUP(A11,'Base de Dados'!D:D,'Base de Dados'!B:B) -> TIMBRO SWISS SA | C11: =_xlfn.XLOOKUP(PRECIFICAÇÃO[[#This Row],[INVOICE]],'Base de Dados'!D:D,'Base de Dados'!X:X) -> CONCLUÍDO | D11: 238723 | E11: FERRO BAUMON VAPOR LM-2262 AZ | F11: 2100 | G11: 5.65 | H11: 5.287 | I11: =H11*G11 -> 29.87155 | J11: =I11*F11 -> 62730.255 | K11: =J11/_xlfn.XLOOKUP(A11,'Base de Dados'!D:D,'Base de Dados'!M:M) -> 0.36145129 | L11: =K11*_xlfn.XLOOKUP(A11,'Base de Dados'!D:D,'Base de Dados'!N:N) -> 4013.0853 | M11: =J11+L11 -> 66743.34 | N11: =M11/F11 -> 31.782543 | O11: =R11-0.1 -> 0.41017662 | P11: =ROUND(N11/O11,0) -> 77 | Q11: =(P11-N11)/P11 -> 0.5872397 | R11: 0.51017662 | S11: =Q11-R11 -> 0.077063082 | T11: =P11+10 -> 87 | U11: =(T11-P11)/T11 -> 0.11494253 | V11: 111003001 | W11: FERRO À VAPOR
A12: BEMOL 17 | B12: =_xlfn.XLOOKUP(A12,'Base de Dados'!D:D,'Base de Dados'!B:B) -> TIMBRO SWISS SA | C12: =_xlfn.XLOOKUP(PRECIFICAÇÃO[[#This Row],[INVOICE]],'Base de Dados'!D:D,'Base de Dados'!X:X) -> CONCLUÍDO | D12: 373482 | E12: JG 3P CAMA SOLTEIRO BAUMON PREMIUM BG | F12: 528 | G12: 8.5 | H12: 5.2308 | I12: =H12*G12 -> 44.4618 | J12: =I12*F12 -> 23475.83 | K12: =J12/_xlfn.XLOOKUP(A12,'Base de Dados'!D:D,'Base de Dados'!M:M) -> 0.043243977 | L12: =K12*_xlfn.XLOOKUP(A12,'Base de Dados'!D:D,'Base de Dados'!N:N) -> 657.33872 | M12: =J12+L12 -> 24133.169 | N12: =M12/F12 -> 45.70676 | O12: =R12-0.1 -> 0.42743575 | P12: =ROUND(N12/O12,0) -> 107 | Q12: =(P12-N12)/P12 -> 0.57283402 | R12: 0.52743575 | S12: =Q12-R12 -> 0.045398276 | T12: =P12+10 -> 117 | U12: =(T12-P12)/T12 -> 0.085470085 | V12: 107001003 | W12: LENÇOL
A13: BEMOL 17 | B13: =_xlfn.XLOOKUP(A13,'Base de Dados'!D:D,'Base de Dados'!B:B) -> TIMBRO SWISS SA | C13: =_xlfn.XLOOKUP(PRECIFICAÇÃO[[#This Row],[INVOICE]],'Base de Dados'!D:D,'Base de Dados'!X:X) -> CONCLUÍDO | D13: 373483 | E13: JG 4P CAMA SOLTEIRO BAUMON PREMIUM VD | F13: 540 | G13: 8.5 | H13: 5.2308 | I13: =H13*G13 -> 44.4618 | J13: =I13*F13 -> 24009.372 | K13: =J13/_xlfn.XLOOKUP(A13,'Base de Dados'!D:D,'Base de Dados'!M:M) -> 0.044226794 | L13: =K13*_xlfn.XLOOKUP(A13,'Base de Dados'!D:D,'Base de Dados'!N:N) -> 672.27823 | M13: =J13+L13 -> 24681.65 | N13: =M13/F13 -> 45.70676 | O13: =R13-0.1 -> 0.42743575 | P13: =ROUND(N13/O13,0) -> 107 | Q13: =(P13-N13)/P13 -> 0.57283402 | R13: 0.52743575 | S13: =Q13-R13 -> 0.045398276 | T13: =P13+10 -> 117 | U13: =(T13-P13)/T13 -> 0.085470085 | V13: 107001003 | W13: LENÇOL
... A47: BEMOL 40 | B47: =_xlfn.XLOOKUP(A47,'Base de Dados'!D:D,'Base de Dados'!B:B) -> TIMBRO SWISS SA | C47: =_xlfn.XLOOKUP(PRECIFICAÇÃO[[#This Row],[INVOICE]],'Base de Dados'!D:D,'Base de Dados'!X:X) -> CONCLUÍDO | D47: 387147 | E47: FORNO ELÉTR BAUMON BANCADA 60L JK60A BR | F47: 1575 | G47: 40.71 | H47: 5.1088 | I47: =H47*G47 -> 207.97925 | J47: =I47*F47 -> 327567.32 | K47: =J47/_xlfn.XLOOKUP(A47,'Base de Dados'!D:D,'Base de Dados'!M:M) -> 0.99999999 | L47: =K47*_xlfn.XLOOKUP(A47,'Base de Dados'!D:D,'Base de Dados'!N:N) -> 44344.379 | M47: =J47+L47 -> 371911.7 | N47: =M47/F47 -> 236.13441 | O47: =R47-0.1 -> 0.38095639 | P47: =ROUND(N47/O47,0) -> 620 | Q47: =(P47-N47)/P47 -> 0.61913805 | R47: 0.48095639 | S47: =Q47-R47 -> 0.13818166 | T47: =P47+10 -> 630 | U47: =(T47-P47)/T47 -> 0.015873016 | V47: 117001006 | W47: FORNO ELÉTRICO
A48: BEMOL003B | B48: =_xlfn.XLOOKUP(A48,'Base de Dados'!D:D,'Base de Dados'!B:B) -> TIMBRO SWISS SA | C48: CONCLUÍDO | D48: 238722 | E48: FERRO BAUMON SECO LM-209A AZ | F48: 3360 | G48: =4500/1000 -> 4.5 | H48: 5.7422 | I48: =H48*G48 -> 25.8399 | J48: =I48*F48 -> 86822.064 | K48: =J48/_xlfn.XLOOKUP(A48,'Base de Dados'!D:D,'Base de Dados'!M:M) -> 0.24022688 | L48: =K48*_xlfn.XLOOKUP(A48,'Base de Dados'!D:D,'Base de Dados'!N:N) -> 8966.3002 | M48: =J48+L48 -> 95788.364 | N48: =M48/F48 -> 28.508442 | O48: =R48-0.1 -> 0.4138077 | P48: =ROUND(N48/O48,0) -> 69 | Q48: =(P48-N48)/P48 -> 0.58683418 | R48: 0.5138077 | S48: =Q48-R48 -> 0.07302648 | T48: =P48+10 -> 79 | U48: =(T48-P48)/T48 -> 0.12658228 | V48: 111003005 | W48: FERRO SECO
A49: BEMOL003B | B49: =_xlfn.XLOOKUP(A49,'Base de Dados'!D:D,'Base de Dados'!B:B) -> TIMBRO SWISS SA | C49: CONCLUÍDO | D49: 238723 | E49: FERRO BAUMON VAPOR LM-2262 AZ | F49: 2600 | G49: =5650/1000 -> 5.65 | H49: 5.7422 | I49: =H49*G49 -> 32.44343 | J49: =I49*F49 -> 84352.918 | K49: =J49/_xlfn.XLOOKUP(A49,'Base de Dados'!D:D,'Base de Dados'!M:M) -> 0.23339503 | L49: =K49*_xlfn.XLOOKUP(A49,'Base de Dados'!D:D,'Base de Dados'!N:N) -> 8711.3062 | M49: =J49+L49 -> 93064.224 | N49: =M49/F49 -> 35.793932 | O49: =R49-0.1 -> 0.41017662 | P49: =ROUND(N49/O49,0) -> 87 | Q49: =(P49-N49)/P49 -> 0.58857549 | R49: 0.51017662 | S49: =Q49-R49 -> 0.078398871 | T49: =P49+10 -> 97 | U49: =(T49-P49)/T49 -> 0.10309278 | V49: 111003001 | W49: FERRO À VAPOR
A50: BEMOL003B | B50: =_xlfn.XLOOKUP(A50,'Base de Dados'!D:D,'Base de Dados'!B:B) -> TIMBRO SWISS SA | C50: CONCLUÍDO | D50: 238699 | E50: CAFETEIRA BAUMON 108TS PT/PR | F50: 1320 | G50: 13.9 | H50: 5.7422 | I50: =H50*G50 -> 79.81658 | J50: =I50*F50 -> 105357.89 | K50: =J50/_xlfn.XLOOKUP(A50,'Base de Dados'!D:D,'Base de Dados'!M:M) -> 0.29151341 | L50: =K50*_xlfn.XLOOKUP(A50,'Base de Dados'!D:D,'Base de Dados'!N:N) -> 10880.534 | M50: =J50+L50 -> 116238.42 | N50: =M50/F50 -> 88.059409 | O50: =R50-0.1 -> 0.41243301 | P50: =ROUND(N50/O50,0) -> 214 | Q50: =(P50-N50)/P50 -> 0.58850744 | R50: 0.51243301 | S50: =Q50-R50 -> 0.076074422 | T50: =P50+10 -> 224 | U50: =(T50-P50)/T50 -> 0.044642857 | V50: 111001005 | W50: CAFETEIRA
A51: BEMOL003B | B51: =_xlfn.XLOOKUP(A51,'Base de Dados'!D:D,'Base de Dados'!B:B) -> TIMBRO SWISS SA | C51: CONCLUÍDO | D51: 238721 | E51: GRILL BAUMON 9228D PT | F51: 1350 | G51: 10.95 | H51: 5.7422 | I51: =H51*G51 -> 62.87709 | J51: =I51*F51 -> 84884.072 | K51: =J51/_xlfn.XLOOKUP(A51,'Base de Dados'!D:D,'Base de Dados'!M:M) -> 0.23486467 | L51: =K51*_xlfn.XLOOKUP(A51,'Base de Dados'!D:D,'Base de Dados'!N:N) -> 8766.1595 | M51: =J51+L51 -> 93650.231 | N51: =M51/F51 -> 69.370541 | O51: =R51-0.1 -> 0.37835474 | P51: =ROUND(N51/O51,0) -> 183 | Q51: =(P51-N51)/P51 -> 0.620926 | R51: 0.47835474 | S51: =Q51-R51 -> 0.14257126 | T51: =P51+10 -> 193 | U51: =(T51-P51)/T51 -> 0.051813472 | V51: 111001013 | W51: GRILL
A52: BEMOL003A | B52: =_xlfn.XLOOKUP(A52,'Base de Dados'!D:D,'Base de Dados'!B:B) -> TIMBRO SWISS SA | C52: CONCLUÍDO | D52: 238699 | E52: CAFETEIRA BAUMON 108TS PT/PR | F52: 1320 | G52: 13.9 | H52: 5.6852 | I52: =H52*G52 -> 79.02428 | J52: =I52*F52 -> 104312.05 | K52: =J52/_xlfn.XLOOKUP(A52,'Base de Dados'!D:D,'Base de Dados'!M:M) -> 0.31531592 | L52: =K52*_xlfn.XLOOKUP(A52,'Base de Dados'!D:D,'Base de Dados'!N:N) -> 11652.121 | M52: =J52+L52 -> 115964.17 | N52: =M52/F52 -> 87.851645 | O52: =R52-0.1 -> 0.39291767 | P52: =ROUND(N52/O52,0) -> 224 | Q52: =(P52-N52)/P52 -> 0.60780516 | R52: 0.49291767 | S52: =Q52-R52 -> 0.11488749 | T52: =P52+10 -> 234 | U52: =(T52-P52)/T52 -> 0.042735043 | V52: 111001005 | W52: CAFETEIRA
A53: BEMOL003A | B53: =_xlfn.XLOOKUP(A53,'Base de Dados'!D:D,'Base de Dados'!B:B) -> TIMBRO SWISS SA | C53: CONCLUÍDO | D53: 238700 | E53: SANDUICHEIRA BAUMON FS-8009C PT | F53: 4404 | G53: 5.69 | H53: 5.6852 | I53: =H53*G53 -> 32.348788 | J53: =I53*F53 -> 142464.06 | K53: =J53/_xlfn.XLOOKUP(A53,'Base de Dados'!D:D,'Base de Dados'!M:M) -> 0.43064236 | L53: =K53*_xlfn.XLOOKUP(A53,'Base de Dados'!D:D,'Base de Dados'!N:N) -> 15913.872 | M53: =J53+L53 -> 158377.93 | N53: =M53/F53 -> 35.962292 | O53: =R53-0.1 -> 0.39291767 | P53: =ROUND(N53/O53,0) -> 92 | Q53: =(P53-N53)/P53 -> 0.60910552 | R53: 0.49291767 | S53: =Q53-R53 -> 0.11618786 | T53: =P53+10 -> 102 | U53: =(T53-P53)/T53 -> 0.098039216 | V53: 111001020 | W53: SANDUICHEIRA
A54: BEMOL003A | B54: =_xlfn.XLOOKUP(A54,'Base de Dados'!D:D,'Base de Dados'!B:B) -> TIMBRO SWISS SA | C54: CONCLUÍDO | D54: 238721 | E54: GRILL BAUMON 9228D PT | F54: 1350 | G54: 10.95 | H54: 5.6852 | I54: =H54*G54 -> 62.25294 | J54: =I54*F54 -> 84041.469 | K54: =J54/_xlfn.XLOOKUP(A54,'Base de Dados'!D:D,'Base de Dados'!M:M) -> 0.25404173 | L54: =K54*_xlfn.XLOOKUP(A54,'Base de Dados'!D:D,'Base de Dados'!N:N) -> 9387.8071 | M54: =J54+L54 -> 93429.276 | N54: =M54/F54 -> 69.206871 | O54: =R54-0.1 -> 0.37835474 | P54: =ROUND(N54/O54,0) -> 183 | Q54: =(P54-N54)/P54 -> 0.62182038 | R54: 0.47835474 | S54: =Q54-R54 -> 0.14346563 | T54: =P54+10 -> 193 | U54: =(T54-P54)/T54 -> 0.051813472 | V54: 111001013 | W54: GRILL
A55: BEMOL004 | B55: =_xlfn.XLOOKUP(A55,'Base de Dados'!D:D,'Base de Dados'!B:B) -> TIMBRO SWISS SA | C55: CONCLUÍDO | D55: 267940 | E55: ASSAD BAUMON VIDRO OVAL 3000ML OVAL-3000 | F55: 2448 | G55: 2.21 | H55: 5.5213 | I55: =H55*G55 -> 12.202073 | J55: =I55*F55 -> 29870.675 | K55: =J55/_xlfn.XLOOKUP(A55,'Base de Dados'!D:D,'Base de Dados'!M:M) -> 0.078915309 | L55: =K55*_xlfn.XLOOKUP(A55,'Base de Dados'!D:D,'Base de Dados'!N:N) -> 2352.8615 | M55: =J55+L55 -> 32223.536 | N55: =M55/F55 -> 13.163209 | O55: =R55-0.1 -> 0.42527551 | P55: =ROUND(N55/O55,0) -> 31 | Q55: =(P55-N55)/P55 -> 0.57538035 | R55: 0.52527551 | S55: =Q55-R55 -> 0.050104835 | T55: =P55+10 -> 41 | U55: =(T55-P55)/T55 -> 0.24390244 | V55: 127001002 | W55: ASSADEIRAS/FÔRMAS
A56: BEMOL004 | B56: =_xlfn.XLOOKUP(A56,'Base de Dados'!D:D,'Base de Dados'!B:B) -> TIMBRO SWISS SA | C56: CONCLUÍDO | D56: 267870 | E56: POTE HERM BAUMON RET 630ML C/ TAMPA R170 | F56: 2448 | G56: 0.95 | H56: 5.5213 | I56: =H56*G56 -> 5.245235 | J56: =I56*F56 -> 12840.335 | K56: =J56/_xlfn.XLOOKUP(A56,'Base de Dados'!D:D,'Base de Dados'!M:M) -> 0.03392287 | L56: =K56*_xlfn.XLOOKUP(A56,'Base de Dados'!D:D,'Base de Dados'!N:N) -> 1011.4111 | M56: =J56+L56 -> 13851.746 | N56: =M56/F56 -> 5.6583931 | O56: =R56-0.1 -> 0.4092054 | P56: =ROUND(N56/O56,0) -> 14 | Q56: =(P56-N56)/P56 -> 0.59582906 | R56: 0.5092054 | S56: =Q56-R56 -> 0.086623663 | T56: =P56+10 -> 24 | U56: =(T56-P56)/T56 -> 0.41666667 | V56: 127001014 | W56: POTES
A57: BEMOL004 | B57: =_xlfn.XLOOKUP(A57,'Base de Dados'!D:D,'Base de Dados'!B:B) -> TIMBRO SWISS SA | C57: CONCLUÍDO | D57: 267947 | E57: COPO MEDIDOR BAUMON VDR 1000ML LB-1000P | F57: 1200 | G57: 1.94 | H57: 5.5213 | I57: =H57*G57 -> 10.711322 | J57: =I57*F57 -> 12853.586 | K57: =J57/_xlfn.XLOOKUP(A57,'Base de Dados'!D:D,'Base de Dados'!M:M) -> 0.033957878 | L57: =K57*_xlfn.XLOOKUP(A57,'Base de Dados'!D:D,'Base de Dados'!N:N) -> 1012.4548 | M57: =J57+L57 -> 13866.041 | N57: =M57/F57 -> 11.555034 | O57: =R57-0.1 -> 0.44510234 | P57: =ROUND(N57/O57,0) -> 26 | Q57: =(P57-N57)/P57 -> 0.5555756 | R57: 0.54510234 | S57: =Q57-R57 -> 0.010473258 | T57: =P57+10 -> 36 | U57: =(T57-P57)/T57 -> 0.27777778 | V57: 127001001 | W57: ACESSÓRIOS DE COZINHA
A58: BEMOL004 | B58: =_xlfn.XLOOKUP(A58,'Base de Dados'!D:D,'Base de Dados'!B:B) -> TIMBRO SWISS SA | C58: CONCLUÍDO | D58: 267946 | E58: COPO MEDIDOR BAUMON VDR 500ML LB-500P | F58: 1200 | G58: 1.33 | H58: 5.5213 | I58: =H58*G58 -> 7.343329 | J58: =I58*F58 -> 8811.9948 | K58: =J58/_xlfn.XLOOKUP(A58,'Base de Dados'!D:D,'Base de Dados'!M:M) -> 0.023280401 | L58: =K58*_xlfn.XLOOKUP(A58,'Base de Dados'!D:D,'Base de Dados'!N:N) -> 694.10563 | M58: =J58+L58 -> 9506.1004 | N58: =M58/F58 -> 7.9217504 | O58: =R58-0.1 -> 0.44510234 | P58: =ROUND(N58/O58,0) -> 18 | Q58: =(P58-N58)/P58 -> 0.55990276 | R58: 0.54510234 | S58: =Q58-R58 -> 0.014800414 | T58: =P58+10 -> 28 | U58: =(T58-P58)/T58 -> 0.35714286 | V58: 127001001 | W58: ACESSÓRIOS DE COZINHA
A59: BEMOL004 | B59: =_xlfn.XLOOKUP(A59,'Base de Dados'!D:D,'Base de Dados'!B:B) -> TIMBRO SWISS SA | C59: CONCLUÍDO | D59: 267945 | E59: ASSADEIRA BAUMON VIDRO 1800ML GC-O1800 | F59: 1200 | G59: 3.01 | H59: 5.5213 | I59: =H59*G59 -> 16.619113 | J59: =I59*F59 -> 19942.936 | K59: =J59/_xlfn.XLOOKUP(A59,'Base de Dados'!D:D,'Base de Dados'!M:M) -> 0.052687224 | L59: =K59*_xlfn.XLOOKUP(A59,'Base de Dados'!D:D,'Base de Dados'!N:N) -> 1570.8706 | M59: =J59+L59 -> 21513.806 | N59: =M59/F59 -> 17.928172 | O59: =R59-0.1 -> 0.42527551 | P59: =ROUND(N59/O59,0) -> 42 | Q59: =(P59-N59)/P59 -> 0.57313877 | R59: 0.52527551 | S59: =Q59-R59 -> 0.047863253 | T59: =P59+10 -> 52 | U59: =(T59-P59)/T59 -> 0.19230769 | V59: 127001002 | W59: ASSADEIRAS/FÔRMAS
A60: BEMOL004 | B60: =_xlfn.XLOOKUP(A60,'Base de Dados'!D:D,'Base de Dados'!B:B) -> TIMBRO SWISS SA | C60: CONCLUÍDO | D60: 267944 | E60: CAÇAROLA BAUMON VIDRO 2000ML GC-2000 | F60: 1662 | G60: 2.6 | H60: 5.5213 | I60: =H60*G60 -> 14.35538 | J60: =I60*F60 -> 23858.642 | K60: =J60/_xlfn.XLOOKUP(A60,'Base de Dados'!D:D,'Base de Dados'!M:M) -> 0.063032124 | L60: =K60*_xlfn.XLOOKUP(A60,'Base de Dados'!D:D,'Base de Dados'!N:N) -> 1879.304 | M60: =J60+L60 -> 25737.946 | N60: =M60/F60 -> 15.486129 | O60: =R60-0.1 -> 0.44079732 | P60: =ROUND(N60/O60,0) -> 35 | Q60: =(P60-N60)/P60 -> 0.55753919 | R60: 0.54079732 | S60: =Q60-R60 -> 0.016741866 | T60: =P60+10 -> 45 | U60: =(T60-P60)/T60 -> 0.22222222 | V60: 127001006 | W60: CAÇAROLA
A61: BEMOL004 | B61: =_xlfn.XLOOKUP(A61,'Base de Dados'!D:D,'Base de Dados'!B:B) -> TIMBRO SWISS SA | C61: CONCLUÍDO | D61: 267943 | E61: CAÇAROLA BAUMON VIDRO 1500ML GC-1500 | F61: 2448 | G61: 1.95 | H61: 5.5213 | I61: =H61*G61 -> 10.766535 | J61: =I61*F61 -> 26356.478 | K61: =J61/_xlfn.XLOOKUP(A61,'Base de Dados'!D:D,'Base de Dados'!M:M) -> 0.069631155 | L61: =K61*_xlfn.XLOOKUP(A61,'Base de Dados'!D:D,'Base de Dados'!N:N) -> 2076.0543 | M61: =J61+L61 -> 28432.532 | N61: =M61/F61 -> 11.614596 | O61: =R61-0.1 -> 0.44079732 | P61: =ROUND(N61/O61,0) -> 26 | Q61: =(P61-N61)/P61 -> 0.55328475 | R61: 0.54079732 | S61: =Q61-R61 -> 0.012487435 | T61: =P61+10 -> 36 | U61: =(T61-P61)/T61 -> 0.27777778 | V61: 127001006 | W61: CAÇAROLA
... A73: BEMOL004 | B73: =_xlfn.XLOOKUP(A73,'Base de Dados'!D:D,'Base de Dados'!B:B) -> TIMBRO SWISS SA | C73: CONCLUÍDO | D73: 268133 | E73: POTE HERM BAUMON 1040ML C/TAMP R195 | F73: 2448 | G73: 1.28 | H73: 5.5213 | I73: =H73*G73 -> 7.067264 | J73: =I73*F73 -> 17300.662 | K73: =J73/_xlfn.XLOOKUP(A73,'Base de Dados'!D:D,'Base de Dados'!M:M) -> 0.045706604 | L73: =K73*_xlfn.XLOOKUP(A73,'Base de Dados'!D:D,'Base de Dados'!N:N) -> 1362.7433 | M73: =J73+L73 -> 18663.406 | N73: =M73/F73 -> 7.6239402 | O73: =R73-0.1 -> 0.4092054 | P73: =ROUND(N73/O73,0) -> 19 | Q73: =(P73-N73)/P73 -> 0.59873999 | R73: 0.5092054 | S73: =Q73-R73 -> 0.08953459 | T73: =P73+10 -> 29 | U73: =(T73-P73)/T73 -> 0.34482759 | V73: 127001014 | W73: POTES
A74: BEMOL 31 | B74: =_xlfn.XLOOKUP(A74,'Base de Dados'!D:D,'Base de Dados'!B:B) -> TIMBRO SWISS SA | C74: =_xlfn.XLOOKUP(PRECIFICAÇÃO[[#This Row],[INVOICE]],'Base de Dados'!D:D,'Base de Dados'!X:X) -> CONCLUÍDO | D74: 267946 | E74: COPO MEDIDOR BAUMON VDR 500ML LB-500P | F74: 2004 | G74: 1.33 | H74: 4.9587 | I74: =H74*G74 -> 6.595071 | J74: =I74*F74 -> 13216.522 | K74: =J74/_xlfn.XLOOKUP(A74,'Base de Dados'!D:D,'Base de Dados'!M:M) -> 0.038221482 | L74: =K74*_xlfn.XLOOKUP(A74,'Base de Dados'!D:D,'Base de Dados'!N:N) -> 880.93025 | M74: =J74+L74 -> 14097.453 | N74: =M74/F74 -> 7.034657 | O74: =R74-0.1 -> 0.44510234 | P74: =ROUND(N74/O74,0) -> 16 | Q74: =(P74-N74)/P74 -> 0.56033394 | R74: 0.54510234 | S74: =Q74-R74 -> 0.015231596 | T74: =P74+10 -> 26 | U74: =(T74-P74)/T74 -> 0.38461538 | V74: 127001001 | W74: ACESSÓRIOS DE COZINHA
A75: BEMOL 31 | B75: =_xlfn.XLOOKUP(A75,'Base de Dados'!D:D,'Base de Dados'!B:B) -> TIMBRO SWISS SA | C75: =_xlfn.XLOOKUP(PRECIFICAÇÃO[[#This Row],[INVOICE]],'Base de Dados'!D:D,'Base de Dados'!X:X) -> CONCLUÍDO | D75: 267869 | E75: POTE BAUMON HERMÉT 400ML RET C/T R145 | F75: 7020 | G75: 0.74 | H75: 4.9587 | I75: =H75*G75 -> 3.669438 | J75: =I75*F75 -> 25759.455 | K75: =J75/_xlfn.XLOOKUP(A75,'Base de Dados'!D:D,'Base de Dados'!M:M) -> 0.074494979 | L75: =K75*_xlfn.XLOOKUP(A75,'Base de Dados'!D:D,'Base de Dados'!N:N) -> 1716.9632 | M75: =J75+L75 -> 27476.418 | N75: =M75/F75 -> 3.9140197 | O75: =R75-0.1 -> 0.4092054 | P75: =ROUND(N75/O75,0) -> 10 | Q75: =(P75-N75)/P75 -> 0.60859803 | R75: 0.5092054 | S75: =Q75-R75 -> 0.099392634 | T75: =P75+10 -> 20 | U75: =(T75-P75)/T75 -> 0.5 | V75: 127001014 | W75: POTES
A76: BEMOL 31 | B76: =_xlfn.XLOOKUP(A76,'Base de Dados'!D:D,'Base de Dados'!B:B) -> TIMBRO SWISS SA | C76: =_xlfn.XLOOKUP(PRECIFICAÇÃO[[#This Row],[INVOICE]],'Base de Dados'!D:D,'Base de Dados'!X:X) -> CONCLUÍDO | D76: 267870 | E76: POTE BAUMON HÉRMET 630ML RET C/T R170 | F76: 6960 | G76: 0.95 | H76: 4.9587 | I76: =H76*G76 -> 4.710765 | J76: =I76*F76 -> 32786.924 | K76: =J76/_xlfn.XLOOKUP(A76,'Base de Dados'!D:D,'Base de Dados'!M:M) -> 0.094818049 | L76: =K76*_xlfn.XLOOKUP(A76,'Base de Dados'!D:D,'Base de Dados'!N:N) -> 2185.3702 | M76: =J76+L76 -> 34972.295 | N76: =M76/F76 -> 5.024755 | O76: =R76-0.1 -> 0.4092054 | P76: =ROUND(N76/O76,0) -> 12 | Q76: =(P76-N76)/P76 -> 0.58127042 | R76: 0.5092054 | S76: =Q76-R76 -> 0.072065019 | T76: =P76+10 -> 22 | U76: =(T76-P76)/T76 -> 0.45454545 | V76: 127001014 | W76: POTES
A77: BEMOL 31 | B77: =_xlfn.XLOOKUP(A77,'Base de Dados'!D:D,'Base de Dados'!B:B) -> TIMBRO SWISS SA | C77: =_xlfn.XLOOKUP(PRECIFICAÇÃO[[#This Row],[INVOICE]],'Base de Dados'!D:D,'Base de Dados'!X:X) -> CONCLUÍDO | D77: 267937 | E77: POTE BAUMON HERMÉT 1020ML RET C/T S195-3 | F77: 2016 | G77: 1.79 | H77: 4.9587 | I77: =H77*G77 -> 8.876073 | J77: =I77*F77 -> 17894.163 | K77: =J77/_xlfn.XLOOKUP(A77,'Base de Dados'!D:D,'Base de Dados'!M:M) -> 0.051748972 | L77: =K77*_xlfn.XLOOKUP(A77,'Base de Dados'!D:D,'Base de Dados'!N:N) -> 1192.7124 | M77: =J77+L77 -> 19086.876 | N77: =M77/F77 -> 9.4676962 | O77: =R77-0.1 -> 0.4092054 | P77: =ROUND(N77/O77,0) -> 23 | Q77: =(P77-N77)/P77 -> 0.58836103 | R77: 0.5092054 | S77: =Q77-R77 -> 0.079155635 | T77: =P77+10 -> 33 | U77: =(T77-P77)/T77 -> 0.3030303 | V77: 127001014 | W77: POTES
A78: BEMOL 31 | B78: =_xlfn.XLOOKUP(A78,'Base de Dados'!D:D,'Base de Dados'!B:B) -> TIMBRO SWISS SA | C78: =_xlfn.XLOOKUP(PRECIFICAÇÃO[[#This Row],[INVOICE]],'Base de Dados'!D:D,'Base de Dados'!X:X) -> CONCLUÍDO | D78: 267941 | E78: ASSAD BAUMON VIDRO QUAD 1800ML GB-S1800 | F78: 2004 | G78: 1.53 | H78: 4.9587 | I78: =H78*G78 -> 7.586811 | J78: =I78*F78 -> 15203.969 | K78: =J78/_xlfn.XLOOKUP(A78,'Base de Dados'!D:D,'Base de Dados'!M:M) -> 0.043969074 | L78: =K78*_xlfn.XLOOKUP(A78,'Base de Dados'!D:D,'Base de Dados'!N:N) -> 1013.401 | M78: =J78+L78 -> 16217.37 | N78: =M78/F78 -> 8.0925001 | O78: =R78-0.1 -> 0.42527551 | P78: =ROUND(N78/O78,0) -> 19 | Q78: =(P78-N78)/P78 -> 0.57407894 | R78: 0.52527551 | S78: =Q78-R78 -> 0.04880343 | T78: =P78+10 -> 29 | U78: =(T78-P78)/T78 -> 0.34482759 | V78: 127001002 | W78: ASSADEIRAS/FÔRMAS
A79: BEMOL 31 | B79: =_xlfn.XLOOKUP(A79,'Base de Dados'!D:D,'Base de Dados'!B:B) -> TIMBRO SWISS SA | C79: =_xlfn.XLOOKUP(PRECIFICAÇÃO[[#This Row],[INVOICE]],'Base de Dados'!D:D,'Base de Dados'!X:X) -> CONCLUÍDO | D79: 267942 | E79: CAÇAROLA BAUMON VIDRO 1000ML GC-1000 | F79: 2004 | G79: 1.46 | H79: 4.9587 | I79: =H79*G79 -> 7.239702 | J79: =I79*F79 -> 14508.363 | K79: =J79/_xlfn.XLOOKUP(A79,'Base de Dados'!D:D,'Base de Dados'!M:M) -> 0.041957417 | L79: =K79*_xlfn.XLOOKUP(A79,'Base de Dados'!D:D,'Base de Dados'!N:N) -> 967.03622 | M79: =J79+L79 -> 15475.399 | N79: =M79/F79 -> 7.722255 | O79: =R79-0.1 -> 0.44079732 | P79: =ROUND(N79/O79,0) -> 18 | Q79: =(P79-N79)/P79 -> 0.57098583 | R79: 0.54079732 | S79: =Q79-R79 -> 0.030188514 | T79: =P79+10 -> 28 | U79: =(T79-P79)/T79 -> 0.35714286 | V79: 127001006 | W79: CAÇAROLA
A80: BEMOL 31 | B80: =_xlfn.XLOOKUP(A80,'Base de Dados'!D:D,'Base de Dados'!B:B) -> TIMBRO SWISS SA | C80: =_xlfn.XLOOKUP(PRECIFICAÇÃO[[#This Row],[INVOICE]],'Base de Dados'!D:D,'Base de Dados'!X:X) -> CONCLUÍDO | D80: 267945 | E80: ASSADEIRA BAUMON VIDRO 1800ML GC-O1800 | F80: 8004 | G80: 3.01 | H80: 4.9587 | I80: =H80*G80 -> 14.925687 | J80: =I80*F80 -> 119465.2 | K80: =J80/_xlfn.XLOOKUP(A80,'Base de Dados'!D:D,'Base de Dados'!M:M) -> 0.34548703 | L80: =K80*_xlfn.XLOOKUP(A80,'Base de Dados'!D:D,'Base de Dados'!N:N) -> 7962.7988 | M80: =J80+L80 -> 127428 | N80: =M80/F80 -> 15.920539 | O80: =R80-0.1 -> 0.42527551 | P80: =ROUND(N80/O80,0) -> 37 | Q80: =(P80-N80)/P80 -> 0.56971515 | R80: 0.52527551 | S80: =Q80-R80 -> 0.044439639 | T80: =P80+10 -> 47 | U80: =(T80-P80)/T80 -> 0.21276596 | V80: 127001002 | W80: ASSADEIRAS/FÔRMAS
A81: BEMOL 31 | B81: =_xlfn.XLOOKUP(A81,'Base de Dados'!D:D,'Base de Dados'!B:B) -> TIMBRO SWISS SA | C81: =_xlfn.XLOOKUP(PRECIFICAÇÃO[[#This Row],[INVOICE]],'Base de Dados'!D:D,'Base de Dados'!X:X) -> CONCLUÍDO | D81: 268132 | E81: POTE HERM BAUMON RET 2260ML C/TAMP JL002 | F81: 6000 | G81: 2.11 | H81: 4.9587 | I81: =H81*G81 -> 10.462857 | J81: =I81*F81 -> 62777.142 | K81: =J81/_xlfn.XLOOKUP(A81,'Base de Dados'!D:D,'Base de Dados'!M:M) -> 0.18154817 | L81: =K81*_xlfn.XLOOKUP(A81,'Base de Dados'!D:D,'Base de Dados'!N:N) -> 4184.3295 | M81: =J81+L81 -> 66961.471 | N81: =M81/F81 -> 11.160245 | O81: =R81-0.1 -> 0.4092054 | P81: =ROUND(N81/O81,0) -> 27 | Q81: =(P81-N81)/P81 -> 0.58665758 | R81: 0.5092054 | S81: =Q81-R81 -> 0.077452184 | T81: =P81+10 -> 37 | U81: =(T81-P81)/T81 -> 0.27027027 | V81: 127001014 | W81: POTES
A82: BEMOL 31 | B82: =_xlfn.XLOOKUP(A82,'Base de Dados'!D:D,'Base de Dados'!B:B) -> TIMBRO SWISS SA | C82: =_xlfn.XLOOKUP(PRECIFICAÇÃO[[#This Row],[INVOICE]],'Base de Dados'!D:D,'Base de Dados'!X:X) -> CONCLUÍDO | D82: 268133 | E82: POTE HERM BAUMON 1040ML C/TAMP R195 | F82: 6960 | G82: 1.28 | H82: 4.9587 | I82: =H82*G82 -> 6.347136 | J82: =I82*F82 -> 44176.067 | K82: =J82/_xlfn.XLOOKUP(A82,'Base de Dados'!D:D,'Base de Dados'!M:M) -> 0.12775484 | L82: =K82*_xlfn.XLOOKUP(A82,'Base de Dados'!D:D,'Base de Dados'!N:N) -> 2944.4988 | M82: =J82+L82 -> 47120.565 | N82: =M82/F82 -> 6.7701962 | O82: =R82-0.1 -> 0.4092054 | P82: =ROUND(N82/O82,0) -> 17 | Q82: =(P82-N82)/P82 -> 0.60175317 | R82: 0.5092054 | S82: =Q82-R82 -> 0.092547767 | T82: =P82+10 -> 27 | U82: =(T82-P82)/T82 -> 0.37037037 | V82: 127001014 | W82: POTES
A83: BEMOL 42 | B83: =_xlfn.XLOOKUP(A83,'Base de Dados'!D:D,'Base de Dados'!B:B) -> TIMBRO SWISS SA | C83: =_xlfn.XLOOKUP(PRECIFICAÇÃO[[#This Row],[INVOICE]],'Base de Dados'!D:D,'Base de Dados'!X:X) -> CONCLUÍDO | D83: 383492 | E83: TRAVESSA BAUMON OVAL VIDRO C/TAMPA 2,4L | F83: 4998 | G83: 19 | H83: 5.1717 | I83: =H83*G83 -> 98.2623 | J83: =I83*F83 -> 491114.98 | K83: =J83/_xlfn.XLOOKUP(A83,'Base de Dados'!D:D,'Base de Dados'!M:M) -> 1.0902156 | L83: =K83*_xlfn.XLOOKUP(A83,'Base de Dados'!D:D,'Base de Dados'!N:N) -> 51426.647 | M83: =J83+L83 -> 542541.62 | N83: =M83/F83 -> 108.55175 | O83: =R83-0.1 -> 0.43667821 | P83: =ROUND(N83/O83,0) -> 249 | Q83: =(P83-N83)/P83 -> 0.56404922 | R83: 0.53667821 | S83: =Q83-R83 -> 0.027371005 | T83: =P83+10 -> 259 | U83: =(T83-P83)/T83 -> 0.038610039 | V83: 127001003 | W83: BANDEJAS/TRAVESSAS/BAIXELAS
A84: BEMOL 42 | B84: =_xlfn.XLOOKUP(A84,'Base de Dados'!D:D,'Base de Dados'!B:B) -> TIMBRO SWISS SA | C84: =_xlfn.XLOOKUP(PRECIFICAÇÃO[[#This Row],[INVOICE]],'Base de Dados'!D:D,'Base de Dados'!X:X) -> CONCLUÍDO | D84: 383493 | E84: TRAVESSA BAUMON OVAL VIDRO C/TAMPA 3L | F84: 6252 | G84: 26 | H84: 5.1717 | I84: =H84*G84 -> 134.4642 | J84: =I84*F84 -> 840670.18 | K84: =J84/_xlfn.XLOOKUP(A84,'Base de Dados'!D:D,'Base de Dados'!M:M) -> 1.8661857 | L84: =K84*_xlfn.XLOOKUP(A84,'Base de Dados'!D:D,'Base de Dados'!N:N) -> 88029.994 | M84: =J84+L84 -> 928700.17 | N84: =M84/F84 -> 148.54449 | O84: =R84-0.1 -> 0.43667821 | P84: =ROUND(N84/O84,0) -> 340 | Q84: =(P84-N84)/P84 -> 0.56310443 | R84: 0.53667821 | S84: =Q84-R84 -> 0.02642622 | T84: =P84+10 -> 350 | U84: =(T84-P84)/T84 -> 0.028571429 | V84: 127001003 | W84: BANDEJAS/TRAVESSAS/BAIXELAS
A85: BEMOL 42 | B85: =_xlfn.XLOOKUP(A85,'Base de Dados'!D:D,'Base de Dados'!B:B) -> TIMBRO SWISS SA | C85: =_xlfn.XLOOKUP(PRECIFICAÇÃO[[#This Row],[INVOICE]],'Base de Dados'!D:D,'Base de Dados'!X:X) -> CONCLUÍDO | D85: 383494 | E85: TRAVESSA BAUMON OVAL VIDRO C/TAMPA 4L | F85: 5832 | G85: 34.1 | H85: 5.1717 | I85: =H85*G85 -> 176.35497 | J85: =I85*F85 -> 1028502.2 | K85: =J85/_xlfn.XLOOKUP(A85,'Base de Dados'!D:D,'Base de Dados'!M:M) -> 2.2831499 | L85: =K85*_xlfn.XLOOKUP(A85,'Base de Dados'!D:D,'Base de Dados'!N:N) -> 107698.65 | M85: =J85+L85 -> 1136200.8 | N85: =M85/F85 -> 194.82182 | O85: =R85-0.1 -> 0.43667821 | P85: =ROUND(N85/O85,0) -> 446 | Q85: =(P85-N85)/P85 -> 0.56317978 | R85: 0.53667821 | S85: =Q85-R85 -> 0.026501573 | T85: =P85+10 -> 456 | U85: =(T85-P85)/T85 -> 0.021929825 | V85: 127001003 | W85: BANDEJAS/TRAVESSAS/BAIXELAS
... A179: BEMOL 33 | B179: =_xlfn.XLOOKUP(A179,'Base de Dados'!D:D,'Base de Dados'!B:B) -> TIMBRO SWISS SA | C179: =_xlfn.XLOOKUP(PRECIFICAÇÃO[[#This Row],[INVOICE]],'Base de Dados'!D:D,'Base de Dados'!X:X) -> CONCLUÍDO | D179: 238697 | E179: FRITAD BAUMON AIR FRYER 3,5L YJ-613D PT | F179: 2112 | G179: 17.08 | H179: 4.9809 | I179: =H179*G179 -> 85.073772 | J179: =I179*F179 -> 179675.81 | K179: =J179/_xlfn.XLOOKUP(A179,'Base de Dados'!D:D,'Base de Dados'!M:M) -> 0.99999998 | L179: =K179*_xlfn.XLOOKUP(A179,'Base de Dados'!D:D,'Base de Dados'!N:N) -> 14599.02 | M179: =J179+L179 -> 194274.83 | N179: =M179/F179 -> 91.986187 | O179: =R179-0.1 -> 0.39270865 | P179: =ROUND(N179/O179,0) -> 234 | Q179: =(P179-N179)/P179 -> 0.60689664 | R179: 0.49270865 | S179: =Q179-R179 -> 0.11418799 | T179: =P179+10 -> 244 | U179: =(T179-P179)/T179 -> 0.040983607 | V179: 111001012 | W179: FRITADEIRA
A180: BEMOL 36 | B180: =_xlfn.XLOOKUP(A180,'Base de Dados'!D:D,'Base de Dados'!B:B) -> TIMBRO SWISS SA | C180: =_xlfn.XLOOKUP(PRECIFICAÇÃO[[#This Row],[INVOICE]],'Base de Dados'!D:D,'Base de Dados'!X:X) -> CONCLUÍDO | D180: 272953 | E180: MINI PROCESSADOR BAUMON WC-P02 PT | F180: 4008 | G180: 5.79 | H180: 5.1176 | I180: =H180*G180 -> 29.630904 | J180: =I180*F180 -> 118760.66 | K180: =J180/_xlfn.XLOOKUP(A180,'Base de Dados'!D:D,'Base de Dados'!M:M) -> 0.17291623 | L180: =K180*_xlfn.XLOOKUP(A180,'Base de Dados'!D:D,'Base de Dados'!N:N) -> 4966.1491 | M180: =J180+L180 -> 123726.81 | N180: =M180/F180 -> 30.869963 | O180: =R180-0.1 -> 0.39018383 | P180: 99 | Q180: =(P180-N180)/P180 -> 0.68818219 | R180: 0.49018383 | S180: =Q180-R180 -> 0.19799836 | T180: 0 | U180: =(T180-P180)/T180 -> #DIV/0! | V180: 111001019 | W180: PROCESSADOR DE ALIMENTOS
A181: BEMOL 36 | B181: =_xlfn.XLOOKUP(A181,'Base de Dados'!D:D,'Base de Dados'!B:B) -> TIMBRO SWISS SA | C181: =_xlfn.XLOOKUP(PRECIFICAÇÃO[[#This Row],[INVOICE]],'Base de Dados'!D:D,'Base de Dados'!X:X) -> CONCLUÍDO | D181: 272958 | E181: SECADOR BAUMON 2000W 127V SD-808 AZ | F181: 3000 | G181: 6.46 | H181: 5.1176 | I181: =H181*G181 -> 33.059696 | J181: =I181*F181 -> 99179.088 | K181: =J181/_xlfn.XLOOKUP(A181,'Base de Dados'!D:D,'Base de Dados'!M:M) -> 0.14440534 | L181: =K181*_xlfn.XLOOKUP(A181,'Base de Dados'!D:D,'Base de Dados'!N:N) -> 4147.3172 | M181: =J181+L181 -> 103326.41 | N181: =M181/F181 -> 34.442135 | O181: =R181-0.1 -> 0.4095633 | P181: 149 | Q181: =(P181-N181)/P181 -> 0.76884473 | R181: 0.5095633 | S181: =Q181-R181 -> 0.25928143 | T181: 0 | U181: =(T181-P181)/T181 -> #DIV/0! | V181: 110001009 | W181: SECADOR
A182: BEMOL 36 | B182: =_xlfn.XLOOKUP(A182,'Base de Dados'!D:D,'Base de Dados'!B:B) -> TIMBRO SWISS SA | C182: =_xlfn.XLOOKUP(PRECIFICAÇÃO[[#This Row],[INVOICE]],'Base de Dados'!D:D,'Base de Dados'!X:X) -> CONCLUÍDO | D182: 272956 | E182: PRANCHA BAUMON 127V 200C SD-515 AZ | F182: 2016 | G182: 4.69 | H182: 5.1176 | I182: =H182*G182 -> 24.001544 | J182: =I182*F182 -> 48387.113 | K182: =J182/_xlfn.XLOOKUP(A182,'Base de Dados'!D:D,'Base de Dados'!M:M) -> 0.070451925 | L182: =K182*_xlfn.XLOOKUP(A182,'Base de Dados'!D:D,'Base de Dados'!N:N) -> 2023.3772 | M182: =J182+L182 -> 50410.49 | N182: =M182/F182 -> 25.005203 | O182: =R182-0.1 -> 0.40088862 | P182: 109 | Q182: =(P182-N182)/P182 -> 0.77059447 | R182: 0.50088862 | S182: =Q182-R182 -> 0.26970584 | T182: 0 | U182: =(T182-P182)/T182 -> #DIV/0! | V182: 110001004 | W182: CHAPA
A183: BEMOL 36 | B183: =_xlfn.XLOOKUP(A183,'Base de Dados'!D:D,'Base de Dados'!B:B) -> TIMBRO SWISS SA | C183: =_xlfn.XLOOKUP(PRECIFICAÇÃO[[#This Row],[INVOICE]],'Base de Dados'!D:D,'Base de Dados'!X:X) -> CONCLUÍDO | D183: 272957 | E183: PRANCHA BAUMON 127V 230C SD-510A AZ | F183: 3240 | G183: 6.08 | H183: 5.1176 | I183: =H183*G183 -> 31.115008 | J183: =I183*F183 -> 100812.63 | K183: =J183/_xlfn.XLOOKUP(A183,'Base de Dados'!D:D,'Base de Dados'!M:M) -> 0.14678379 | L183: =K183*_xlfn.XLOOKUP(A183,'Base de Dados'!D:D,'Base de Dados'!N:N) -> 4215.6259 | M183: =J183+L183 -> 105028.25 | N183: =M183/F183 -> 32.416127 | O183: =R183-0.1 -> 0.40088862 | P183: 149 | Q183: =(P183-N183)/P183 -> 0.7824421 | R183: 0.50088862 | S183: =Q183-R183 -> 0.28155348 | T183: 0 | U183: =(T183-P183)/T183 -> #DIV/0! | V183: 110001004 | W183: CHAPA
A184: BEMOL 36 | B184: =_xlfn.XLOOKUP(A184,'Base de Dados'!D:D,'Base de Dados'!B:B) -> TIMBRO SWISS SA | C184: =_xlfn.XLOOKUP(PRECIFICAÇÃO[[#This Row],[INVOICE]],'Base de Dados'!D:D,'Base de Dados'!X:X) -> CONCLUÍDO | D184: 238722 | E184: FERRO BAUMON SECO LM-209A AZ | F184: 2892 | G184: 4.5 | H184: 5.1176 | I184: =H184*G184 -> 23.0292 | J184: =I184*F184 -> 66600.446 | K184: =J184/_xlfn.XLOOKUP(A184,'Base de Dados'!D:D,'Base de Dados'!M:M) -> 0.096970648 | L184: =K184*_xlfn.XLOOKUP(A184,'Base de Dados'!D:D,'Base de Dados'!N:N) -> 2784.9941 | M184: =J184+L184 -> 69385.44 | N184: =M184/F184 -> 23.992199 | O184: =R184-0.1 -> 0.4138077 | P184: 79 | Q184: =(P184-N184)/P184 -> 0.69630127 | R184: 0.5138077 | S184: =Q184-R184 -> 0.18249358 | T184: 0 | U184: =(T184-P184)/T184 -> #DIV/0! | V184: 111003005 | W184: FERRO SECO
A185: BEMOL 36 | B185: =_xlfn.XLOOKUP(A185,'Base de Dados'!D:D,'Base de Dados'!B:B) -> TIMBRO SWISS SA | C185: =_xlfn.XLOOKUP(PRECIFICAÇÃO[[#This Row],[INVOICE]],'Base de Dados'!D:D,'Base de Dados'!X:X) -> CONCLUÍDO | D185: 238697 | E185: FRITAD BAUMON AIR FRYER 3,5L YJ-613D PT | F185: 1628 | G185: 17.08 | H185: 5.1176 | I185: =H185*G185 -> 87.408608 | J185: =I185*F185 -> 142301.21 | K185: =J185/_xlfn.XLOOKUP(A185,'Base de Dados'!D:D,'Base de Dados'!M:M) -> 0.20719142 | L185: =K185*_xlfn.XLOOKUP(A185,'Base de Dados'!D:D,'Base de Dados'!N:N) -> 5950.5313 | M185: =J185+L185 -> 148251.75 | N185: =M185/F185 -> 91.063725 | O185: =R185-0.1 -> 0.39270865 | P185: 299 | Q185: =(P185-N185)/P185 -> 0.69543905 | R185: 0.49270865 | S185: =Q185-R185 -> 0.20273039 | T185: 0 | U185: =(T185-P185)/T185 -> #DIV/0! | V185: 111001012 | W185: FRITADEIRA
A186: BEMOL 36 | B186: =_xlfn.XLOOKUP(A186,'Base de Dados'!D:D,'Base de Dados'!B:B) -> TIMBRO SWISS SA | C186: =_xlfn.XLOOKUP(PRECIFICAÇÃO[[#This Row],[INVOICE]],'Base de Dados'!D:D,'Base de Dados'!X:X) -> CONCLUÍDO | D186: 238700 | E186: SANDUICHEIRA BAUMON FS-8009C PT | F186: 3804 | G186: 5.69 | H186: 5.1176 | I186: =H186*G186 -> 29.119144 | J186: =I186*F186 -> 110769.22 | K186: =J186/_xlfn.XLOOKUP(A186,'Base de Dados'!D:D,'Base de Dados'!M:M) -> 0.16128065 | L186: =K186*_xlfn.XLOOKUP(A186,'Base de Dados'!D:D,'Base de Dados'!N:N) -> 4631.9755 | M186: =J186+L186 -> 115401.2 | N186: =M186/F186 -> 30.336803 | O186: =R186-0.1 -> 0.39291767 | P186: 77 | Q186: =(P186-N186)/P186 -> 0.60601554 | R186: 0.49291767 | S186: =Q186-R186 -> 0.11309788 | T186: 0 | U186: =(T186-P186)/T186 -> #DIV/0! | V186: 111001020 | W186: SANDUICHEIRA
A187: BEMOL 37 | B187: =_xlfn.XLOOKUP(A187,'Base de Dados'!D:D,'Base de Dados'!B:B) -> TIMBRO SWISS SA | C187: =_xlfn.XLOOKUP(PRECIFICAÇÃO[[#This Row],[INVOICE]],'Base de Dados'!D:D,'Base de Dados'!X:X) -> CONCLUÍDO | D187: 358232 | E187: FORNO ELÉT BAUMON 48L BANCADA JK48A PT | F187: 1282 | G187: 30.83 | H187: 5.1655 | I187: =H187*G187 -> 159.25236 | J187: =I187*F187 -> 204161.53 | K187: =J187/_xlfn.XLOOKUP(A187,'Base de Dados'!D:D,'Base de Dados'!M:M) -> 1 | L187: =K187*_xlfn.XLOOKUP(A187,'Base de Dados'!D:D,'Base de Dados'!N:N) -> 20723.99 | M187: =J187+L187 -> 224885.52 | N187: =M187/F187 -> 175.41772 | O187: =R187-0.1 -> 0.38095639 | P187: =ROUND(N187/O187,0) -> 460 | Q187: =(P187-N187)/P187 -> 0.61865712 | R187: 0.48095639 | S187: =Q187-R187 -> 0.13770074 | T187: =P187+10 -> 470 | U187: =(T187-P187)/T187 -> 0.021276596 | V187: 117001006 | W187: FORNO ELÉTRICO
A188: BEMOL 38 | B188: =_xlfn.XLOOKUP(A188,'Base de Dados'!D:D,'Base de Dados'!B:B) -> TIMBRO SWISS SA | C188: =_xlfn.XLOOKUP(PRECIFICAÇÃO[[#This Row],[INVOICE]],'Base de Dados'!D:D,'Base de Dados'!X:X) -> EM TRÂNSITO | D188: 373481 | E188: JG 3P CAMA SOLTEIRO BAUMON PREMIUM AZ | F188: 300 | G188: 8.25 | H188: 5.1176 | I188: =H188*G188 -> 42.2202 | J188: =I188*F188 -> 12666.06 | K188: =J188/_xlfn.XLOOKUP(A188,'Base de Dados'!D:D,'Base de Dados'!M:M) -> #DIV/0! | L188: =K188*_xlfn.XLOOKUP(A188,'Base de Dados'!D:D,'Base de Dados'!N:N) -> #DIV/0! | M188: =J188+L188 -> #DIV/0! | N188: =M188/F188 -> #DIV/0! | O188: =R188-0.1 -> 0.42743575 | P188: =ROUND(N188/O188,0) -> #DIV/0! | Q188: =(P188-N188)/P188 -> #DIV/0! | R188: 0.52743575 | S188: =Q188-R188 -> #DIV/0! | T188: =P188+10 -> #DIV/0! | U188: =(T188-P188)/T188 -> #DIV/0! | V188: 107001003 | W188: LENÇOL
A189: BEMOL 38 | B189: =_xlfn.XLOOKUP(A189,'Base de Dados'!D:D,'Base de Dados'!B:B) -> TIMBRO SWISS SA | C189: =_xlfn.XLOOKUP(PRECIFICAÇÃO[[#This Row],[INVOICE]],'Base de Dados'!D:D,'Base de Dados'!X:X) -> EM TRÂNSITO | D189: 373482 | E189: JG 3P CAMA SOLTEIRO BAUMON PREMIUM BG | F189: 300 | G189: 8.25 | H189: 5.1176 | I189: =H189*G189 -> 42.2202 | J189: =I189*F189 -> 12666.06 | K189: =J189/_xlfn.XLOOKUP(A189,'Base de Dados'!D:D,'Base de Dados'!M:M) -> #DIV/0! | M189: =J189+L189 -> 12666.06 | N189: =M189/F189 -> 42.2202 | O189: =R189-0.1 -> 0.42743575 | P189: =ROUND(N189/O189,0) -> 99 | Q189: =(P189-N189)/P189 -> 0.57353333 | R189: 0.52743575 | S189: =Q189-R189 -> 0.046097587 | U189: =(T189-P189)/T189 -> #DIV/0! | V189: 107001003 | W189: LENÇOL
A190: BEMOL 38 | B190: =_xlfn.XLOOKUP(A190,'Base de Dados'!D:D,'Base de Dados'!B:B) -> TIMBRO SWISS SA | C190: =_xlfn.XLOOKUP(PRECIFICAÇÃO[[#This Row],[INVOICE]],'Base de Dados'!D:D,'Base de Dados'!X:X) -> EM TRÂNSITO | D190: 387143 | E190: JG 3P CAMA SOLTEIRO BAUMON T-180 RO | F190: 300 | G190: 8.25 | H190: 5.1176 | I190: =H190*G190 -> 42.2202 | J190: =I190*F190 -> 12666.06 | K190: =J190/_xlfn.XLOOKUP(A190,'Base de Dados'!D:D,'Base de Dados'!M:M) -> #DIV/0! | L190: =K190*_xlfn.XLOOKUP(A190,'Base de Dados'!D:D,'Base de Dados'!N:N) -> #DIV/0! | M190: =J190+L190 -> #DIV/0! | N190: =M190/F190 -> #DIV/0! | O190: =R190-0.1 -> 0.42743575 | P190: =ROUND(N190/O190,0) -> #DIV/0! | Q190: =(P190-N190)/P190 -> #DIV/0! | R190: 0.52743575 | S190: =Q190-R190 -> #DIV/0! | U190: =(T190-P190)/T190 -> #DIV/0! | V190: 107001003 | W190: LENÇOL
A191: BEMOL 38 | B191: =_xlfn.XLOOKUP(A191,'Base de Dados'!D:D,'Base de Dados'!B:B) -> TIMBRO SWISS SA | C191: =_xlfn.XLOOKUP(PRECIFICAÇÃO[[#This Row],[INVOICE]],'Base de Dados'!D:D,'Base de Dados'!X:X) -> EM TRÂNSITO | D191: 373484 | E191: JG 4P CAMA CASAL BAUMON PREMIUM AZ | F191: 372 | G191: 14.26 | H191: 5.1176 | I191: =H191*G191 -> 72.976976 | J191: =I191*F191 -> 27147.435 | K191: =J191/_xlfn.XLOOKUP(A191,'Base de Dados'!D:D,'Base de Dados'!M:M) -> #DIV/0! | L191: =K191*_xlfn.XLOOKUP(A191,'Base de Dados'!D:D,'Base de Dados'!N:N) -> #DIV/0! | M191: =J191+L191 -> #DIV/0! | N191: =M191/F191 -> #DIV/0! | O191: =R191-0.1 -> 0.42743575 | P191: =ROUND(N191/O191,0) -> #DIV/0! | Q191: =(P191-N191)/P191 -> #DIV/0! | R191: 0.52743575 | S191: =Q191-R191 -> #DIV/0! | U191: =(T191-P191)/T191 -> #DIV/0! | V191: 107001003 | W191: LENÇOL
A192: BEMOL 38 | B192: =_xlfn.XLOOKUP(A192,'Base de Dados'!D:D,'Base de Dados'!B:B) -> TIMBRO SWISS SA | C192: =_xlfn.XLOOKUP(PRECIFICAÇÃO[[#This Row],[INVOICE]],'Base de Dados'!D:D,'Base de Dados'!X:X) -> EM TRÂNSITO | D192: 373485 | E192: JG 4P CAMA CASAL BAUMON PREMIUM BG | F192: 372 | G192: 14.26 | H192: 5.1176 | I192: =H192*G192 -> 72.976976 | J192: =I192*F192 -> 27147.435 | K192: =J192/_xlfn.XLOOKUP(A192,'Base de Dados'!D:D,'Base de Dados'!M:M) -> #DIV/0! | L192: =K192*_xlfn.XLOOKUP(A192,'Base de Dados'!D:D,'Base de Dados'!N:N) -> #DIV/0! | M192: =J192+L192 -> #DIV/0! | N192: =M192/F192 -> #DIV/0! | O192: =R192-0.1 -> 0.42743575 | P192: =ROUND(N192/O192,0) -> #DIV/0! | Q192: =(P192-N192)/P192 -> #DIV/0! | R192: 0.52743575 | S192: =Q192-R192 -> #DIV/0! | U192: =(T192-P192)/T192 -> #DIV/0! | V192: 107001003 | W192: LENÇOL
A193: BEMOL 38 | B193: =_xlfn.XLOOKUP(A193,'Base de Dados'!D:D,'Base de Dados'!B:B) -> TIMBRO SWISS SA | C193: =_xlfn.XLOOKUP(PRECIFICAÇÃO[[#This Row],[INVOICE]],'Base de Dados'!D:D,'Base de Dados'!X:X) -> EM TRÂNSITO | D193: 373486 | E193: JG 4P CAMA CASAL BAUMON PREMIUM VD | F193: 372 | G193: 14.26 | H193: 5.1176 | I193: =H193*G193 -> 72.976976 | J193: =I193*F193 -> 27147.435 | K193: =J193/_xlfn.XLOOKUP(A193,'Base de Dados'!D:D,'Base de Dados'!M:M) -> #DIV/0! | L193: =K193*_xlfn.XLOOKUP(A193,'Base de Dados'!D:D,'Base de Dados'!N:N) -> #DIV/0! | M193: =J193+L193 -> #DIV/0! | N193: =M193/F193 -> #DIV/0! | O193: =R193-0.1 -> 0.42743575 | P193: =ROUND(N193/O193,0) -> #DIV/0! | Q193: =(P193-N193)/P193 -> #DIV/0! | R193: 0.52743575 | S193: =Q193-R193 -> #DIV/0! | U193: =(T193-P193)/T193 -> #DIV/0! | V193: 107001003 | W193: LENÇOL
A194: BEMOL 38 | B194: =_xlfn.XLOOKUP(A194,'Base de Dados'!D:D,'Base de Dados'!B:B) -> TIMBRO SWISS SA | C194: =_xlfn.XLOOKUP(PRECIFICAÇÃO[[#This Row],[INVOICE]],'Base de Dados'!D:D,'Base de Dados'!X:X) -> EM TRÂNSITO | D194: 387144 | E194: JG 4P CAMA CASAL BAUMON T200 RENDA BR | F194: 372 | G194: 15.24 | H194: 5.1176 | I194: =H194*G194 -> 77.992224 | J194: =I194*F194 -> 29013.107 | K194: =J194/_xlfn.XLOOKUP(A194,'Base de Dados'!D:D,'Base de Dados'!M:M) -> #DIV/0! | L194: =K194*_xlfn.XLOOKUP(A194,'Base de Dados'!D:D,'Base de Dados'!N:N) -> #DIV/0! | M194: =J194+L194 -> #DIV/0! | N194: =M194/F194 -> #DIV/0! | O194: =R194-0.1 -> 0.42743575 | P194: =ROUND(N194/O194,0) -> #DIV/0! | Q194: =(P194-N194)/P194 -> #DIV/0! | R194: 0.52743575 | S194: =Q194-R194 -> #DIV/0! | U194: =(T194-P194)/T194 -> #DIV/0! | V194: 107001003 | W194: LENÇOL
A195: BEMOL 38 | B195: =_xlfn.XLOOKUP(A195,'Base de Dados'!D:D,'Base de Dados'!B:B) -> TIMBRO SWISS SA | C195: =_xlfn.XLOOKUP(PRECIFICAÇÃO[[#This Row],[INVOICE]],'Base de Dados'!D:D,'Base de Dados'!X:X) -> EM TRÂNSITO | D195: 373487 | E195: JG 4P CAMA QUEEN BAUMON PREMIUM AZ | F195: 380 | G195: 15.51 | H195: 5.1176 | I195: =H195*G195 -> 79.373976 | J195: =I195*F195 -> 30162.111 | K195: =J195/_xlfn.XLOOKUP(A195,'Base de Dados'!D:D,'Base de Dados'!M:M) -> #DIV/0! | L195: =K195*_xlfn.XLOOKUP(A195,'Base de Dados'!D:D,'Base de Dados'!N:N) -> #DIV/0! | M195: =J195+L195 -> #DIV/0! | N195: =M195/F195 -> #DIV/0! | O195: =R195-0.1 -> 0.42743575 | P195: =ROUND(N195/O195,0) -> #DIV/0! | Q195: =(P195-N195)/P195 -> #DIV/0! | R195: 0.52743575 | S195: =Q195-R195 -> #DIV/0! | U195: =(T195-P195)/T195 -> #DIV/0! | V195: 107001003 | W195: LENÇOL
A196: BEMOL 38 | B196: =_xlfn.XLOOKUP(A196,'Base de Dados'!D:D,'Base de Dados'!B:B) -> TIMBRO SWISS SA | C196: =_xlfn.XLOOKUP(PRECIFICAÇÃO[[#This Row],[INVOICE]],'Base de Dados'!D:D,'Base de Dados'!X:X) -> EM TRÂNSITO | D196: 373488 | E196: JG 4P CAMA QUEEN BAUMON PREMIUM BG | F196: 380 | G196: 15.51 | H196: 5.1176 | I196: =H196*G196 -> 79.373976 | J196: =I196*F196 -> 30162.111 | K196: =J196/_xlfn.XLOOKUP(A196,'Base de Dados'!D:D,'Base de Dados'!M:M) -> #DIV/0! | L196: =K196*_xlfn.XLOOKUP(A196,'Base de Dados'!D:D,'Base de Dados'!N:N) -> #DIV/0! | M196: =J196+L196 -> #DIV/0! | N196: =M196/F196 -> #DIV/0! | O196: =R196-0.1 -> 0.42743575 | P196: =ROUND(N196/O196,0) -> #DIV/0! | Q196: =(P196-N196)/P196 -> #DIV/0! | R196: 0.52743575 | S196: =Q196-R196 -> #DIV/0! | U196: =(T196-P196)/T196 -> #DIV/0! | V196: 107001003 | W196: LENÇOL
A197: BEMOL 38 | B197: =_xlfn.XLOOKUP(A197,'Base de Dados'!D:D,'Base de Dados'!B:B) -> TIMBRO SWISS SA | C197: =_xlfn.XLOOKUP(PRECIFICAÇÃO[[#This Row],[INVOICE]],'Base de Dados'!D:D,'Base de Dados'!X:X) -> EM TRÂNSITO | D197: 373489 | E197: JG 4P CAMA QUEEN BAUMON PREMIUM VD | F197: 380 | G197: 15.51 | H197: 5.1176 | I197: =H197*G197 -> 79.373976 | J197: =I197*F197 -> 30162.111 | K197: =J197/_xlfn.XLOOKUP(A197,'Base de Dados'!D:D,'Base de Dados'!M:M) -> #DIV/0! | L197: =K197*_xlfn.XLOOKUP(A197,'Base de Dados'!D:D,'Base de Dados'!N:N) -> #DIV/0! | M197: =J197+L197 -> #DIV/0! | N197: =M197/F197 -> #DIV/0! | O197: =R197-0.1 -> 0.42743575 | P197: =ROUND(N197/O197,0) -> #DIV/0! | Q197: =(P197-N197)/P197 -> #DIV/0! | R197: 0.52743575 | S197: =Q197-R197 -> #DIV/0! | U197: =(T197-P197)/T197 -> #DIV/0! | V197: 107001003 | W197: LENÇOL
A198: BEMOL 38 | B198: =_xlfn.XLOOKUP(A198,'Base de Dados'!D:D,'Base de Dados'!B:B) -> TIMBRO SWISS SA | C198: =_xlfn.XLOOKUP(PRECIFICAÇÃO[[#This Row],[INVOICE]],'Base de Dados'!D:D,'Base de Dados'!X:X) -> EM TRÂNSITO | D198: 387145 | E198: JG 4P CAMA QUEEN BAUMON T200 RENDA BR | F198: 380 | G198: 15.84 | H198: 5.1176 | I198: =H198*G198 -> 81.062784 | J198: =I198*F198 -> 30803.858 | K198: =J198/_xlfn.XLOOKUP(A198,'Base de Dados'!D:D,'Base de Dados'!M:M) -> #DIV/0! | L198: =K198*_xlfn.XLOOKUP(A198,'Base de Dados'!D:D,'Base de Dados'!N:N) -> #DIV/0! | M198: =J198+L198 -> #DIV/0! | N198: =M198/F198 -> #DIV/0! | O198: =R198-0.1 -> 0.42743575 | P198: =ROUND(N198/O198,0) -> #DIV/0! | Q198: =(P198-N198)/P198 -> #DIV/0! | R198: 0.52743575 | S198: =Q198-R198 -> #DIV/0! | U198: =(T198-P198)/T198 -> #DIV/0! | V198: 107001003 | W198: LENÇOL
A199: BEMOL 38 | B199: =_xlfn.XLOOKUP(A199,'Base de Dados'!D:D,'Base de Dados'!B:B) -> TIMBRO SWISS SA | C199: =_xlfn.XLOOKUP(PRECIFICAÇÃO[[#This Row],[INVOICE]],'Base de Dados'!D:D,'Base de Dados'!X:X) -> EM TRÂNSITO | D199: 373490 | E199: JG 4P CAMA KING BAUMON PREMIUM AZ | F199: 352 | G199: 18.23 | H199: 5.1176 | I199: =H199*G199 -> 93.293848 | J199: =I199*F199 -> 32839.434 | K199: =J199/_xlfn.XLOOKUP(A199,'Base de Dados'!D:D,'Base de Dados'!M:M) -> #DIV/0! | L199: =K199*_xlfn.XLOOKUP(A199,'Base de Dados'!D:D,'Base de Dados'!N:N) -> #DIV/0! | M199: =J199+L199 -> #DIV/0! | N199: =M199/F199 -> #DIV/0! | O199: =R199-0.1 -> 0.42743575 | P199: =ROUND(N199/O199,0) -> #DIV/0! | Q199: =(P199-N199)/P199 -> #DIV/0! | R199: 0.52743575 | S199: =Q199-R199 -> #DIV/0! | U199: =(T199-P199)/T199 -> #DIV/0! | V199: 107001003 | W199: LENÇOL
A200: BEMOL 38 | B200: =_xlfn.XLOOKUP(A200,'Base de Dados'!D:D,'Base de Dados'!B:B) -> TIMBRO SWISS SA | C200: =_xlfn.XLOOKUP(PRECIFICAÇÃO[[#This Row],[INVOICE]],'Base de Dados'!D:D,'Base de Dados'!X:X) -> EM TRÂNSITO | D200: 373491 | E200: JG 4P CAMA KING BAUMON PREMIUM BG | F200: 352 | G200: 18.23 | H200: 5.1176 | I200: =H200*G200 -> 93.293848 | J200: =I200*F200 -> 32839.434 | K200: =J200/_xlfn.XLOOKUP(A200,'Base de Dados'!D:D,'Base de Dados'!M:M) -> #DIV/0! | L200: =K200*_xlfn.XLOOKUP(A200,'Base de Dados'!D:D,'Base de Dados'!N:N) -> #DIV/0! | M200: =J200+L200 -> #DIV/0! | N200: =M200/F200 -> #DIV/0! | O200: =R200-0.1 -> 0.42743575 | P200: =ROUND(N200/O200,0) -> #DIV/0! | Q200: =(P200-N200)/P200 -> #DIV/0! | R200: 0.52743575 | S200: =Q200-R200 -> #DIV/0! | U200: =(T200-P200)/T200 -> #DIV/0! | V200: 107001003 | W200: LENÇOL
A201: BEMOL 38 | B201: =_xlfn.XLOOKUP(A201,'Base de Dados'!D:D,'Base de Dados'!B:B) -> TIMBRO SWISS SA | C201: =_xlfn.XLOOKUP(PRECIFICAÇÃO[[#This Row],[INVOICE]],'Base de Dados'!D:D,'Base de Dados'!X:X) -> EM TRÂNSITO | D201: 373492 | E201: JG 4P CAMA KING BAUMON PREMIUM VD | F201: 352 | G201: 18.23 | H201: 5.1176 | I201: =H201*G201 -> 93.293848 | J201: =I201*F201 -> 32839.434 | K201: =J201/_xlfn.XLOOKUP(A201,'Base de Dados'!D:D,'Base de Dados'!M:M) -> #DIV/0! | L201: =K201*_xlfn.XLOOKUP(A201,'Base de Dados'!D:D,'Base de Dados'!N:N) -> #DIV/0! | M201: =J201+L201 -> #DIV/0! | N201: =M201/F201 -> #DIV/0! | O201: =R201-0.1 -> 0.42743575 | P201: =ROUND(N201/O201,0) -> #DIV/0! | Q201: =(P201-N201)/P201 -> #DIV/0! | R201: 0.52743575 | S201: =Q201-R201 -> #DIV/0! | U201: =(T201-P201)/T201 -> #DIV/0! | V201: 107001003 | W201: LENÇOL
... A243: BEMOL 71 | B243: =_xlfn.XLOOKUP(A243,'Base de Dados'!D:D,'Base de Dados'!B:B) -> TIMBRO SWISS SA | C243: =_xlfn.XLOOKUP(PRECIFICAÇÃO[[#This Row],[INVOICE]],'Base de Dados'!D:D,'Base de Dados'!X:X) -> EM PRODUÇÃO | D243: 272955 | E243: VAPORIZADOR PORTÁTIL BAUMON QH-08BK BR | F243: 1600 | G243: 15.04 | H243: 5.1176 | I243: =H243*G243 -> 76.968704 | J243: =I243*F243 -> 123149.93 | K243: =J243/_xlfn.XLOOKUP(A243,'Base de Dados'!D:D,'Base de Dados'!M:M) -> #DIV/0! | L243: =K243*_xlfn.XLOOKUP(A243,'Base de Dados'!D:D,'Base de Dados'!N:N) -> #DIV/0! | M243: =J243+L243 -> #DIV/0! | N243: =M243/F243 -> #DIV/0! | O243: =R243-0.1 -> 0.41940406 | P243: =ROUND(N243/O243,0) -> #DIV/0! | Q243: =(P243-N243)/P243 -> #DIV/0! | R243: 0.51940406 | S243: =Q243-R243 -> #DIV/0! | U243: =(T243-P243)/T243 -> #DIV/0! | V243: 111003006 | W243: VAPORIZADOR
A244: BEMOL 35 | B244: =_xlfn.XLOOKUP(A244,'Base de Dados'!D:D,'Base de Dados'!B:B) -> TIMBRO SWISS SA | C244: =_xlfn.XLOOKUP(PRECIFICAÇÃO[[#This Row],[INVOICE]],'Base de Dados'!D:D,'Base de Dados'!X:X) -> CONCLUÍDO | D244: 267869 | E244: POTE BAUMON HERMÉT 400ML RET C/T R145 | F244: 3132 | G244: =740/1000 -> 0.74 | H244: 4.9587 | I244: =H244*G244 -> 3.669438 | J244: =I244*F244 -> 11492.68 | K244: =J244/_xlfn.XLOOKUP(A244,'Base de Dados'!D:D,'Base de Dados'!M:M) -> 0.021027252 | L244: =K244*_xlfn.XLOOKUP(A244,'Base de Dados'!D:D,'Base de Dados'!N:N) -> 1274.6367 | M244: =J244+L244 -> 12767.316 | N244: =M244/F244 -> 4.0764101 | O244: =R244-0.1 -> 0.4092054 | P244: =ROUND(N244/O244,0) -> 10 | Q244: =(P244-N244)/P244 -> 0.59235899 | R244: 0.5092054 | S244: =Q244-R244 -> 0.083153589 | T244: =P244+10 -> 20 | U244: =(T244-P244)/T244 -> 0.5 | V244: 127001014 | W244: POTES
A245: BEMOL 35 | B245: =_xlfn.XLOOKUP(A245,'Base de Dados'!D:D,'Base de Dados'!B:B) -> TIMBRO SWISS SA | C245: =_xlfn.XLOOKUP(PRECIFICAÇÃO[[#This Row],[INVOICE]],'Base de Dados'!D:D,'Base de Dados'!X:X) -> CONCLUÍDO | D245: 358232 | E245: FORNO ELÉT BAUMON 48L BANCADA JK48A PT | F245: 3500 | G245: 30.83 | H245: 4.9587 | I245: =H245*G245 -> 152.87672 | J245: =I245*F245 -> 535068.52 | K245: =J245/_xlfn.XLOOKUP(A245,'Base de Dados'!D:D,'Base de Dados'!M:M) -> 0.97897275 | L245: =K245*_xlfn.XLOOKUP(A245,'Base de Dados'!D:D,'Base de Dados'!N:N) -> 59343.684 | M245: =J245+L245 -> 594412.21 | N245: =M245/F245 -> 169.83206 | O245: =R245-0.1 -> 0.38095639 | P245: =ROUND(N245/O245,0) -> 446 | Q245: =(P245-N245)/P245 -> 0.61921063 | R245: 0.48095639 | S245: =Q245-R245 -> 0.13825424 | T245: =P245+10 -> 456 | U245: =(T245-P245)/T245 -> 0.021929825 | V245: 117001006 | W245: FORNO ELÉTRICO
A246: BEMOL 45 | B246: =_xlfn.XLOOKUP(A246,'Base de Dados'!D:D,'Base de Dados'!B:B) -> TIMBRO SWISS SA | C246: =_xlfn.XLOOKUP(PRECIFICAÇÃO[[#This Row],[INVOICE]],'Base de Dados'!D:D,'Base de Dados'!X:X) -> CONCLUÍDO | D246: 272749 | E246: LIQUIDIFICADOR BAUMON 1,5L KP-1805 PT | F246: 1000 | G246: 16.95 | H246: 5.1176 | I246: =H246*G246 -> 86.74332 | J246: =I246*F246 -> 86743.32 | K246: =J246/_xlfn.XLOOKUP(A246,'Base de Dados'!D:D,'Base de Dados'!M:M) -> #DIV/0! | L246: =K246*_xlfn.XLOOKUP(A246,'Base de Dados'!D:D,'Base de Dados'!N:N) -> #DIV/0! | M246: =J246+L246 -> #DIV/0! | N246: =M246/F246 -> #DIV/0! | O246: =R246-0.1 -> 0.40979214 | P246: =ROUND(N246/O246,0) -> #DIV/0! | Q246: =(P246-N246)/P246 -> #DIV/0! | R246: 0.50979214 | S246: =Q246-R246 -> #DIV/0! | U246: =(T246-P246)/T246 -> #DIV/0! | V246: 111001017 | W246: LIQUIDIFICADOR ACIMA DE 3 VELOCIDADES
A247: BEMOL 45 | B247: =_xlfn.XLOOKUP(A247,'Base de Dados'!D:D,'Base de Dados'!B:B) -> TIMBRO SWISS SA | C247: =_xlfn.XLOOKUP(PRECIFICAÇÃO[[#This Row],[INVOICE]],'Base de Dados'!D:D,'Base de Dados'!X:X) -> CONCLUÍDO | D247: 358233 | E247: MÁQUINA DE GELO BAUMON HC-2 PT | F247: 800 | G247: 330.5 | H247: 5.1176 | I247: =H247*G247 -> 1691.3668 | J247: =I247*F247 -> 1353093.4 | K247: =J247/_xlfn.XLOOKUP(A247,'Base de Dados'!D:D,'Base de Dados'!M:M) -> #DIV/0! | L247: =K247*_xlfn.XLOOKUP(A247,'Base de Dados'!D:D,'Base de Dados'!N:N) -> #DIV/0! | M247: =J247+L247 -> #DIV/0! | N247: =M247/F247 -> #DIV/0! | O247: =R247-0.1 -> 0.39018383 | P247: =ROUND(N247/O247,0) -> #DIV/0! | Q247: =(P247-N247)/P247 -> #DIV/0! | R247: 0.49018383 | S247: =Q247-R247 -> #DIV/0! | U247: =(T247-P247)/T247 -> #DIV/0! | V247: 111001019 | W247: PROCESSADOR DE ALIMENTOS
A248: BEMOL 45 | B248: =_xlfn.XLOOKUP(A248,'Base de Dados'!D:D,'Base de Dados'!B:B) -> TIMBRO SWISS SA | C248: =_xlfn.XLOOKUP(PRECIFICAÇÃO[[#This Row],[INVOICE]],'Base de Dados'!D:D,'Base de Dados'!X:X) -> CONCLUÍDO | D248: 370453 | E248: SUP/ DE TV ARTICULADO BAUMON YN-927AT M | F248: 2004 | G248: 7.54 | H248: 5.1176 | I248: =H248*G248 -> 38.586704 | J248: =I248*F248 -> 77327.755 | K248: =J248/_xlfn.XLOOKUP(A248,'Base de Dados'!D:D,'Base de Dados'!M:M) -> #DIV/0! | L248: =K248*_xlfn.XLOOKUP(A248,'Base de Dados'!D:D,'Base de Dados'!N:N) -> #DIV/0! | M248: =J248+L248 -> #DIV/0! | N248: =M248/F248 -> #DIV/0! | O248: =R248-0.1 -> 0.37093718 | P248: =ROUND(N248/O248,0) -> #DIV/0! | Q248: =(P248-N248)/P248 -> #DIV/0! | R248: 0.47093718 | S248: =Q248-R248 -> #DIV/0! | U248: =(T248-P248)/T248 -> #DIV/0! | V248: 130001013 | W248: SUPORTES
A249: BEMOL 45 | B249: =_xlfn.XLOOKUP(A249,'Base de Dados'!D:D,'Base de Dados'!B:B) -> TIMBRO SWISS SA | C249: =_xlfn.XLOOKUP(PRECIFICAÇÃO[[#This Row],[INVOICE]],'Base de Dados'!D:D,'Base de Dados'!X:X) -> CONCLUÍDO | D249: 272955 | E249: VAPORIZADOR PORTÁTIL BAUMON QH-08BK BR | F249: 1520 | G249: 15.04 | H249: 5.1176 | I249: =H249*G249 -> 76.968704 | J249: =I249*F249 -> 116992.43 | K249: =J249/_xlfn.XLOOKUP(A249,'Base de Dados'!D:D,'Base de Dados'!M:M) -> #DIV/0! | L249: =K249*_xlfn.XLOOKUP(A249,'Base de Dados'!D:D,'Base de Dados'!N:N) -> #DIV/0! | M249: =J249+L249 -> #DIV/0! | N249: =M249/F249 -> #DIV/0! | O249: =R249-0.1 -> 0.41940406 | P249: =ROUND(N249/O249,0) -> #DIV/0! | Q249: =(P249-N249)/P249 -> #DIV/0! | R249: 0.51940406 | S249: =Q249-R249 -> #DIV/0! | U249: =(T249-P249)/T249 -> #DIV/0! | V249: 111003006 | W249: VAPORIZADOR
A250: BEMOL 52 | B250: =_xlfn.XLOOKUP(A250,'Base de Dados'!D:D,'Base de Dados'!B:B) -> TIMBRO SWISS SA | C250: =_xlfn.XLOOKUP(PRECIFICAÇÃO[[#This Row],[INVOICE]],'Base de Dados'!D:D,'Base de Dados'!X:X) -> EM PRODUÇÃO | D250: 354935 | E250: LIQUID BAUMON GSE019 PT | F250: 992 | G250: 1.78 | H250: 5.1176 | I250: =H250*G250 -> 9.109328 | J250: =I250*F250 -> 9036.4534 | K250: =J250/_xlfn.XLOOKUP(A250,'Base de Dados'!D:D,'Base de Dados'!M:M) -> #DIV/0! | L250: =K250*_xlfn.XLOOKUP(A250,'Base de Dados'!D:D,'Base de Dados'!N:N) -> #DIV/0! | M250: =J250+L250 -> #DIV/0! | N250: =M250/F250 -> #DIV/0! | O250: =R250-0.1 -> 0.43322996 | P250: =ROUND(N250/O250,0) -> #DIV/0! | Q250: =(P250-N250)/P250 -> #DIV/0! | R250: 0.53322996 | S250: =Q250-R250 -> #DIV/0! | U250: =(T250-P250)/T250 -> #DIV/0! | V250: 111001016 | W250: LIQUIDIFICADOR ATÉ 3 VELOCIDADES
A251: BEMOL 54 | B251: =_xlfn.XLOOKUP(A251,'Base de Dados'!D:D,'Base de Dados'!B:B) -> TIMBRO SWISS SA | C251: =_xlfn.XLOOKUP(PRECIFICAÇÃO[[#This Row],[INVOICE]],'Base de Dados'!D:D,'Base de Dados'!X:X) -> EM TRÂNSITO | D251: 238698 | E251: FRITAD BAUMON AIR FRYER 12L GSE021 PT | F251: 1112 | G251: 37.81 | H251: 5.1176 | I251: =H251*G251 -> 193.49646 | J251: =I251*F251 -> 215168.06 | K251: =J251/_xlfn.XLOOKUP(A251,'Base de Dados'!D:D,'Base de Dados'!M:M) -> #DIV/0! | L251: =K251*_xlfn.XLOOKUP(A251,'Base de Dados'!D:D,'Base de Dados'!N:N) -> #DIV/0! | M251: =J251+L251 -> #DIV/0! | N251: =M251/F251 -> #DIV/0! | O251: =R251-0.1 -> 0.39270865 | P251: =ROUND(N251/O251,0) -> #DIV/0! | Q251: =(P251-N251)/P251 -> #DIV/0! | R251: 0.49270865 | S251: =Q251-R251 -> #DIV/0! | U251: =(T251-P251)/T251 -> #DIV/0! | V251: 111001012 | W251: FRITADEIRA
A252: BEMOL 56 | B252: =_xlfn.XLOOKUP(A252,'Base de Dados'!D:D,'Base de Dados'!B:B) -> TIMBRO SWISS SA | C252: =_xlfn.XLOOKUP(PRECIFICAÇÃO[[#This Row],[INVOICE]],'Base de Dados'!D:D,'Base de Dados'!X:X) -> EM TRÂNSITO | D252: 238723 | E252: FERRO BAUMON VAPOR LM-2262 AZ | F252: 2400 | G252: 5.65 | H252: 5.1176 | I252: =H252*G252 -> 28.91444 | J252: =I252*F252 -> 69394.656 | K252: =J252/_xlfn.XLOOKUP(A252,'Base de Dados'!D:D,'Base de Dados'!M:M) -> #DIV/0! | L252: =K252*_xlfn.XLOOKUP(A252,'Base de Dados'!D:D,'Base de Dados'!N:N) -> #DIV/0! | M252: =J252+L252 -> #DIV/0! | N252: =M252/F252 -> #DIV/0! | O252: =R252-0.1 -> 0.41017662 | P252: =ROUND(N252/O252,0) -> #DIV/0! | Q252: =(P252-N252)/P252 -> #DIV/0! | R252: 0.51017662 | S252: =Q252-R252 -> #DIV/0! | U252: =(T252-P252)/T252 -> #DIV/0! | V252: 111003001 | W252: FERRO À VAPOR
A253: BEMOL 56 | B253: =_xlfn.XLOOKUP(A253,'Base de Dados'!D:D,'Base de Dados'!B:B) -> TIMBRO SWISS SA | C253: =_xlfn.XLOOKUP(PRECIFICAÇÃO[[#This Row],[INVOICE]],'Base de Dados'!D:D,'Base de Dados'!X:X) -> EM TRÂNSITO | D253: 272749 | E253: LIQUIDIFICADOR BAUMON 1,5L KP-1805 PT | F253: 1220 | G253: 16.95 | H253: 5.1176 | I253: =H253*G253 -> 86.74332 | J253: =I253*F253 -> 105826.85 | K253: =J253/_xlfn.XLOOKUP(A253,'Base de Dados'!D:D,'Base de Dados'!M:M) -> #DIV/0! | L253: =K253*_xlfn.XLOOKUP(A253,'Base de Dados'!D:D,'Base de Dados'!N:N) -> #DIV/0! | M253: =J253+L253 -> #DIV/0! | N253: =M253/F253 -> #DIV/0! | O253: =R253-0.1 -> 0.40979214 | P253: =ROUND(N253/O253,0) -> #DIV/0! | Q253: =(P253-N253)/P253 -> #DIV/0! | R253: 0.50979214 | S253: =Q253-R253 -> #DIV/0! | U253: =(T253-P253)/T253 -> #DIV/0! | V253: 111001017 | W253: LIQUIDIFICADOR ACIMA DE 3 VELOCIDADES
A254: BEMOL 56 | B254: =_xlfn.XLOOKUP(A254,'Base de Dados'!D:D,'Base de Dados'!B:B) -> TIMBRO SWISS SA | C254: =_xlfn.XLOOKUP(PRECIFICAÇÃO[[#This Row],[INVOICE]],'Base de Dados'!D:D,'Base de Dados'!X:X) -> EM TRÂNSITO | D254: 272955 | E254: VAPORIZADOR PORTÁTIL BAUMON QH-08BK BR | F254: 1600 | G254: 15.04 | H254: 5.1176 | I254: =H254*G254 -> 76.968704 | J254: =I254*F254 -> 123149.93 | K254: =J254/_xlfn.XLOOKUP(A254,'Base de Dados'!D:D,'Base de Dados'!M:M) -> #DIV/0! | L254: =K254*_xlfn.XLOOKUP(A254,'Base de Dados'!D:D,'Base de Dados'!N:N) -> #DIV/0! | M254: =J254+L254 -> #DIV/0! | N254: =M254/F254 -> #DIV/0! | O254: =R254-0.1 -> 0.41940406 | P254: =ROUND(N254/O254,0) -> #DIV/0! | Q254: =(P254-N254)/P254 -> #DIV/0! | R254: 0.51940406 | S254: =Q254-R254 -> #DIV/0! | U254: =(T254-P254)/T254 -> #DIV/0! | V254: 111003006 | W254: VAPORIZADOR
A255: BEMOL 56 | B255: =_xlfn.XLOOKUP(A255,'Base de Dados'!D:D,'Base de Dados'!B:B) -> TIMBRO SWISS SA | C255: =_xlfn.XLOOKUP(PRECIFICAÇÃO[[#This Row],[INVOICE]],'Base de Dados'!D:D,'Base de Dados'!X:X) -> EM TRÂNSITO | D255: 272957 | E255: PRANCHA BAUMON 127V 230C SD-510A AZ | F255: 2160 | G255: 6.08 | H255: 5.1176 | I255: =H255*G255 -> 31.115008 | J255: =I255*F255 -> 67208.417 | K255: =J255/_xlfn.XLOOKUP(A255,'Base de Dados'!D:D,'Base de Dados'!M:M) -> #DIV/0! | L255: =K255*_xlfn.XLOOKUP(A255,'Base de Dados'!D:D,'Base de Dados'!N:N) -> #DIV/0! | M255: =J255+L255 -> #DIV/0! | N255: =M255/F255 -> #DIV/0! | O255: =R255-0.1 -> 0.40088862 | P255: =ROUND(N255/O255,0) -> #DIV/0! | Q255: =(P255-N255)/P255 -> #DIV/0! | R255: 0.50088862 | S255: =Q255-R255 -> #DIV/0! | U255: =(T255-P255)/T255 -> #DIV/0! | V255: 110001004 | W255: CHAPA
A256: BEMOL 56 | B256: =_xlfn.XLOOKUP(A256,'Base de Dados'!D:D,'Base de Dados'!B:B) -> TIMBRO SWISS SA | C256: =_xlfn.XLOOKUP(PRECIFICAÇÃO[[#This Row],[INVOICE]],'Base de Dados'!D:D,'Base de Dados'!X:X) -> EM TRÂNSITO | D256: 370451 | E256: SUPORTE DE TV BAUMON BLISTER LCD800 P | F256: 5000 | G256: 1.38 | H256: 5.1176 | I256: =H256*G256 -> 7.062288 | J256: =I256*F256 -> 35311.44 | K256: =J256/_xlfn.XLOOKUP(A256,'Base de Dados'!D:D,'Base de Dados'!M:M) -> #DIV/0! | L256: =K256*_xlfn.XLOOKUP(A256,'Base de Dados'!D:D,'Base de Dados'!N:N) -> #DIV/0! | M256: =J256+L256 -> #DIV/0! | N256: =M256/F256 -> #DIV/0! | O256: =R256-0.1 -> 0.37093718 | P256: =ROUND(N256/O256,0) -> #DIV/0! | Q256: =(P256-N256)/P256 -> #DIV/0! | R256: 0.47093718 | S256: =Q256-R256 -> #DIV/0! | U256: =(T256-P256)/T256 -> #DIV/0! | V256: 130001013 | W256: SUPORTES
A257: BEMOL 56 | B257: =_xlfn.XLOOKUP(A257,'Base de Dados'!D:D,'Base de Dados'!B:B) -> TIMBRO SWISS SA | C257: =_xlfn.XLOOKUP(PRECIFICAÇÃO[[#This Row],[INVOICE]],'Base de Dados'!D:D,'Base de Dados'!X:X) -> EM TRÂNSITO | D257: 370452 | E257: SUPORTE DE TV BAUMON YN-109MF G | F257: 2200 | G257: 5.15 | H257: 5.1176 | I257: =H257*G257 -> 26.35564 | J257: =I257*F257 -> 57982.408 | K257: =J257/_xlfn.XLOOKUP(A257,'Base de Dados'!D:D,'Base de Dados'!M:M) -> #DIV/0! | L257: =K257*_xlfn.XLOOKUP(A257,'Base de Dados'!D:D,'Base de Dados'!N:N) -> #DIV/0! | M257: =J257+L257 -> #DIV/0! | N257: =M257/F257 -> #DIV/0! | O257: =R257-0.1 -> 0.37093718 | P257: =ROUND(N257/O257,0) -> #DIV/0! | Q257: =(P257-N257)/P257 -> #DIV/0! | R257: 0.47093718 | S257: =Q257-R257 -> #DIV/0! | U257: =(T257-P257)/T257 -> #DIV/0! | V257: 130001013 | W257: SUPORTES
... A315: BEMOL 68 | B315: =_xlfn.XLOOKUP(A315,'Base de Dados'!D:D,'Base de Dados'!B:B) -> TIMBRO SWISS SA | C315: =_xlfn.XLOOKUP(PRECIFICAÇÃO[[#This Row],[INVOICE]],'Base de Dados'!D:D,'Base de Dados'!X:X) -> EM TRÂNSITO | D315: 358229 | E315: FRIGOBAR BAUMON 46L HC46 BR | F315: 1160 | G315: 51.46 | H315: 5.1176 | I315: =H315*G315 -> 263.3517 | J315: =I315*F315 -> 305487.97 | K315: =J315/_xlfn.XLOOKUP(A315,'Base de Dados'!D:D,'Base de Dados'!M:M) -> #DIV/0! | L315: =K315*_xlfn.XLOOKUP(A315,'Base de Dados'!D:D,'Base de Dados'!N:N) -> #DIV/0! | M315: =J315+L315 -> #DIV/0! | N315: =M315/F315 -> #DIV/0! | O315: =R315-0.1 -> 0.35806811 | P315: =ROUND(N315/O315,0) -> #DIV/0! | Q315: =(P315-N315)/P315 -> #DIV/0! | R315: 0.45806811 | S315: =Q315-R315 -> #DIV/0! | U315: =(T315-P315)/T315 -> #DIV/0! | V315: 117006005 | W315: FRIGOBAR
A316: BEMOL 69 | B316: =_xlfn.XLOOKUP(A316,'Base de Dados'!D:D,'Base de Dados'!B:B) -> TIMBRO SWISS SA | C316: =_xlfn.XLOOKUP(PRECIFICAÇÃO[[#This Row],[INVOICE]],'Base de Dados'!D:D,'Base de Dados'!X:X) -> EM PRODUÇÃO | D316: 272956 | E316: PRANCHA BAUMON 127V 200C SD-515 AZ | F316: 3000 | G316: 4.69 | H316: 5.1176 | I316: =H316*G316 -> 24.001544 | J316: =I316*F316 -> 72004.632 | K316: =J316/_xlfn.XLOOKUP(A316,'Base de Dados'!D:D,'Base de Dados'!M:M) -> #DIV/0! | L316: =K316*_xlfn.XLOOKUP(A316,'Base de Dados'!D:D,'Base de Dados'!N:N) -> #DIV/0! | M316: =J316+L316 -> #DIV/0! | N316: =M316/F316 -> #DIV/0! | O316: =R316-0.1 -> 0.40088862 | P316: =ROUND(N316/O316,0) -> #DIV/0! | Q316: =(P316-N316)/P316 -> #DIV/0! | R316: 0.50088862 | S316: =Q316-R316 -> #DIV/0! | U316: =(T316-P316)/T316 -> #DIV/0! | V316: 110001004 | W316: =_xlfn.XLOOKUP(PRECIFICAÇÃO[[#This Row],[GM9]],Markup!A:A,Markup!B:B) -> CHAPA
A317: BEMOL 69 | B317: =_xlfn.XLOOKUP(A317,'Base de Dados'!D:D,'Base de Dados'!B:B) -> TIMBRO SWISS SA | C317: =_xlfn.XLOOKUP(PRECIFICAÇÃO[[#This Row],[INVOICE]],'Base de Dados'!D:D,'Base de Dados'!X:X) -> EM PRODUÇÃO | D317: 272958 | E317: SECADOR BAUMON 2000W 127V SD-808 AZ | F317: 3636 | G317: 6.46 | H317: 5.1176 | I317: =H317*G317 -> 33.059696 | J317: =I317*F317 -> 120205.05 | K317: =J317/_xlfn.XLOOKUP(A317,'Base de Dados'!D:D,'Base de Dados'!M:M) -> #DIV/0! | L317: =K317*_xlfn.XLOOKUP(A317,'Base de Dados'!D:D,'Base de Dados'!N:N) -> #DIV/0! | M317: =J317+L317 -> #DIV/0! | N317: =M317/F317 -> #DIV/0! | O317: =R317-0.1 -> 0.4095633 | P317: =ROUND(N317/O317,0) -> #DIV/0! | Q317: =(P317-N317)/P317 -> #DIV/0! | R317: 0.5095633 | S317: =Q317-R317 -> #DIV/0! | U317: =(T317-P317)/T317 -> #DIV/0! | V317: 110001009 | W317: =_xlfn.XLOOKUP(PRECIFICAÇÃO[[#This Row],[GM9]],Markup!A:A,Markup!B:B) -> SECADOR
A318: BEMOL 69 | B318: =_xlfn.XLOOKUP(A318,'Base de Dados'!D:D,'Base de Dados'!B:B) -> TIMBRO SWISS SA | C318: =_xlfn.XLOOKUP(PRECIFICAÇÃO[[#This Row],[INVOICE]],'Base de Dados'!D:D,'Base de Dados'!X:X) -> EM PRODUÇÃO | D318: 358233 | E318: MÁQUINA DE GELO BAUMON HC-2 PT | F318: 1400 | G318: 43.66 | H318: 5.1176 | I318: =H318*G318 -> 223.43442 | J318: =I318*F318 -> 312808.18 | K318: =J318/_xlfn.XLOOKUP(A318,'Base de Dados'!D:D,'Base de Dados'!M:M) -> #DIV/0! | L318: =K318*_xlfn.XLOOKUP(A318,'Base de Dados'!D:D,'Base de Dados'!N:N) -> #DIV/0! | M318: =J318+L318 -> #DIV/0! | N318: =M318/F318 -> #DIV/0! | O318: =R318-0.1 -> 0.39018383 | P318: =ROUND(N318/O318,0) -> #DIV/0! | Q318: =(P318-N318)/P318 -> #DIV/0! | R318: 0.49018383 | S318: =Q318-R318 -> #DIV/0! | U318: =(T318-P318)/T318 -> #DIV/0! | V318: 111001019 | W318: =_xlfn.XLOOKUP(PRECIFICAÇÃO[[#This Row],[GM9]],Markup!A:A,Markup!B:B) -> PROCESSADOR DE ALIMENTOS
A319: BEMOL 72 | B319: =_xlfn.XLOOKUP(A319,'Base de Dados'!D:D,'Base de Dados'!B:B) -> TIMBRO SWISS SA | C319: =_xlfn.XLOOKUP(PRECIFICAÇÃO[[#This Row],[INVOICE]],'Base de Dados'!D:D,'Base de Dados'!X:X) -> EM PRODUÇÃO | D319: 373758 | E319: SUPORTE DE TV BAUMON YN-LED002 PT | F319: 9000 | G319: 2.2 | H319: 5.1176 | I319: =H319*G319 -> 11.25872 | J319: =I319*F319 -> 101328.48 | K319: =J319/_xlfn.XLOOKUP(A319,'Base de Dados'!D:D,'Base de Dados'!M:M) -> #DIV/0! | L319: =K319*_xlfn.XLOOKUP(A319,'Base de Dados'!D:D,'Base de Dados'!N:N) -> #DIV/0! | M319: =J319+L319 -> #DIV/0! | N319: =M319/F319 -> #DIV/0! | O319: =R319-0.1 -> 0.37093718 | P319: =ROUND(N319/O319,0) -> #DIV/0! | Q319: =(P319-N319)/P319 -> #DIV/0! | R319: 0.47093718 | S319: =Q319-R319 -> #DIV/0! | U319: =(T319-P319)/T319 -> #DIV/0! | V319: 130001013 | W319: =_xlfn.XLOOKUP(PRECIFICAÇÃO[[#This Row],[GM9]],Markup!A:A,Markup!B:B) -> SUPORTES
A320: BEMOL 72 | B320: =_xlfn.XLOOKUP(A320,'Base de Dados'!D:D,'Base de Dados'!B:B) -> TIMBRO SWISS SA | C320: =_xlfn.XLOOKUP(PRECIFICAÇÃO[[#This Row],[INVOICE]],'Base de Dados'!D:D,'Base de Dados'!X:X) -> EM PRODUÇÃO | D320: 370451 | E320: SUPORTE DE TV BAUMON BLISTER LCD800 P | F320: 5000 | G320: 1.38 | H320: 5.1176 | I320: =H320*G320 -> 7.062288 | J320: =I320*F320 -> 35311.44 | K320: =J320/_xlfn.XLOOKUP(A320,'Base de Dados'!D:D,'Base de Dados'!M:M) -> #DIV/0! | L320: =K320*_xlfn.XLOOKUP(A320,'Base de Dados'!D:D,'Base de Dados'!N:N) -> #DIV/0! | M320: =J320+L320 -> #DIV/0! | N320: =M320/F320 -> #DIV/0! | O320: =R320-0.1 -> 0.37093718 | P320: =ROUND(N320/O320,0) -> #DIV/0! | Q320: =(P320-N320)/P320 -> #DIV/0! | R320: 0.47093718 | S320: =Q320-R320 -> #DIV/0! | U320: =(T320-P320)/T320 -> #DIV/0! | V320: 130001013 | W320: =_xlfn.XLOOKUP(PRECIFICAÇÃO[[#This Row],[GM9]],Markup!A:A,Markup!B:B) -> SUPORTES
A321: BEMOL 72 | B321: =_xlfn.XLOOKUP(A321,'Base de Dados'!D:D,'Base de Dados'!B:B) -> TIMBRO SWISS SA | C321: =_xlfn.XLOOKUP(PRECIFICAÇÃO[[#This Row],[INVOICE]],'Base de Dados'!D:D,'Base de Dados'!X:X) -> EM PRODUÇÃO | D321: 370452 | E321: SUPORTE DE TV BAUMON YN-109MF G | F321: 2000 | G321: 5.15 | H321: 5.1176 | I321: =H321*G321 -> 26.35564 | J321: =I321*F321 -> 52711.28 | K321: =J321/_xlfn.XLOOKUP(A321,'Base de Dados'!D:D,'Base de Dados'!M:M) -> #DIV/0! | L321: =K321*_xlfn.XLOOKUP(A321,'Base de Dados'!D:D,'Base de Dados'!N:N) -> #DIV/0! | M321: =J321+L321 -> #DIV/0! | N321: =M321/F321 -> #DIV/0! | O321: =R321-0.1 -> 0.37093718 | P321: =ROUND(N321/O321,0) -> #DIV/0! | Q321: =(P321-N321)/P321 -> #DIV/0! | R321: 0.47093718 | S321: =Q321-R321 -> #DIV/0! | U321: =(T321-P321)/T321 -> #DIV/0! | V321: 130001013 | W321: =_xlfn.XLOOKUP(PRECIFICAÇÃO[[#This Row],[GM9]],Markup!A:A,Markup!B:B) -> SUPORTES
A322: BEMOL 72 | B322: =_xlfn.XLOOKUP(A322,'Base de Dados'!D:D,'Base de Dados'!B:B) -> TIMBRO SWISS SA | C322: =_xlfn.XLOOKUP(PRECIFICAÇÃO[[#This Row],[INVOICE]],'Base de Dados'!D:D,'Base de Dados'!X:X) -> EM PRODUÇÃO | D322: 370453 | E322: SUP/ DE TV ARTICULADO BAUMON YN-927AT M | F322: 2004 | G322: 7.54 | H322: 5.1176 | I322: =H322*G322 -> 38.586704 | J322: =I322*F322 -> 77327.755 | K322: =J322/_xlfn.XLOOKUP(A322,'Base de Dados'!D:D,'Base de Dados'!M:M) -> #DIV/0! | L322: =K322*_xlfn.XLOOKUP(A322,'Base de Dados'!D:D,'Base de Dados'!N:N) -> #DIV/0! | M322: =J322+L322 -> #DIV/0! | N322: =M322/F322 -> #DIV/0! | O322: =R322-0.1 -> 0.37093718 | P322: =ROUND(N322/O322,0) -> #DIV/0! | Q322: =(P322-N322)/P322 -> #DIV/0! | R322: 0.47093718 | S322: =Q322-R322 -> #DIV/0! | U322: =(T322-P322)/T322 -> #DIV/0! | V322: 130001013 | W322: =_xlfn.XLOOKUP(PRECIFICAÇÃO[[#This Row],[GM9]],Markup!A:A,Markup!B:B) -> SUPORTES
A323: BEMOL 72 | B323: =_xlfn.XLOOKUP(A323,'Base de Dados'!D:D,'Base de Dados'!B:B) -> TIMBRO SWISS SA | C323: =_xlfn.XLOOKUP(PRECIFICAÇÃO[[#This Row],[INVOICE]],'Base de Dados'!D:D,'Base de Dados'!X:X) -> EM PRODUÇÃO | D323: 238700 | E323: SANDUICHEIRA BAUMON FS-8009C PT | F323: 3900 | G323: 5.69 | H323: 5.1176 | I323: =H323*G323 -> 29.119144 | J323: =I323*F323 -> 113564.66 | K323: =J323/_xlfn.XLOOKUP(A323,'Base de Dados'!D:D,'Base de Dados'!M:M) -> #DIV/0! | L323: =K323*_xlfn.XLOOKUP(A323,'Base de Dados'!D:D,'Base de Dados'!N:N) -> #DIV/0! | M323: =J323+L323 -> #DIV/0! | N323: =M323/F323 -> #DIV/0! | O323: =R323-0.1 -> 0.39291767 | P323: =ROUND(N323/O323,0) -> #DIV/0! | Q323: =(P323-N323)/P323 -> #DIV/0! | R323: 0.49291767 | S323: =Q323-R323 -> #DIV/0! | U323: =(T323-P323)/T323 -> #DIV/0! | V323: 111001020 | W323: =_xlfn.XLOOKUP(PRECIFICAÇÃO[[#This Row],[GM9]],Markup!A:A,Markup!B:B) -> SANDUICHEIRA
A324: INV-000261-26 | B324: =_xlfn.XLOOKUP(A324,'Base de Dados'!D:D,'Base de Dados'!B:B) -> ELOX TRANDING | C324: =_xlfn.XLOOKUP(PRECIFICAÇÃO[[#This Row],[INVOICE]],'Base de Dados'!D:D,'Base de Dados'!X:X) -> EM TRÂNSITO | D324: 382674 | E324: BAUMON PULSE B97A SPEAKER BOX | F324: 1400 | G324: 30.5 | H324: 5.1176 | I324: =H324*G324 -> 156.0868 | J324: =I324*F324 -> 218521.52 | K324: =J324/_xlfn.XLOOKUP(A324,'Base de Dados'!D:D,'Base de Dados'!M:M) -> #DIV/0! | L324: =K324*_xlfn.XLOOKUP(A324,'Base de Dados'!D:D,'Base de Dados'!N:N) -> #DIV/0! | M324: =J324+L324 -> #DIV/0! | N324: =M324/F324 -> #DIV/0! | O324: =R324-0.1 -> 0.30618864 | P324: =ROUND(N324/O324,0) -> #DIV/0! | Q324: =(P324-N324)/P324 -> #DIV/0! | R324: 0.40618864 | S324: =Q324-R324 -> #DIV/0! | U324: =(T324-P324)/T324 -> #DIV/0! | V324: 102001006 | W324: =_xlfn.XLOOKUP(PRECIFICAÇÃO[[#This Row],[GM9]],Markup!A:A,Markup!B:B) -> CAIXA ACÚSTICA
A325: INV-000273-26 | B325: =_xlfn.XLOOKUP(A325,'Base de Dados'!D:D,'Base de Dados'!B:B) -> ELOX TRANDING | C325: =_xlfn.XLOOKUP(PRECIFICAÇÃO[[#This Row],[INVOICE]],'Base de Dados'!D:D,'Base de Dados'!X:X) -> EM TRÂNSITO | D325: 382674 | E325: BAUMON PULSE B97A SPEAKER BOX | F325: 1427 | G325: 30.5 | H325: 5.1176 | I325: =H325*G325 -> 156.0868 | J325: =I325*F325 -> 222735.86 | K325: =J325/_xlfn.XLOOKUP(A325,'Base de Dados'!D:D,'Base de Dados'!M:M) -> #DIV/0! | L325: =K325*_xlfn.XLOOKUP(A325,'Base de Dados'!D:D,'Base de Dados'!N:N) -> #DIV/0! | M325: =J325+L325 -> #DIV/0! | N325: =M325/F325 -> #DIV/0! | O325: =R325-0.1 -> 0.30618864 | P325: =ROUND(N325/O325,0) -> #DIV/0! | Q325: =(P325-N325)/P325 -> #DIV/0! | R325: 0.40618864 | S325: =Q325-R325 -> #DIV/0! | U325: =(T325-P325)/T325 -> #DIV/0! | V325: 102001006 | W325: =_xlfn.XLOOKUP(PRECIFICAÇÃO[[#This Row],[GM9]],Markup!A:A,Markup!B:B) -> CAIXA ACÚSTICA
A326: INV-000276-26 | B326: =_xlfn.XLOOKUP(A326,'Base de Dados'!D:D,'Base de Dados'!B:B) -> ELOX TRANDING | C326: =_xlfn.XLOOKUP(PRECIFICAÇÃO[[#This Row],[INVOICE]],'Base de Dados'!D:D,'Base de Dados'!X:X) -> EM TRÂNSITO | D326: 372039 | E326: FREEZER BAUMON VERTICAL 180L BD180U BR | F326: 146 | G326: 106 | H326: 5.1176 | I326: =H326*G326 -> 542.4656 | J326: =I326*F326 -> 79199.978 | K326: =J326/_xlfn.XLOOKUP(A326,'Base de Dados'!D:D,'Base de Dados'!M:M) -> #DIV/0! | L326: =K326*_xlfn.XLOOKUP(A326,'Base de Dados'!D:D,'Base de Dados'!N:N) -> #DIV/0! | M326: =J326+L326 -> #DIV/0! | N326: =M326/F326 -> #DIV/0! | O326: =R326-0.1 -> 0.36421504 | P326: =ROUND(N326/O326,0) -> #DIV/0! | Q326: =(P326-N326)/P326 -> #DIV/0! | R326: 0.46421504 | S326: =Q326-R326 -> #DIV/0! | U326: =(T326-P326)/T326 -> #DIV/0! | V326: 117005002 | W326: =_xlfn.XLOOKUP(PRECIFICAÇÃO[[#This Row],[GM9]],Markup!A:A,Markup!B:B) -> FREEZER VERTICAL
A327: INV-000276-26 | B327: =_xlfn.XLOOKUP(A327,'Base de Dados'!D:D,'Base de Dados'!B:B) -> ELOX TRANDING | C327: =_xlfn.XLOOKUP(PRECIFICAÇÃO[[#This Row],[INVOICE]],'Base de Dados'!D:D,'Base de Dados'!X:X) -> EM TRÂNSITO | D327: 372040 | E327: FREEZER BAUMON HORIZONTAL 100L BD100Q BR | F327: 263 | G327: 64 | H327: 5.1176 | I327: =H327*G327 -> 327.5264 | J327: =I327*F327 -> 86139.443 | K327: =J327/_xlfn.XLOOKUP(A327,'Base de Dados'!D:D,'Base de Dados'!M:M) -> #DIV/0! | L327: =K327*_xlfn.XLOOKUP(A327,'Base de Dados'!D:D,'Base de Dados'!N:N) -> #DIV/0! | M327: =J327+L327 -> #DIV/0! | N327: =M327/F327 -> #DIV/0! | O327: =R327-0.1 -> 0.34663446 | P327: =ROUND(N327/O327,0) -> #DIV/0! | Q327: =(P327-N327)/P327 -> #DIV/0! | R327: 0.44663446 | S327: =Q327-R327 -> #DIV/0! | U327: =(T327-P327)/T327 -> #DIV/0! | V327: 117005001 | W327: =_xlfn.XLOOKUP(PRECIFICAÇÃO[[#This Row],[GM9]],Markup!A:A,Markup!B:B) -> FREEZER HORIZONTAL
... A352: PI-BAUMON-032026 | B352: =_xlfn.XLOOKUP(A352,'Base de Dados'!D:D,'Base de Dados'!B:B) -> TECHFRIO (BE JAY) | C352: =_xlfn.XLOOKUP(PRECIFICAÇÃO[[#This Row],[INVOICE]],'Base de Dados'!D:D,'Base de Dados'!X:X) -> EM PRODUÇÃO | D352: 391223 | E352: SPLIT 32000 BAUMON INV 220V BR | F352: 270 | G352: 433.06 | H352: 5.0894 | I352: =H352*G352 -> 2204.0156 | J352: =I352*F352 -> 595084.2 | K352: =J352/_xlfn.XLOOKUP(A352,'Base de Dados'!D:D,'Base de Dados'!M:M) -> #DIV/0! | L352: =K352*_xlfn.XLOOKUP(A352,'Base de Dados'!D:D,'Base de Dados'!N:N) -> #DIV/0! | M352: =J352+L352 -> #DIV/0! | N352: =M352/F352 -> #DIV/0! | O352: =R352-0.1 -> 0.26561336 | P352: =ROUND(N352/O352,0) -> #DIV/0! | Q352: =(P352-N352)/P352 -> #DIV/0! | R352: 0.36561336 | S352: =Q352-R352 -> #DIV/0! | U352: =(T352-P352)/T352 -> #DIV/0! | V352: 117008009 | W352: =_xlfn.XLOOKUP(PRECIFICAÇÃO[[#This Row],[GM9]],Markup!A:A,Markup!B:B) -> SPLIT INVERTER DE 18001 À 30000 BTUS
A353: BEMOL 62 | B353: =_xlfn.XLOOKUP(A353,'Base de Dados'!D:D,'Base de Dados'!B:B) -> TIMBRO SWISS SA | C353: =_xlfn.XLOOKUP(PRECIFICAÇÃO[[#This Row],[INVOICE]],'Base de Dados'!D:D,'Base de Dados'!X:X) -> EM TRÂNSITO | D353: 269686 | E353: POTE BAUMON HERMÉT 630ML R170-2FULL AZ | F353: 1512 | G353: 1.73 | H353: 5.0894 | I353: =H353*G353 -> 8.804662 | J353: =I353*F353 -> 13312.649 | K353: =J353/_xlfn.XLOOKUP(A353,'Base de Dados'!D:D,'Base de Dados'!M:M) -> #DIV/0! | L353: =K353*_xlfn.XLOOKUP(A353,'Base de Dados'!D:D,'Base de Dados'!N:N) -> #DIV/0! | M353: =J353+L353 -> #DIV/0! | N353: =M353/F353 -> #DIV/0! | O353: =R353-0.1 -> -0.1 | P353: =ROUND(N353/O353,0) -> #DIV/0! | Q353: =(P353-N353)/P353 -> #DIV/0! | S353: =Q353-R353 -> #DIV/0! | U353: =(T353-P353)/T353 -> #DIV/0! | V353: 127001014 | W353: =_xlfn.XLOOKUP(PRECIFICAÇÃO[[#This Row],[GM9]],Markup!A:A,Markup!B:B) -> POTES
A354: BEMOL 62 | B354: =_xlfn.XLOOKUP(A354,'Base de Dados'!D:D,'Base de Dados'!B:B) -> TIMBRO SWISS SA | C354: =_xlfn.XLOOKUP(PRECIFICAÇÃO[[#This Row],[INVOICE]],'Base de Dados'!D:D,'Base de Dados'!X:X) -> EM TRÂNSITO | D354: 267936 | E354: POTE BAUMON HERMÉT 750ML QD C/T S150-2 | F354: 2304 | G354: 1.34 | H354: 5.0894 | I354: =H354*G354 -> 6.819796 | J354: =I354*F354 -> 15712.81 | K354: =J354/_xlfn.XLOOKUP(A354,'Base de Dados'!D:D,'Base de Dados'!M:M) -> #DIV/0! | L354: =K354*_xlfn.XLOOKUP(A354,'Base de Dados'!D:D,'Base de Dados'!N:N) -> #DIV/0! | M354: =J354+L354 -> #DIV/0! | N354: =M354/F354 -> #DIV/0! | O354: =R354-0.1 -> -0.1 | P354: =ROUND(N354/O354,0) -> #DIV/0! | Q354: =(P354-N354)/P354 -> #DIV/0! | S354: =Q354-R354 -> #DIV/0! | U354: =(T354-P354)/T354 -> #DIV/0! | V354: 127001014 | W354: =_xlfn.XLOOKUP(PRECIFICAÇÃO[[#This Row],[GM9]],Markup!A:A,Markup!B:B) -> POTES
A355: BEMOL 62 | B355: =_xlfn.XLOOKUP(A355,'Base de Dados'!D:D,'Base de Dados'!B:B) -> TIMBRO SWISS SA | C355: =_xlfn.XLOOKUP(PRECIFICAÇÃO[[#This Row],[INVOICE]],'Base de Dados'!D:D,'Base de Dados'!X:X) -> EM TRÂNSITO | D355: 267943 | E355: CAÇAROLA BAUMON 1500ML VIDRO GC-1500 | F355: 1992 | G355: 1.95 | H355: 5.0894 | I355: =H355*G355 -> 9.92433 | J355: =I355*F355 -> 19769.265 | K355: =J355/_xlfn.XLOOKUP(A355,'Base de Dados'!D:D,'Base de Dados'!M:M) -> #DIV/0! | L355: =K355*_xlfn.XLOOKUP(A355,'Base de Dados'!D:D,'Base de Dados'!N:N) -> #DIV/0! | M355: =J355+L355 -> #DIV/0! | N355: =M355/F355 -> #DIV/0! | O355: =R355-0.1 -> -0.1 | P355: =ROUND(N355/O355,0) -> #DIV/0! | Q355: =(P355-N355)/P355 -> #DIV/0! | S355: =Q355-R355 -> #DIV/0! | U355: =(T355-P355)/T355 -> #DIV/0! | V355: 127001006 | W355: =_xlfn.XLOOKUP(PRECIFICAÇÃO[[#This Row],[GM9]],Markup!A:A,Markup!B:B) -> CAÇAROLA
A356: BEMOL 62 | B356: =_xlfn.XLOOKUP(A356,'Base de Dados'!D:D,'Base de Dados'!B:B) -> TIMBRO SWISS SA | C356: =_xlfn.XLOOKUP(PRECIFICAÇÃO[[#This Row],[INVOICE]],'Base de Dados'!D:D,'Base de Dados'!X:X) -> EM TRÂNSITO | D356: 267939 | E356: ASSAD BAUMON RET 1600ML C/T VDR GB1600 | F356: 1512 | G356: 2.1 | H356: 5.0894 | I356: =H356*G356 -> 10.68774 | J356: =I356*F356 -> 16159.863 | K356: =J356/_xlfn.XLOOKUP(A356,'Base de Dados'!D:D,'Base de Dados'!M:M) -> #DIV/0! | L356: =K356*_xlfn.XLOOKUP(A356,'Base de Dados'!D:D,'Base de Dados'!N:N) -> #DIV/0! | M356: =J356+L356 -> #DIV/0! | N356: =M356/F356 -> #DIV/0! | O356: =R356-0.1 -> -0.1 | P356: =ROUND(N356/O356,0) -> #DIV/0! | Q356: =(P356-N356)/P356 -> #DIV/0! | S356: =Q356-R356 -> #DIV/0! | U356: =(T356-P356)/T356 -> #DIV/0! | V356: 127001002 | W356: =_xlfn.XLOOKUP(PRECIFICAÇÃO[[#This Row],[GM9]],Markup!A:A,Markup!B:B) -> ASSADEIRAS/FÔRMAS
A357: BEMOL 62 | B357: =_xlfn.XLOOKUP(A357,'Base de Dados'!D:D,'Base de Dados'!B:B) -> TIMBRO SWISS SA | C357: =_xlfn.XLOOKUP(PRECIFICAÇÃO[[#This Row],[INVOICE]],'Base de Dados'!D:D,'Base de Dados'!X:X) -> EM TRÂNSITO | D357: 267940 | E357: ASSAD BAUMON VIDRO OVAL 3000ML OVAL-3000 | F357: 1500 | G357: 2.21 | H357: 5.0894 | I357: =H357*G357 -> 11.247574 | J357: =I357*F357 -> 16871.361 | K357: =J357/_xlfn.XLOOKUP(A357,'Base de Dados'!D:D,'Base de Dados'!M:M) -> #DIV/0! | L357: =K357*_xlfn.XLOOKUP(A357,'Base de Dados'!D:D,'Base de Dados'!N:N) -> #DIV/0! | M357: =J357+L357 -> #DIV/0! | N357: =M357/F357 -> #DIV/0! | O357: =R357-0.1 -> -0.1 | P357: =ROUND(N357/O357,0) -> #DIV/0! | Q357: =(P357-N357)/P357 -> #DIV/0! | S357: =Q357-R357 -> #DIV/0! | U357: =(T357-P357)/T357 -> #DIV/0! | V357: 127001002 | W357: =_xlfn.XLOOKUP(PRECIFICAÇÃO[[#This Row],[GM9]],Markup!A:A,Markup!B:B) -> ASSADEIRAS/FÔRMAS
A358: BEMOL 62 | B358: =_xlfn.XLOOKUP(A358,'Base de Dados'!D:D,'Base de Dados'!B:B) -> TIMBRO SWISS SA | C358: =_xlfn.XLOOKUP(PRECIFICAÇÃO[[#This Row],[INVOICE]],'Base de Dados'!D:D,'Base de Dados'!X:X) -> EM TRÂNSITO | D358: 267938 | E358: POTE BAUMON HERMÉT 1430ML RET C/T R220-3 | F358: 1572 | G358: 2.15 | H358: 5.0894 | I358: =H358*G358 -> 10.94221 | J358: =I358*F358 -> 17201.154 | K358: =J358/_xlfn.XLOOKUP(A358,'Base de Dados'!D:D,'Base de Dados'!M:M) -> #DIV/0! | L358: =K358*_xlfn.XLOOKUP(A358,'Base de Dados'!D:D,'Base de Dados'!N:N) -> #DIV/0! | M358: =J358+L358 -> #DIV/0! | N358: =M358/F358 -> #DIV/0! | O358: =R358-0.1 -> -0.1 | P358: =ROUND(N358/O358,0) -> #DIV/0! | Q358: =(P358-N358)/P358 -> #DIV/0! | S358: =Q358-R358 -> #DIV/0! | U358: =(T358-P358)/T358 -> #DIV/0! | V358: 127001014 | W358: =_xlfn.XLOOKUP(PRECIFICAÇÃO[[#This Row],[GM9]],Markup!A:A,Markup!B:B) -> POTES
A359: BEMOL 62 | B359: =_xlfn.XLOOKUP(A359,'Base de Dados'!D:D,'Base de Dados'!B:B) -> TIMBRO SWISS SA | C359: =_xlfn.XLOOKUP(PRECIFICAÇÃO[[#This Row],[INVOICE]],'Base de Dados'!D:D,'Base de Dados'!X:X) -> EM TRÂNSITO | D359: 267932 | E359: POTE BAUMON HERMÉT 1040ML C/T R195-2FULL | F359: 1872 | G359: 2.38 | H359: 5.0894 | I359: =H359*G359 -> 12.112772 | J359: =I359*F359 -> 22675.109 | K359: =J359/_xlfn.XLOOKUP(A359,'Base de Dados'!D:D,'Base de Dados'!M:M) -> #DIV/0! | L359: =K359*_xlfn.XLOOKUP(A359,'Base de Dados'!D:D,'Base de Dados'!N:N) -> #DIV/0! | M359: =J359+L359 -> #DIV/0! | N359: =M359/F359 -> #DIV/0! | O359: =R359-0.1 -> -0.1 | P359: =ROUND(N359/O359,0) -> #DIV/0! | Q359: =(P359-N359)/P359 -> #DIV/0! | S359: =Q359-R359 -> #DIV/0! | U359: =(T359-P359)/T359 -> #DIV/0! | V359: 127001014 | W359: =_xlfn.XLOOKUP(PRECIFICAÇÃO[[#This Row],[GM9]],Markup!A:A,Markup!B:B) -> POTES
...

Sheet Markup
A1: Grupo | B1: Descrição do Grupo | C1: Mark-up MAO
A2: 101001001 | B2: ACESSÓRIOS INFANTIS | C2: 0.47032477
A3: 101001002 | B3: ANDAJÁ | C3: 0.45176018
A4: 101001003 | B4: ASSENTO P/ AUTO | C4: 0.45176018
A5: 101001004 | B5: BANHEIRA | C5: 0.45391454
A6: 101001005 | B6: BEBÊ-CONFORTO | C6: 0.44950634
A7: 101001006 | B7: CADEIRÃO | C7: 0.45310314
A8: 101001007 | B8: CARRINHO DE BEBÊ | C8: 0.44169724
A9: 101001008 | B9: CERCADO | C9: 0.44885696
A10: 101001010 | B10: BABÁ ELETRÔNICA | C10: 0.56535851
A11: 102001002 | B11: ALTO-FALANTES | C11: 0.56235845
A12: 102001004 | B12: CD PLAYER P/AUTO | C12: 0.57350834
A13: 102001005 | B13: CAIXA DE SOM ÁUDIO | C13: 0.53091321
... A27: 104001001 | B27: BICICLETA ADULTO MASCULINO | C27: 0.53078379
A28: 104001002 | B28: BICICLETA ADULTO FEMININO | C28: 0.54297121 | F28: Base de Dados
A29: 104001003 | B29: BICICLETA INFANTIL/CROSS | C29: 0.55110035
A30: 104001004 | B30: BICICLETA JUVENIL/MOTONETA | C30: 0.53826745
A31: 104001005 | B31: ACESSÓRIOS PARA BICICLETA | C31: 0.52865553
A32: 105001001 | B32: ACESSÓRIOS BRINQUEDO | C32: 0.42267942
A33: 105001002 | B33: PISTAS | C33: 0.41647921
A34: 105001003 | B34: BONECOS | C34: 0.40834293
A35: 105001004 | B35: BONECAS | C35: 0.45424368
A36: 105001005 | B36: CARRINHOS & CIA | C36: 0.44412892
A37: 105001006 | B37: CARRINHOS & CIA C/ CONTROLE REMOTO | C37: 0.42451602
A38: 105001007 | B38: CONJUNTO/PLAYSET MENINOS | C38: 0.41983075
A39: 105001008 | B39: CONJUNTO/PLAYSET MENINAS | C39: 0.49088069
A40: 105001009 | B40: EDUCATIVO/PRÉ-ESCOLAR | C40: 0.41453448
... A630: 120004006 | B630: KIT FORNO DE AÇO | C630: 0.38337042
